Workbook

Sheet Assumptions
A1: Self-Serve Dependency Score - assumptions (recommended method)
A3: Weights
A4: Broker reliance weight | B4: 0.5
A5: App activity weight | B5: 0.3
A6: Offer activity weight | B6: 0.2
A8: Gate: broker reliance % at or below this = not broker-led (score 0) | B8: 20
A9: High Dependency: score >= | B9: 70
A10: Medium Dependency: score >= | B10: 40
A12: Broker reliance bands (pct)
A13: <= this -> 0 | B13: 20
A14: < this -> 25 | B14: 40
A15: < this -> 50 | B15: 60
A16: < this -> 75 (else 100) | B16: 80
A18: App active days bands
A19: > this -> 0 | B19: 30
A20: >= this -> 25 | B20: 20
A21: >= this -> 50 | B21: 10
A22: >= this -> 75 (else 100) | B22: 5
A24: Make-an-offer bands
A25: >= this -> 0 | B25: 5
A26: >= this -> 25 | B26: 3
A27: equals this -> 50 | B27: 2
A28: equals this -> 75 (0 offers -> 100) | B28: 1
A30: Low-confidence flag: orders_6m <= | B30: 2
A32: Source: weights and initial bands supplied by Zain (case-study brief). Changes vs brief: broker 0-band is <=20% (was <20%) and the broker gate; both explained in the report.
A33: Commercial lens (stage 2)
A34: Higher-value threshold: 6m GMV >= (£) | B34: 2000
A35: Key-account threshold: 6m GMV >= (£) | B35: 10000
A36: Momentum band: Growing if H2 >= H1 x (1 + this); Declining if H2 < H1 x (1 - this); else Stable | B36: 0.2
A38: Segmentation (stage 3)
A39: Phase 1 cohort rule: minimum orders_6m | B39: 3
A40: Phase 1 cohort rule: minimum self_serve_orders | B40: 2
A41: Broker % inconsistency flag: gap vs order counts greater than (pts) | B41: 10
A42: Critical data-quality blocker (Phase 1 cohort) = account_status "Duplicate". All other flags are warnings and never change a segment.
A43: February completeness is UNCONFIRMED. H2 (Dec-Feb) momentum assumes February is a full month.
A45: Stage 3.1 guardrails (context flags - never change a segment)
A46: Borderline momentum: H2 vs H1 within this many points of +20% or -20% | B46: 0.05
A47: Lifecycle: New Customer if tenure_months <= (only for H2 Active / No H1 GMV accounts) | B47: 6
A48: Lapse context: One-Off / Insufficient History if orders_6m <= | B48: 2
A49: Lapse context: One-Off / Insufficient History if months with GMV <= | B49: 1
A50: February sensitivity: same H1 (Sep-Nov) vs Dec-Jan only, compared as monthly averages (H1/3 vs (Dec+Jan)/2), same +/-20% rule. Sensitive = the momentum group changes (Growing/Stable = one group).
A51: Material broker inconsistency: provided vs implied (manual / (manual+self-serve)) crosses the 20% gate, changes the broker sub-score band, or changes the Dependency Tier.
A52: Key-account sign-off: Migration Candidate AND Key. Human/AM approval required before any migration activity.
A53: Phase 1 rollout status: Not Eligible if Phase 1 criteria not met; Manual Review if met but material broker inconsistency, borderline momentum, February-sensitive, or (Stage 5) lumpy buyer cadence (B83/B84 not met); otherwise Ready.
A56: Stage 4A feature analysis (analysis definitions - not yet NBA rules)
A57: Self-serve milestone M1: app_active_days_6m >= | B57: 10
A58: Self-serve milestone M2: pdp_views_6m >= | B58: 50
A59: Self-serve milestone M3: make_an_offer_6m >= | B59: 3
A60: Archetype: "engaged" if app_active_days_6m >= | B60: 20
A61: Archetype: "engaged" if pdp_views_6m >= | B61: 200
A62: Archetype: independent browser-buyer needs offers >= | B62: 3
A63: Archetype: independent browser-buyer needs orders_6m >= | B63: 3
A64: Rising Tail watchlist: gmv_total_6m >= (£) | B64: 1000
A65: Rising Tail watchlist: orders_6m >= | B65: 3
A66: Rising Tail watchlist: app_active_days_6m >= (or offers rule) | B66: 20
A67: Rising Tail watchlist: make_an_offer_6m >= (or app rule) | B67: 3
A68: Rising Tail also requires: Low dependency, Tail, and Growing/Stable momentum OR H2 Active / No H1 GMV with >= 2 months of GMV. Context flag only - primary Action Segment unchanged.
A70: Stage 4B NBA engine (rule parameters)
A71: Discovery-to-Offer: pdp_views_6m >= | B71: 50
A72: Discovery-to-Offer: make_an_offer_6m < | B72: 3
A73: Reinforce: minimum months with GMV | B73: 3
A74: Long-tail Discovery-to-Offer: minimum orders_6m | B74: 2
A75: Warning H2_SINGLE_MONTH_SPIKE: largest H2 month share >= | B75: 0.8
A76: Phase 1 (90 days) Progressing: PDP views >= | B76: 15
A77: Phase 1 (90 days) Progressing: app active days >= | B77: 5
A78: Phase 1 (90 days) Capability: PDP views >= | B78: 25
A79: Phase 1 (90 days) Capability: app active days >= | B79: 6
A80: Phase 1 (90 days) supportive: offers >= | B80: 2
A81: GMV guardrail (regular buyers): At Risk if GMV to date < this share of pro-rated expected GMV | B81: 0.7
A82: GMV guardrail: first check on day | B82: 45
... A85: Phase 1 monitoring window (days) | B85: 90
A86: recent_activity_status: Recently Active if Jan or Feb GMV > 0; otherwise No Meaningful History if orders <= B48 or months with GMV <= B49; otherwise Recent Inactivity. Zero February alone is context only.
A88: Stage 5 execution (pipeline code: fleek_gtm_engine/). Phase 1 refinement: an otherwise Ready account with buyer cadence Lumpy (B83/B84 not met) goes to Manual Review.

Sheet Execution Queue
A1: Execution Queue - RUN001 baseline (300 accounts). Generated by fleek_engine; drafts are NOT sent. Sorted by priority, value tier, GMV.
A3: account_id | B3: attention_priority | C3: value_tier | D3: gmv_total_6m | E3: action_segment | F3: primary_nba | G3: nba_reason_code | H3: execution_status | I3: action_state | J3: owner_role | K3: named_owner_required | L3: notify_am_before_send | M3: playbook_id | N3: recommended_channel | O3: first_action | P3: follow_up_days | Q3: success_condition | R3: stop_condition | S3: escalation_condition | T3: guardrail_codes | U3: draft_status | V3: message_template_id | W3: draft_customer_message | X3: internal_task_brief | Y3: secondary_test | Z3: secondary_test_arm | AA3: secondary_test_draft | AB3: nurture_subcontext | AC3: recent_activity_status | AD3: lifecycle_context | AE3: rising_tail_watchlist | AF3: phase1_rollout_status | AG3: buyer_cadence | AH3: migration_progress_status | AI3: next_rerun_behaviour | AJ3: change_type | AK3: change_flags | AL3: generated_action
A4: ACC-005 | B4: P0 | C4: Key | D4: 24555 | E4: 2. Protect / Retain First | F4: Retention Conversation | G4: DECLINING_KEY_CORE | H4: HOLD — Critical Data Issue | I4: On Hold | J4: Portfolio Lead | K4: =FALSE() -> FALSE | L4: =FALSE() -> FALSE | M4: PB01_RETENTION | N4: Personal email from AM, then call | O4: Portfolio Lead resolves the Duplicate status; no contact until cleared. | P4: 7 | Q4: Root cause logged and next-90-day GMV back to at least the Sep-Nov (H1) level, or the decline arrested. | R4: Customer confirms a planned pause/seasonal gap (log cadence), or no response after 2 attempts (escalate). | S4: No response after 2 attempts, or Key account with further decline -> Portfolio Lead. | T4: CRITICAL_DATA_BLOCKER | U4: Withheld: account on HOLD (critical data issue) | X4: WHY NOW: Commercially important, broker-led spend is falling. WHAT WE KNOW: - Key, Broker-Reliant, Account Managed; £24,555 6m GMV; Retailer, United Kingdom; tenure 41 months. - Momentum: Declining (Sep-Nov £17,529 -> Dec-Feb £7,025); Recently Active (last GMV month: February); 14 orders over 5 month(s). - Dependency: Medium (broker reliance 50%; 7 AM-placed / 7 self-serve orders). - Engagement: 10 product views, 8 app days, 1 offer(s), 100 Fleek chats, 0 video requests; basket Mixed. - Warnings: CRITICAL_DATA_BLOCKER. WHAT TO DO: Resolve the Duplicate status (find/merge the matching record, confirm GMV is not double-counted) before any contact. Underlying action once cleared: Retention Conversation. WHAT NOT TO DO: No outbound communication while on HOLD. SUCCESS: Root cause logged and next-90-day GMV back to at least the Sep-Nov (H1) level, or the decline arrested. | AC4: Recently Active | AD4: Existing Customer | AE4: =FALSE() -> FALSE | AF4: Not Eligible | AG4: Regular | AH4: N/A | AI4: Stay in playbook while momentum is Declining; exit when momentum is Stable/Growing for a full run; if the account lapses, NBA moves to Verify/Win-Back. | AJ4: BASELINE | AK4: BASELINE | AL4: 5b28ca9bd14c
A5: ACC-002 | B5: P1 | C5: Key | D5: 70650 | E5: 3. Win-Back / Verify | F5: Verify Demand / Win-Back | G5: LAPSED_THIN_HISTORY | H5: Ready — Human | I5: Draft Ready | J5: Account Manager | K5: =FALSE() -> FALSE | L5: =FALSE() -> FALSE | M5: PB02_VERIFY_WINBACK | N5: Personal email from AM, then call | O5: Send cadence check-in (verify, don't assume churn). | P5: 14 | Q5: Cadence recorded and account reclassified, or a new order within 90 days (60 days for recent-inactivity checks). | R5: Customer confirms infrequent/seasonal buying (set a reminder for their window) or confirms churn (log reason). | S5: Key account with no response after 2 attempts -> Portfolio Lead. | T5: MATERIAL_BROKER_INCONSISTENCY; LOW_CONFIDENCE | U5: Draft ready (not sent) | V5: VERIFY_CADENCE | W5: Hi {first_name}, Thanks for your previous orders with Fleek. I wanted to check how you usually plan your stock buying (seasonal, project by project, or ongoing) so we can get in touch at the right moments rather than too often. Happy to talk on a quick call, or just reply here with what works for you. Best, {sender_name} | X5: WHY NOW: Apparent lapse rests on 1-2 orders or one buying month; cadence is unknown. WHAT WE KNOW: - Key, Broker-Reliant, Account Managed; £70,650 6m GMV; Reseller, United States; tenure 10 months. - Momentum: Lapsed; No Meaningful History (last GMV month: October); 2 orders over 2 month(s). - Dependency: High (broker reliance 70%; 1 AM-placed / 1 self-serve orders). - Engagement: 6 product views, 2 app days, 2 offer(s), 12 Fleek chats, 0 video requests; basket Handpick-only. - Warnings: MATERIAL_BROKER_INCONSISTENCY; LOW_CONFIDENCE. WHAT TO DO: Do not assume churn. Verify expected purchase frequency first, then set the next contact window. WHAT NOT TO DO: Do not treat as churn or run a discount-led win-back. SUCCESS: Cadence recorded and account reclassified, or a new order within 90 days (60 days for recent-inactivity checks). | AC5: No Meaningful History | AD5: Existing Customer | AE5: =FALSE() -> FALSE | AF5: Not Eligible | AG5: Lumpy | AH5: N/A | AI5: If an order appears, the account re-segments automatically; if confirmed seasonal, suppress re-contact until the stated window. | AJ5: BASELINE | AK5: BASELINE | AL5: ad531f2937d6
A6: ACC-008 | B6: P1 | C6: Key | D6: 19265 | E6: 2. Protect / Retain First | F6: Retention Conversation | G6: DECLINING_KEY_CORE | H6: Ready — Human | I6: Draft Ready | J6: Account Manager | K6: =FALSE() -> FALSE | L6: =FALSE() -> FALSE | M6: PB01_RETENTION | N6: Personal email from AM, then call | O6: Read brief; send outreach to book a review call. | P6: 7 | Q6: Root cause logged and next-90-day GMV back to at least the Sep-Nov (H1) level, or the decline arrested. | R6: Customer confirms a planned pause/seasonal gap (log cadence), or no response after 2 attempts (escalate). | S6: No response after 2 attempts, or Key account with further decline -> Portfolio Lead. | T6: H2_SINGLE_MONTH_SPIKE | U6: Draft ready (not sent) | V6: RET_AM | W6: Hi {first_name}, I'd like to set up a short call to review how sourcing through Fleek is working for you at the moment and what you're planning to buy over the next few months. It will help me make sure the stock I source for you (bundles and handpicked stock) is the right fit. Would sometime later this week or early next week suit you? Best, {sender_name} | X6: WHY NOW: Commercially important, broker-led spend is falling. WHAT WE KNOW: - Key, Broker-Reliant, Account Managed; £19,265 6m GMV; Retailer, Sweden; tenure 15 months. - Momentum: Declining (Sep-Nov £12,458 -> Dec-Feb £6,808); Recently Active (last GMV month: February); 16 orders over 5 month(s). - Dependency: High (broker reliance 84%; 13 AM-placed / 3 self-serve orders). - Engagement: 13 product views, 4 app days, 0 offer(s), 29 Fleek chats, 1 video requests; basket Mixed. - Warnings: H2_SINGLE_MONTH_SPIKE. WHAT TO DO: Book a conversation. Explore stock availability, price, assortment fit, buying cadence, competitor/offline wholesaler use and operational friction. Agree a recovery plan. WHAT NOT TO DO: Do not reduce AM support or push migration; do not suggest the customer is at fault; do not propose chat/video/feature usage as the fix. SUCCESS: Root cause logged and next-90-day GMV back to at least the Sep-Nov (H1) level, or the decline arrested. | AC6: Recently Active | AD6: Existing Customer | AE6: =FALSE() -> FALSE | AF6: Not Eligible | AG6: Regular | AH6: N/A | AI6: Stay in playbook while momentum is Declining; exit when momentum is Stable/Growing for a full run; if the account lapses, NBA moves to Verify/Win-Back. | AJ6: BASELINE | AK6: BASELINE | AL6: bbf41110e504
A7: ACC-009 | B7: P1 | C7: Key | D7: 18652 | E7: 2. Protect / Retain First | F7: Retention Conversation | G7: DECLINING_KEY_CORE | H7: Ready — Human | I7: Draft Ready | J7: Account Manager | K7: =FALSE() -> FALSE | L7: =FALSE() -> FALSE | M7: PB01_RETENTION | N7: Personal email from AM, then call | O7: Read brief; send outreach to book a review call. | P7: 7 | Q7: Root cause logged and next-90-day GMV back to at least the Sep-Nov (H1) level, or the decline arrested. | R7: Customer confirms a planned pause/seasonal gap (log cadence), or no response after 2 attempts (escalate). | S7: No response after 2 attempts, or Key account with further decline -> Portfolio Lead. | U7: Draft ready (not sent) | V7: RET_AM | W7: Hi {first_name}, I'd like to set up a short call to review how sourcing through Fleek is working for you at the moment and what you're planning to buy over the next few months. It will help me make sure the stock I source for you (bundles and handpicked stock) is the right fit. Would sometime later this week or early next week suit you? Best, {sender_name} | X7: WHY NOW: Commercially important, broker-led spend is falling. WHAT WE KNOW: - Key, Broker-Reliant, Account Managed; £18,652 6m GMV; Reseller, United Kingdom; tenure 8 months. - Momentum: Declining (Sep-Nov £12,807 -> Dec-Feb £5,845); Recently Active (last GMV month: February); 35 orders over 6 month(s). - Dependency: High (broker reliance 68%; 24 AM-placed / 11 self-serve orders). - Engagement: 2 product views, 1 app days, 1 offer(s), 30 Fleek chats, 0 video requests; basket Mixed. WHAT TO DO: Book a conversation. Explore stock availability, price, assortment fit, buying cadence, competitor/offline wholesaler use and operational friction. Agree a recovery plan. WHAT NOT TO DO: Do not reduce AM support or push migration; do not suggest the customer is at fault; do not propose chat/video/feature usage as the fix. SUCCESS: Root cause logged and next-90-day GMV back to at least the Sep-Nov (H1) level, or the decline arrested. | AC7: Recently Active | AD7: Existing Customer | AE7: =FALSE() -> FALSE | AF7: Not Eligible | AG7: Regular | AH7: N/A | AI7: Stay in playbook while momentum is Declining; exit when momentum is Stable/Growing for a full run; if the account lapses, NBA moves to Verify/Win-Back. | AJ7: BASELINE | AK7: BASELINE | AL7: 14b26d9cbee4
A8: ACC-010 | B8: P1 | C8: Key | D8: 17026 | E8: 2. Protect / Retain First | F8: Retention Conversation | G8: DECLINING_KEY_CORE | H8: Ready — Human | I8: Draft Ready | J8: Account Manager | K8: =FALSE() -> FALSE | L8: =FALSE() -> FALSE | M8: PB01_RETENTION | N8: Personal email from AM, then call | O8: Read brief; send outreach to book a review call. | P8: 7 | Q8: Root cause logged and next-90-day GMV back to at least the Sep-Nov (H1) level, or the decline arrested. | R8: Customer confirms a planned pause/seasonal gap (log cadence), or no response after 2 attempts (escalate). | S8: No response after 2 attempts, or Key account with further decline -> Portfolio Lead. | U8: Draft ready (not sent) | V8: RET_AM | W8: Hi {first_name}, I'd like to set up a short call to review how sourcing through Fleek is working for you at the moment and what you're planning to buy over the next few months. It will help me make sure the stock I source for you (handpicked stock) is the right fit. Would sometime later this week or early next week suit you? Best, {sender_name} | X8: WHY NOW: Commercially important, broker-led spend is falling. WHAT WE KNOW: - Key, Broker-Reliant, Account Managed; £17,026 6m GMV; Reseller, Portugal; tenure 10 months. - Momentum: Declining (Sep-Nov £11,150 -> Dec-Feb £5,876); Recently Active (last GMV month: February); 13 orders over 6 month(s). - Dependency: High (broker reliance 69%; 9 AM-placed / 4 self-serve orders). - Engagement: 1 product views, 1 app days, 0 offer(s), 40 Fleek chats, 0 video requests; basket Handpick-only. WHAT TO DO: Book a conversation. Explore stock availability, price, assortment fit, buying cadence, competitor/offline wholesaler use and operational friction. Agree a recovery plan. WHAT NOT TO DO: Do not reduce AM support or push migration; do not suggest the customer is at fault; do not propose chat/video/feature usage as the fix. SUCCESS: Root cause logged and next-90-day GMV back to at least the Sep-Nov (H1) level, or the decline arrested. | AC8: Recently Active | AD8: Existing Customer | AE8: =FALSE() -> FALSE | AF8: Not Eligible | AG8: Regular | AH8: N/A | AI8: Stay in playbook while momentum is Declining; exit when momentum is Stable/Growing for a full run; if the account lapses, NBA moves to Verify/Win-Back. | AJ8: BASELINE | AK8: BASELINE | AL8: 4966e1678608
A9: ACC-013 | B9: P1 | C9: Key | D9: 14315 | E9: 2. Protect / Retain First | F9: Retention Conversation | G9: DECLINING_KEY_CORE | H9: Ready — Human | I9: Draft Ready | J9: Account Manager | K9: =FALSE() -> FALSE | L9: =FALSE() -> FALSE | M9: PB01_RETENTION | N9: Personal email from AM, then call | O9: Read brief; send outreach to book a review call. | P9: 7 | Q9: Root cause logged and next-90-day GMV back to at least the Sep-Nov (H1) level, or the decline arrested. | R9: Customer confirms a planned pause/seasonal gap (log cadence), or no response after 2 attempts (escalate). | S9: No response after 2 attempts, or Key account with further decline -> Portfolio Lead. | U9: Draft ready (not sent) | V9: RET_AM | W9: Hi {first_name}, I'd like to set up a short call to review how sourcing through Fleek is working for you at the moment and what you're planning to buy over the next few months. It will help me make sure the stock I source for you (bundles and handpicked stock) is the right fit. Would sometime later this week or early next week suit you? Best, {sender_name} | X9: WHY NOW: Commercially important, broker-led spend is falling. WHAT WE KNOW: - Key, Broker-Reliant, Account Managed; £14,315 6m GMV; Reseller, United Kingdom; tenure 17 months. - Momentum: Declining (Sep-Nov £9,966 -> Dec-Feb £4,350); Recently Active (last GMV month: February); 21 orders over 5 month(s). - Dependency: Medium (broker reliance 59%; 12 AM-placed / 9 self-serve orders). - Engagement: 5 product views, 8 app days, 1 offer(s), 36 Fleek chats, 0 video requests; basket Mixed. WHAT TO DO: Book a conversation. Explore stock availability, price, assortment fit, buying cadence, competitor/offline wholesaler use and operational friction. Agree a recovery plan. WHAT NOT TO DO: Do not reduce AM support or push migration; do not suggest the customer is at fault; do not propose chat/video/feature usage as the fix. SUCCESS: Root cause logged and next-90-day GMV back to at least the Sep-Nov (H1) level, or the decline arrested. | AC9: Recently Active | AD9: Existing Customer | AE9: =FALSE() -> FALSE | AF9: Not Eligible | AG9: Regular | AH9: N/A | AI9: Stay in playbook while momentum is Declining; exit when momentum is Stable/Growing for a full run; if the account lapses, NBA moves to Verify/Win-Back. | AJ9: BASELINE | AK9: BASELINE | AL9: d5ca9688e26f
A10: ACC-211 | B10: P1 | C10: Key | D10: 13412 | E10: 8. Retention / Reactivation | F10: Retention Conversation | G10: ENGAGED_BUT_SHRINKING | H10: Ready — Human | I10: Draft Ready | J10: Customer Success / Growth | K10: =TRUE() -> TRUE | L10: =FALSE() -> FALSE | M10: PB01_RETENTION | N10: Personal email, then call | O10: Read brief; send outreach to book a call. | P10: 7 | Q10: Root cause logged and next-90-day GMV back to at least the Sep-Nov (H1) level, or the decline arrested. | R10: Customer confirms a planned pause/seasonal gap (log cadence), or no response after 2 attempts (escalate). | S10: No response after 2 attempts, or Key account with further decline -> Portfolio Lead. | T10: H2_SINGLE_MONTH_SPIKE | U10: Draft ready (not sent) | V10: RET_CS | W10: Hi {first_name}, I'm part of the Fleek team and wanted to hear how the platform is working for your buying at the moment. Is anything making it harder to find or secure the stock you need? I'd value a short call to understand what would be most useful for you over the coming months. Would a quick call this week work? Best, {sender_name} | X10: WHY NOW: Heavily self-serving account whose spend is falling; product adoption is not the issue. WHAT WE KNOW: - Key, Self-Serve, Self Serve; £13,412 6m GMV; Reseller, France; tenure 5 months. - Momentum: Declining (Sep-Nov £9,034 -> Dec-Feb £4,378); Recent Inactivity (last GMV month: December); 15 orders over 3 month(s). - Dependency: Low (broker reliance 0%; 0 AM-placed / 15 self-serve orders). - Engagement: 6665 product views, 100 app days, 71 offer(s), 18 Fleek chats, 0 video requests; basket Mixed. - Warnings: H2_SINGLE_MONTH_SPIKE. WHAT TO DO: Book a conversation. The customer already uses the product heavily: explore stock availability, price, offer outcomes and competitor use. WHAT NOT TO DO: Do not send more product nudges - engagement is not the problem. SUCCESS: Root cause logged and next-90-day GMV back to at least the Sep-Nov (H1) level, or the decline arrested. | AC10: Recent Inactivity | AD10: Existing Customer | AE10: =FALSE() -> FALSE | AF10: Not Eligible | AG10: Regular | AH10: N/A | AI10: Stay in playbook while momentum is Declining; exit when momentum is Stable/Growing for a full run; if the account lapses, NBA moves to Verify/Win-Back. | AJ10: BASELINE | AK10: BASELINE | AL10: 1147923b913d
A11: ACC-014 | B11: P1 | C11: Key | D11: 11721 | E11: 2. Protect / Retain First | F11: Retention Conversation | G11: DECLINING_KEY_CORE | H11: Ready — Human | I11: Draft Ready | J11: Account Manager | K11: =FALSE() -> FALSE | L11: =FALSE() -> FALSE | M11: PB01_RETENTION | N11: Personal email from AM, then call | O11: Read brief; send outreach to book a review call. | P11: 7 | Q11: Root cause logged and next-90-day GMV back to at least the Sep-Nov (H1) level, or the decline arrested. | R11: Customer confirms a planned pause/seasonal gap (log cadence), or no response after 2 attempts (escalate). | S11: No response after 2 attempts, or Key account with further decline -> Portfolio Lead. | U11: Draft ready (not sent) | V11: RET_AM | W11: Hi {first_name}, I'd like to set up a short call to review how sourcing through Fleek is working for you at the moment and what you're planning to buy over the next few months. It will help me make sure the stock I source for you (bundles and handpicked stock) is the right fit. Would sometime later this week or early next week suit you? Best, {sender_name} | X11: WHY NOW: Commercially important, broker-led spend is falling. WHAT WE KNOW: - Key, Broker-Reliant, Account Managed; £11,721 6m GMV; Reseller, United States; tenure 8 months. - Momentum: Declining (Sep-Nov £7,060 -> Dec-Feb £4,661); Recently Active (last GMV month: February); 27 orders over 6 month(s). - Dependency: High (broker reliance 81%; 22 AM-placed / 5 self-serve orders). - Engagement: 1 product views, 5 app days, 0 offer(s), 64 Fleek chats, 36 video requests; basket Mixed. WHAT TO DO: Book a conversation. Explore stock availability, price, assortment fit, buying cadence, competitor/offline wholesaler use and operational friction. Agree a recovery plan. WHAT NOT TO DO: Do not reduce AM support or push migration; do not suggest the customer is at fault; do not propose chat/video/feature usage as the fix. SUCCESS: Root cause logged and next-90-day GMV back to at least the Sep-Nov (H1) level, or the decline arrested. | AC11: Recently Active | AD11: Existing Customer | AE11: =FALSE() -> FALSE | AF11: Not Eligible | AG11: Regular | AH11: N/A | AI11: Stay in playbook while momentum is Declining; exit when momentum is Stable/Growing for a full run; if the account lapses, NBA moves to Verify/Win-Back. | AJ11: BASELINE | AK11: BASELINE | AL11: 3541cedf4075
A12: ACC-015 | B12: P1 | C12: Key | D12: 11481 | E12: 3. Win-Back / Verify | F12: Verify Demand / Win-Back | G12: LAPSED_ESTABLISHED | H12: Ready — Human | I12: Draft Ready | J12: Account Manager | K12: =FALSE() -> FALSE | L12: =FALSE() -> FALSE | M12: PB02_VERIFY_WINBACK | N12: Personal email from AM, then call | O12: Send win-back check-in. | P12: 14 | Q12: Cadence recorded and account reclassified, or a new order within 90 days (60 days for recent-inactivity checks). | R12: Customer confirms infrequent/seasonal buying (set a reminder for their window) or confirms churn (log reason). | S12: Key account with no response after 2 attempts -> Portfolio Lead. | U12: Draft ready (not sent) | V12: WINBACK | W12: Hi {first_name}, It's been a little while since we last caught up, so I wanted to check in on your buying plans for the coming months. If you're sourcing bundles and handpicked stock again soon, I'd be glad to talk through what you're looking for and how we can help. Would a quick call be useful? Best, {sender_name} | X12: WHY NOW: Established buyer with a repeat pattern has had no GMV since November or earlier. WHAT WE KNOW: - Key, Broker-Reliant, Account Managed; £11,481 6m GMV; Reseller, United Kingdom; tenure 13 months. - Momentum: Lapsed; Recent Inactivity (last GMV month: November); 8 orders over 3 month(s). - Dependency: High (broker reliance 64%; 5 AM-placed / 3 self-serve orders). - Engagement: 5 product views, 6 app days, 1 offer(s), 96 Fleek chats, 0 video requests; basket Mixed. WHAT TO DO: Win-back conversation about upcoming buying needs and what would bring them back. WHAT NOT TO DO: Do not say 'you churned' or 'you've stopped buying'. SUCCESS: Cadence recorded and account reclassified, or a new order within 90 days (60 days for recent-inactivity checks). | AC12: Recent Inactivity | AD12: Existing Customer | AE12: =FALSE() -> FALSE | AF12: Not Eligible | AG12: Regular | AH12: N/A | AI12: If an order appears, the account re-segments automatically; if confirmed seasonal, suppress re-contact until the stated window. | AJ12: BASELINE | AK12: BASELINE | AL12: 2285c67f93e3
A13: ACC-017 | B13: P1 | C13: Key | D13: 10950 | E13: 2. Protect / Retain First | F13: Retention Conversation | G13: DECLINING_KEY_CORE | H13: Ready — Human | I13: Draft Ready | J13: Account Manager | K13: =FALSE() -> FALSE | L13: =FALSE() -> FALSE | M13: PB01_RETENTION | N13: Personal email from AM, then call | O13: Read brief; send outreach to book a review call. | P13: 7 | Q13: Root cause logged and next-90-day GMV back to at least the Sep-Nov (H1) level, or the decline arrested. | R13: Customer confirms a planned pause/seasonal gap (log cadence), or no response after 2 attempts (escalate). | S13: No response after 2 attempts, or Key account with further decline -> Portfolio Lead. | T13: H2_SINGLE_MONTH_SPIKE | U13: Draft ready (not sent) | V13: RET_AM | W13: Hi {first_name}, I'd like to set up a short call to review how sourcing through Fleek is working for you at the moment and what you're planning to buy over the next few months. It will help me make sure the stock I source for you (bundles and handpicked stock) is the right fit. Would sometime later this week or early next week suit you? Best, {sender_name} | X13: WHY NOW: Commercially important, broker-led spend is falling. WHAT WE KNOW: - Key, Broker-Reliant, Account Managed; £10,950 6m GMV; Reseller, United Kingdom; tenure 18 months. - Momentum: Declining (Sep-Nov £7,711 -> Dec-Feb £3,238); Recently Active (last GMV month: February); 37 orders over 5 month(s). - Dependency: High (broker reliance 78%; 29 AM-placed / 8 self-serve orders). - Engagement: 2 product views, 4 app days, 1 offer(s), 55 Fleek chats, 1 video requests; basket Mixed. - Warnings: H2_SINGLE_MONTH_SPIKE. WHAT TO DO: Book a conversation. Explore stock availability, price, assortment fit, buying cadence, competitor/offline wholesaler use and operational friction. Agree a recovery plan. WHAT NOT TO DO: Do not reduce AM support or push migration; do not suggest the customer is at fault; do not propose chat/video/feature usage as the fix. SUCCESS: Root cause logged and next-90-day GMV back to at least the Sep-Nov (H1) level, or the decline arrested. | AC13: Recently Active | AD13: Existing Customer | AE13: =FALSE() -> FALSE | AF13: Not Eligible | AG13: Regular | AH13: N/A | AI13: Stay in playbook while momentum is Declining; exit when momentum is Stable/Growing for a full run; if the account lapses, NBA moves to Verify/Win-Back. | AJ13: BASELINE | AK13: BASELINE | AL13: 5cb38fc6a985
A14: ACC-018 | B14: P1 | C14: Core | D14: 8613 | E14: 2. Protect / Retain First | F14: Retention Conversation | G14: DECLINING_KEY_CORE | H14: Ready — Human | I14: Draft Ready | J14: Account Manager | K14: =FALSE() -> FALSE | L14: =FALSE() -> FALSE | M14: PB01_RETENTION | N14: Personal email from AM, then call | O14: Read brief; send outreach to book a review call. | P14: 7 | Q14: Root cause logged and next-90-day GMV back to at least the Sep-Nov (H1) level, or the decline arrested. | R14: Customer confirms a planned pause/seasonal gap (log cadence), or no response after 2 attempts (escalate). | S14: No response after 2 attempts, or Key account with further decline -> Portfolio Lead. | T14: FEB_SENSITIVE; NO_FEB_GMV (Feb unconfirmed) | U14: Draft ready (not sent) | V14: RET_AM | W14: Hi {first_name}, I'd like to set up a short call to review how sourcing through Fleek is working for you at the moment and what you're planning to buy over the next few months. It will help me make sure the stock I source for you (bundles) is the right fit. Would sometime later this week or early next week suit you? Best, {sender_name} | X14: WHY NOW: Commercially important, broker-led spend is falling. WHAT WE KNOW: - Core, Broker-Reliant, Account Managed; £8,613 6m GMV; Reseller, United Kingdom; tenure 10 months. - Momentum: Declining (Sep-Nov £5,605 -> Dec-Feb £3,010); Recently Active (last GMV month: January); 11 orders over 5 month(s). - Dependency: High (broker reliance 74%; 8 AM-placed / 3 self-serve orders). - Engagement: 10 product views, 3 app days, 0 offer(s), 1 Fleek chats, 0 video requests; basket Bundle-only. - Warnings: FEB_SENSITIVE; NO_FEB_GMV (Feb unconfirmed). WHAT TO DO: Book a conversation. Explore stock availability, price, assortment fit, buying cadence, competitor/offline wholesaler use and operational friction. Agree a recovery plan. WHAT NOT TO DO: Do not reduce AM support or push migration; do not suggest the customer is at fault; do not propose chat/video/feature usage as the fix. SUCCESS: Root cause logged and next-90-day GMV back to at least the Sep-Nov (H1) level, or the decline arrested. | AC14: Recently Active | AD14: Existing Customer | AE14: =FALSE() -> FALSE | AF14: Not Eligible | AG14: Regular | AH14: N/A | AI14: Stay in playbook while momentum is Declining; exit when momentum is Stable/Growing for a full run; if the account lapses, NBA moves to Verify/Win-Back. | AJ14: BASELINE | AK14: BASELINE | AL14: b301fe425ce1
A15: ACC-021 | B15: P1 | C15: Core | D15: 6199 | E15: 2. Protect / Retain First | F15: Retention Conversation | G15: DECLINING_KEY_CORE | H15: Ready — Human | I15: Draft Ready | J15: Account Manager | K15: =FALSE() -> FALSE | L15: =FALSE() -> FALSE | M15: PB01_RETENTION | N15: Personal email from AM, then call | O15: Read brief; send outreach to book a review call. | P15: 7 | Q15: Root cause logged and next-90-day GMV back to at least the Sep-Nov (H1) level, or the decline arrested. | R15: Customer confirms a planned pause/seasonal gap (log cadence), or no response after 2 attempts (escalate). | S15: No response after 2 attempts, or Key account with further decline -> Portfolio Lead. | U15: Draft ready (not sent) | V15: RET_AM | W15: Hi {first_name}, I'd like to set up a short call to review how sourcing through Fleek is working for you at the moment and what you're planning to buy over the next few months. It will help me make sure the stock I source for you (bundles and handpicked stock) is the right fit. Would sometime later this week or early next week suit you? Best, {sender_name} | X15: WHY NOW: Commercially important, broker-led spend is falling. WHAT WE KNOW: - Core, Broker-Reliant, Account Managed; £6,199 6m GMV; Reseller, France; tenure 7 months. - Momentum: Declining (Sep-Nov £3,866 -> Dec-Feb £2,332); Recently Active (last GMV month: February); 19 orders over 6 month(s). - Dependency: High (broker reliance 64%; 12 AM-placed / 7 self-serve orders). - Engagement: 2 product views, 6 app days, 1 offer(s), 19 Fleek chats, 13 video requests; basket Mixed. WHAT TO DO: Book a conversation. Explore stock availability, price, assortment fit, buying cadence, competitor/offline wholesaler use and operational friction. Agree a recovery plan. WHAT NOT TO DO: Do not reduce AM support or push migration; do not suggest the customer is at fault; do not propose chat/video/feature usage as the fix. SUCCESS: Root cause logged and next-90-day GMV back to at least the Sep-Nov (H1) level, or the decline arrested. | AC15: Recently Active | AD15: Existing Customer | AE15: =FALSE() -> FALSE | AF15: Not Eligible | AG15: Regular | AH15: N/A | AI15: Stay in playbook while momentum is Declining; exit when momentum is Stable/Growing for a full run; if the account lapses, NBA moves to Verify/Win-Back. | AJ15: BASELINE | AK15: BASELINE | AL15: 71752711fe5b
A16: ACC-022 | B16: P1 | C16: Core | D16: 6140 | E16: 2. Protect / Retain First | F16: Retention Conversation | G16: DECLINING_KEY_CORE | H16: Ready — Human | I16: Draft Ready | J16: Account Manager | K16: =FALSE() -> FALSE | L16: =FALSE() -> FALSE | M16: PB01_RETENTION | N16: Personal email from AM, then call | O16: Read brief; send outreach to book a review call. | P16: 7 | Q16: Root cause logged and next-90-day GMV back to at least the Sep-Nov (H1) level, or the decline arrested. | R16: Customer confirms a planned pause/seasonal gap (log cadence), or no response after 2 attempts (escalate). | S16: No response after 2 attempts, or Key account with further decline -> Portfolio Lead. | T16: H2_SINGLE_MONTH_SPIKE | U16: Draft ready (not sent) | V16: RET_AM | W16: Hi {first_name}, I'd like to set up a short call to review how sourcing through Fleek is working for you at the moment and what you're planning to buy over the next few months. It will help me make sure the stock I source for you (bundles) is the right fit. Would sometime later this week or early next week suit you? Best, {sender_name} | X16: WHY NOW: Commercially important, broker-led spend is falling. WHAT WE KNOW: - Core, Broker-Reliant, Account Managed; £6,140 6m GMV; Reseller, United States; tenure 21 months. - Momentum: Declining (Sep-Nov £4,539 -> Dec-Feb £1,601); Recent Inactivity (last GMV month: December); 7 orders over 3 month(s). - Dependency: Medium (broker reliance 49%; 3 AM-placed / 4 self-serve orders). - Engagement: 12 product views, 4 app days, 2 offer(s), 33 Fleek chats, 2 video requests; basket Bundle-only. - Warnings: H2_SINGLE_MONTH_SPIKE. WHAT TO DO: Book a conversation. Explore stock availability, price, assortment fit, buying cadence, competitor/offline wholesaler use and operational friction. Agree a recovery plan. WHAT NOT TO DO: Do not reduce AM support or push migration; do not suggest the customer is at fault; do not propose chat/video/feature usage as the fix. SUCCESS: Root cause logged and next-90-day GMV back to at least the Sep-Nov (H1) level, or the decline arrested. | AC16: Recent Inactivity | AD16: Existing Customer | AE16: =FALSE() -> FALSE | AF16: Not Eligible | AG16: Regular | AH16: N/A | AI16: Stay in playbook while momentum is Declining; exit when momentum is Stable/Growing for a full run; if the account lapses, NBA moves to Verify/Win-Back. | AJ16: BASELINE | AK16: BASELINE | AL16: 8f37f6a06496
A17: ACC-023 | B17: P1 | C17: Core | D17: 5727 | E17: 2. Protect / Retain First | F17: Retention Conversation | G17: DECLINING_KEY_CORE | H17: Ready — Human | I17: Draft Ready | J17: Account Manager | K17: =FALSE() -> FALSE | L17: =FALSE() -> FALSE | M17: PB01_RETENTION | N17: Personal email from AM, then call | O17: Read brief; send outreach to book a review call. | P17: 7 | Q17: Root cause logged and next-90-day GMV back to at least the Sep-Nov (H1) level, or the decline arrested. | R17: Customer confirms a planned pause/seasonal gap (log cadence), or no response after 2 attempts (escalate). | S17: No response after 2 attempts, or Key account with further decline -> Portfolio Lead. | T17: FEB_SENSITIVE; H2_SINGLE_MONTH_SPIKE | U17: Draft ready (not sent) | V17: RET_AM | W17: Hi {first_name}, I'd like to set up a short call to review how sourcing through Fleek is working for you at the moment and what you're planning to buy over the next few months. It will help me make sure the stock I source for you (handpicked stock) is the right fit. Would sometime later this week or early next week suit you? Best, {sender_name} | X17: WHY NOW: Commercially important, broker-led spend is falling. WHAT WE KNOW: - Core, Broker-Reliant, Account Managed; £5,727 6m GMV; Reseller, France; tenure 43 months. - Momentum: Declining (Sep-Nov £4,800 -> Dec-Feb £927); Recently Active (last GMV month: February); 4 orders over 4 month(s). - Dependency: High (broker reliance 64%; 3 AM-placed / 1 self-serve orders). - Engagement: 10 product views, 0 app days, 1 offer(s), 9 Fleek chats, 0 video requests; basket Handpick-only. - Warnings: FEB_SENSITIVE; H2_SINGLE_MONTH_SPIKE. WHAT TO DO: Book a conversation. Explore stock availability, price, assortment fit, buying cadence, competitor/offline wholesaler use and operational friction. Agree a recovery plan. WHAT NOT TO DO: Do not reduce AM support or push migration; do not suggest the customer is at fault; do not propose chat/video/feature usage as the fix. SUCCESS: Root cause logged and next-90-day GMV back to at least the Sep-Nov (H1) level, or the decline arrested. | AC17: Recently Active | AD17: Existing Customer | AE17: =FALSE() -> FALSE | AF17: Not Eligible | AG17: Lumpy | AH17: N/A | AI17: Stay in playbook while momentum is Declining; exit when momentum is Stable/Growing for a full run; if the account lapses, NBA moves to Verify/Win-Back. | AJ17: BASELINE | AK17: BASELINE | AL17: 2808d52199a5
A18: ACC-026 | B18: P1 | C18: Core | D18: 4772 | E18: 3. Win-Back / Verify | F18: Verify Demand / Win-Back | G18: LAPSED_THIN_HISTORY | H18: Ready — Human | I18: Draft Ready | J18: Account Manager | K18: =FALSE() -> FALSE | L18: =FALSE() -> FALSE | M18: PB02_VERIFY_WINBACK | N18: Personal email from AM, then call | O18: Send cadence check-in (verify, don't assume churn). | P18: 14 | Q18: Cadence recorded and account reclassified, or a new order within 90 days (60 days for recent-inactivity checks). | R18: Customer confirms infrequent/seasonal buying (set a reminder for their window) or confirms churn (log reason). | S18: Key account with no response after 2 attempts -> Portfolio Lead. | T18: LOW_CONFIDENCE | U18: Draft ready (not sent) | V18: VERIFY_CADENCE | W18: Hi {first_name}, Thanks for your previous orders with Fleek. I wanted to check how you usually plan your stock buying (seasonal, project by project, or ongoing) so we can get in touch at the right moments rather than too often. Happy to talk on a quick call, or just reply here with what works for you. Best, {sender_name} | X18: WHY NOW: Apparent lapse rests on 1-2 orders or one buying month; cadence is unknown. WHAT WE KNOW: - Core, Broker-Reliant, Account Managed; £4,772 6m GMV; Reseller, Germany; tenure 9 months. - Momentum: Lapsed; No Meaningful History (last GMV month: November); 2 orders over 2 month(s). - Dependency: High (broker reliance 82%; 2 AM-placed / 0 self-serve orders). - Engagement: 0 product views, 1 app days, 2 offer(s), 6 Fleek chats, 0 video requests; basket Bundle-only. - Warnings: LOW_CONFIDENCE. WHAT TO DO: Do not assume churn. Verify expected purchase frequency first, then set the next contact window. WHAT NOT TO DO: Do not treat as churn or run a discount-led win-back. SUCCESS: Cadence recorded and account reclassified, or a new order within 90 days (60 days for recent-inactivity checks). | AC18: No Meaningful History | AD18: Existing Customer | AE18: =FALSE() -> FALSE | AF18: Not Eligible | AG18: Lumpy | AH18: N/A | AI18: If an order appears, the account re-segments automatically; if confirmed seasonal, suppress re-contact until the stated window. | AJ18: BASELINE | AK18: BASELINE | AL18: beae7abebe16
A19: ACC-028 | B19: P1 | C19: Core | D19: 4639 | E19: 2. Protect / Retain First | F19: Retention Conversation | G19: DECLINING_KEY_CORE | H19: Ready — Human | I19: Draft Ready | J19: Account Manager | K19: =FALSE() -> FALSE | L19: =FALSE() -> FALSE | M19: PB01_RETENTION | N19: Personal email from AM, then call | O19: Read brief; send outreach to book a review call. | P19: 7 | Q19: Root cause logged and next-90-day GMV back to at least the Sep-Nov (H1) level, or the decline arrested. | R19: Customer confirms a planned pause/seasonal gap (log cadence), or no response after 2 attempts (escalate). | S19: No response after 2 attempts, or Key account with further decline -> Portfolio Lead. | T19: H2_SINGLE_MONTH_SPIKE; NO_FEB_GMV (Feb unconfirmed) | U19: Draft ready (not sent) | V19: RET_AM | W19: Hi {first_name}, I'd like to set up a short call to review how sourcing through Fleek is working for you at the moment and what you're planning to buy over the next few months. It will help me make sure the stock I source for you (handpicked stock) is the right fit. Would sometime later this week or early next week suit you? Best, {sender_name} | X19: WHY NOW: Commercially important, broker-led spend is falling. WHAT WE KNOW: - Core, Broker-Reliant, Account Managed; £4,639 6m GMV; Reseller, Netherlands; tenure 11 months. - Momentum: Declining (Sep-Nov £3,271 -> Dec-Feb £1,368); Recently Active (last GMV month: January); 7 orders over 4 month(s). - Dependency: High (broker reliance 48%; 3 AM-placed / 4 self-serve orders). - Engagement: 8 product views, 4 app days, 1 offer(s), 35 Fleek chats, 0 video requests; basket Handpick-only. - Warnings: H2_SINGLE_MONTH_SPIKE; NO_FEB_GMV (Feb unconfirmed). WHAT TO DO: Book a conversation. Explore stock availability, price, assortment fit, buying cadence, competitor/offline wholesaler use and operational friction. Agree a recovery plan. WHAT NOT TO DO: Do not reduce AM support or push migration; do not suggest the customer is at fault; do not propose chat/video/feature usage as the fix. SUCCESS: Root cause logged and next-90-day GMV back to at least the Sep-Nov (H1) level, or the decline arrested. | AC19: Recently Active | AD19: Existing Customer | AE19: =FALSE() -> FALSE | AF19: Not Eligible | AG19: Regular | AH19: N/A | AI19: Stay in playbook while momentum is Declining; exit when momentum is Stable/Growing for a full run; if the account lapses, NBA moves to Verify/Win-Back. | AJ19: BASELINE | AK19: BASELINE | AL19: f91bbd0fb68a
A20: ACC-214 | B20: P1 | C20: Core | D20: 4632 | E20: 8. Retention / Reactivation | F20: Retention Conversation | G20: ENGAGED_BUT_SHRINKING | H20: Ready — Human | I20: Draft Ready | J20: Customer Success / Growth | K20: =TRUE() -> TRUE | L20: =FALSE() -> FALSE | M20: PB01_RETENTION | N20: Personal email, then call | O20: Read brief; send outreach to book a call. | P20: 7 | Q20: Root cause logged and next-90-day GMV back to at least the Sep-Nov (H1) level, or the decline arrested. | R20: Customer confirms a planned pause/seasonal gap (log cadence), or no response after 2 attempts (escalate). | S20: No response after 2 attempts, or Key account with further decline -> Portfolio Lead. | T20: H2_SINGLE_MONTH_SPIKE; NO_FEB_GMV (Feb unconfirmed) | U20: Draft ready (not sent) | V20: RET_CS | W20: Hi {first_name}, I'm part of the Fleek team and wanted to hear how the platform is working for your buying at the moment. Is anything making it harder to find or secure the stock you need? I'd value a short call to understand what would be most useful for you over the coming months. Would a quick call this week work? Best, {sender_name} | X20: WHY NOW: Heavily self-serving account whose spend is falling; product adoption is not the issue. WHAT WE KNOW: - Core, Self-Serve, Self Serve; £4,632 6m GMV; Reseller, United Kingdom; tenure 5 months. - Momentum: Declining (Sep-Nov £4,516 -> Dec-Feb £116); Recently Active (last GMV month: January); 12 orders over 3 month(s). - Dependency: Low (broker reliance 0%; 0 AM-placed / 12 self-serve orders). - Engagement: 665 product views, 74 app days, 53 offer(s), 70 Fleek chats, 1 video requests; basket Mixed. - Warnings: H2_SINGLE_MONTH_SPIKE; NO_FEB_GMV (Feb unconfirmed). WHAT TO DO: Book a conversation. The customer already uses the product heavily: explore stock availability, price, offer outcomes and competitor use. WHAT NOT TO DO: Do not send more product nudges - engagement is not the problem. SUCCESS: Root cause logged and next-90-day GMV back to at least the Sep-Nov (H1) level, or the decline arrested. | AC20: Recently Active | AD20: Existing Customer | AE20: =FALSE() -> FALSE | AF20: Not Eligible | AG20: Regular | AH20: N/A | AI20: Stay in playbook while momentum is Declining; exit when momentum is Stable/Growing for a full run; if the account lapses, NBA moves to Verify/Win-Back. | AJ20: BASELINE | AK20: BASELINE | AL20: 85018850706f
A21: ACC-032 | B21: P1 | C21: Core | D21: 4179 | E21: 3. Win-Back / Verify | F21: Verify Demand / Win-Back | G21: LAPSED_THIN_HISTORY | H21: Ready — Human | I21: Draft Ready | J21: Account Manager | K21: =FALSE() -> FALSE | L21: =FALSE() -> FALSE | M21: PB02_VERIFY_WINBACK | N21: Personal email from AM, then call | O21: Send cadence check-in (verify, don't assume churn). | P21: 14 | Q21: Cadence recorded and account reclassified, or a new order within 90 days (60 days for recent-inactivity checks). | R21: Customer confirms infrequent/seasonal buying (set a reminder for their window) or confirms churn (log reason). | S21: Key account with no response after 2 attempts -> Portfolio Lead. | T21: LOW_CONFIDENCE | U21: Draft ready (not sent) | V21: VERIFY_CADENCE | W21: Hi {first_name}, Thanks for your previous orders with Fleek. I wanted to check how you usually plan your stock buying (seasonal, project by project, or ongoing) so we can get in touch at the right moments rather than too often. Happy to talk on a quick call, or just reply here with what works for you. Best, {sender_name} | X21: WHY NOW: Apparent lapse rests on 1-2 orders or one buying month; cadence is unknown. WHAT WE KNOW: - Core, Broker-Reliant, Account Managed; £4,179 6m GMV; Reseller, France; tenure 12 months. - Momentum: Lapsed; No Meaningful History (last GMV month: November); 2 orders over 2 month(s). - Dependency: High (broker reliance 80%; 2 AM-placed / 0 self-serve orders). - Engagement: 10 product views, 1 app days, 1 offer(s), 64 Fleek chats, 0 video requests; basket Handpick-only. - Warnings: LOW_CONFIDENCE. WHAT TO DO: Do not assume churn. Verify expected purchase frequency first, then set the next contact window. WHAT NOT TO DO: Do not treat as churn or run a discount-led win-back. SUCCESS: Cadence recorded and account reclassified, or a new order within 90 days (60 days for recent-inactivity checks). | AC21: No Meaningful History | AD21: Existing Customer | AE21: =FALSE() -> FALSE | AF21: Not Eligible | AG21: Lumpy | AH21: N/A | AI21: If an order appears, the account re-segments automatically; if confirmed seasonal, suppress re-contact until the stated window. | AJ21: BASELINE | AK21: BASELINE | AL21: 8480fbee4c85
A22: ACC-215 | B22: P1 | C22: Core | D22: 3907 | E22: 8. Retention / Reactivation | F22: Verify Demand / Win-Back | G22: LAPSED_THIN_HISTORY | H22: Ready — Human | I22: Draft Ready | J22: Customer Success / Growth | K22: =TRUE() -> TRUE | L22: =FALSE() -> FALSE | M22: PB02_VERIFY_WINBACK | N22: Personal email, then call | O22: Send cadence check-in (verify, don't assume churn). | P22: 14 | Q22: Cadence recorded and account reclassified, or a new order within 90 days (60 days for recent-inactivity checks). | R22: Customer confirms infrequent/seasonal buying (set a reminder for their window) or confirms churn (log reason). | S22: Key account with no response after 2 attempts -> Portfolio Lead. | T22: LOW_CONFIDENCE | U22: Draft ready (not sent) | V22: VERIFY_CADENCE | W22: Hi {first_name}, Thanks for your previous orders with Fleek. I wanted to check how you usually plan your stock buying (seasonal, project by project, or ongoing) so we can get in touch at the right moments rather than too often. Happy to talk on a quick call, or just reply here with what works for you. Best, {sender_name} | X22: WHY NOW: Apparent lapse rests on 1-2 orders or one buying month; cadence is unknown. WHAT WE KNOW: - Core, Self-Serve, Self Serve; £3,907 6m GMV; Reseller, United States; tenure 5 months. - Momentum: Lapsed; No Meaningful History (last GMV month: October); 1 orders over 1 month(s). - Dependency: Low (broker reliance 0%; 0 AM-placed / 1 self-serve orders). - Engagement: 76 product views, 14 app days, 0 offer(s), 3 Fleek chats, 0 video requests; basket Handpick-only. - Warnings: LOW_CONFIDENCE. WHAT TO DO: Do not assume churn. Verify expected purchase frequency first, then set the next contact window. WHAT NOT TO DO: Do not treat as churn or run a discount-led win-back. SUCCESS: Cadence recorded and account reclassified, or a new order within 90 days (60 days for recent-inactivity checks). | AC22: No Meaningful History | AD22: Existing Customer | AE22: =FALSE() -> FALSE | AF22: Not Eligible | AG22: Lumpy | AH22: N/A | AI22: If an order appears, the account re-segments automatically; if confirmed seasonal, suppress re-contact until the stated window. | AJ22: BASELINE | AK22: BASELINE | AL22: 7be89ed5f41b
A23: ACC-035 | B23: P1 | C23: Core | D23: 3906 | E23: 2. Protect / Retain First | F23: Retention Conversation | G23: DECLINING_KEY_CORE | H23: Ready — Human | I23: Draft Ready | J23: Account Manager | K23: =FALSE() -> FALSE | L23: =FALSE() -> FALSE | M23: PB01_RETENTION | N23: Personal email from AM, then call | O23: Read brief; send outreach to book a review call. | P23: 7 | Q23: Root cause logged and next-90-day GMV back to at least the Sep-Nov (H1) level, or the decline arrested. | R23: Customer confirms a planned pause/seasonal gap (log cadence), or no response after 2 attempts (escalate). | S23: No response after 2 attempts, or Key account with further decline -> Portfolio Lead. | T23: MATERIAL_BROKER_INCONSISTENCY; H2_SINGLE_MONTH_SPIKE; NO_FEB_GMV (Feb unconfirmed) | U23: Draft ready (not sent) | V23: RET_AM | W23: Hi {first_name}, I'd like to set up a short call to review how sourcing through Fleek is working for you at the moment and what you're planning to buy over the next few months. It will help me make sure the stock I source for you (handpicked stock) is the right fit. Would sometime later this week or early next week suit you? Best, {sender_name} | X23: WHY NOW: Commercially important, broker-led spend is falling. WHAT WE KNOW: - Core, Broker-Reliant, Account Managed; £3,906 6m GMV; Reseller, United Kingdom; tenure 19 months. - Momentum: Declining (Sep-Nov £2,595 -> Dec-Feb £1,311); Recently Active (last GMV month: January); 5 orders over 3 month(s). - Dependency: Medium (broker reliance 55%; 3 AM-placed / 2 self-serve orders). - Engagement: 11 product views, 6 app days, 0 offer(s), 86 Fleek chats, 3 video requests; basket Handpick-only. - Warnings: MATERIAL_BROKER_INCONSISTENCY; H2_SINGLE_MONTH_SPIKE; NO_FEB_GMV (Feb unconfirmed). WHAT TO DO: Book a conversation. Explore stock availability, price, assortment fit, buying cadence, competitor/offline wholesaler use and operational friction. Agree a recovery plan. WHAT NOT TO DO: Do not reduce AM support or push migration; do not suggest the customer is at fault; do not propose chat/video/feature usage as the fix. SUCCESS: Root cause logged and next-90-day GMV back to at least the Sep-Nov (H1) level, or the decline arrested. | AC23: Recently Active | AD23: Existing Customer | AE23: =FALSE() -> FALSE | AF23: Not Eligible | AG23: Regular | AH23: N/A | AI23: Stay in playbook while momentum is Declining; exit when momentum is Stable/Growing for a full run; if the account lapses, NBA moves to Verify/Win-Back. | AJ23: BASELINE | AK23: BASELINE | AL23: 54b853a6f434
A24: ACC-037 | B24: P1 | C24: Core | D24: 3863 | E24: 2. Protect / Retain First | F24: Retention Conversation | G24: DECLINING_KEY_CORE | H24: Ready — Human | I24: Draft Ready | J24: Account Manager | K24: =FALSE() -> FALSE | L24: =FALSE() -> FALSE | M24: PB01_RETENTION | N24: Personal email from AM, then call | O24: Read brief; send outreach to book a review call. | P24: 7 | Q24: Root cause logged and next-90-day GMV back to at least the Sep-Nov (H1) level, or the decline arrested. | R24: Customer confirms a planned pause/seasonal gap (log cadence), or no response after 2 attempts (escalate). | S24: No response after 2 attempts, or Key account with further decline -> Portfolio Lead. | U24: Draft ready (not sent) | V24: RET_AM | W24: Hi {first_name}, I'd like to set up a short call to review how sourcing through Fleek is working for you at the moment and what you're planning to buy over the next few months. It will help me make sure the stock I source for you (bundles and handpicked stock) is the right fit. Would sometime later this week or early next week suit you? Best, {sender_name} | X24: WHY NOW: Commercially important, broker-led spend is falling. WHAT WE KNOW: - Core, Broker-Reliant, Account Managed; £3,863 6m GMV; Reseller, Belgium; tenure 11 months. - Momentum: Declining (Sep-Nov £2,595 -> Dec-Feb £1,267); Recently Active (last GMV month: February); 7 orders over 4 month(s). - Dependency: High (broker reliance 84%; 6 AM-placed / 1 self-serve orders). - Engagement: 8 product views, 2 app days, 1 offer(s), 55 Fleek chats, 0 video requests; basket Mixed. WHAT TO DO: Book a conversation. Explore stock availability, price, assortment fit, buying cadence, competitor/offline wholesaler use and operational friction. Agree a recovery plan. WHAT NOT TO DO: Do not reduce AM support or push migration; do not suggest the customer is at fault; do not propose chat/video/feature usage as the fix. SUCCESS: Root cause logged and next-90-day GMV back to at least the Sep-Nov (H1) level, or the decline arrested. | AC24: Recently Active | AD24: Existing Customer | AE24: =FALSE() -> FALSE | AF24: Not Eligible | AG24: Regular | AH24: N/A | AI24: Stay in playbook while momentum is Declining; exit when momentum is Stable/Growing for a full run; if the account lapses, NBA moves to Verify/Win-Back. | AJ24: BASELINE | AK24: BASELINE | AL24: f3fb6364e78b
A25: ACC-038 | B25: P1 | C25: Core | D25: 3702 | E25: 8. Retention / Reactivation | F25: Verify Demand / Win-Back | G25: LAPSED_THIN_HISTORY | H25: Ready — Human | I25: Draft Ready | J25: Account Manager | K25: =FALSE() -> FALSE | L25: =FALSE() -> FALSE | M25: PB02_VERIFY_WINBACK | N25: Personal email from AM, then call | O25: Send cadence check-in (verify, don't assume churn). | P25: 14 | Q25: Cadence recorded and account reclassified, or a new order within 90 days (60 days for recent-inactivity checks). | R25: Customer confirms infrequent/seasonal buying (set a reminder for their window) or confirms churn (log reason). | S25: Key account with no response after 2 attempts -> Portfolio Lead. | T25: LOW_CONFIDENCE | U25: Draft ready (not sent) | V25: VERIFY_CADENCE | W25: Hi {first_name}, Thanks for your previous orders with Fleek. I wanted to check how you usually plan your stock buying (seasonal, project by project, or ongoing) so we can get in touch at the right moments rather than too often. Happy to talk on a quick call, or just reply here with what works for you. Best, {sender_name} | X25: WHY NOW: Apparent lapse rests on 1-2 orders or one buying month; cadence is unknown. WHAT WE KNOW: - Core, AM-Owned / Self-Serving, Account Managed; £3,702 6m GMV; Retailer, United Kingdom; tenure 32 months. - Momentum: Lapsed; No Meaningful History (last GMV month: October); 2 orders over 2 month(s). - Dependency: Low (broker reliance 4%; 0 AM-placed / 2 self-serve orders). - Engagement: 78 product views, 16 app days, 2 offer(s), 37 Fleek chats, 0 video requests; basket Handpick-only. - Warnings: LOW_CONFIDENCE. WHAT TO DO: Do not assume churn. Verify expected purchase frequency first, then set the next contact window. WHAT NOT TO DO: Do not treat as churn or run a discount-led win-back. SUCCESS: Cadence recorded and account reclassified, or a new order within 90 days (60 days for recent-inactivity checks). | AC25: No Meaningful History | AD25: Existing Customer | AE25: =FALSE() -> FALSE | AF25: Not Eligible | AG25: Lumpy | AH25: N/A | AI25: If an order appears, the account re-segments automatically; if confirmed seasonal, suppress re-contact until the stated window. | AJ25: BASELINE | AK25: BASELINE | AL25: 172ea5e0f915
A26: ACC-040 | B26: P1 | C26: Core | D26: 3579 | E26: 2. Protect / Retain First | F26: Retention Conversation | G26: DECLINING_KEY_CORE | H26: Ready — Human | I26: Draft Ready | J26: Account Manager | K26: =FALSE() -> FALSE | L26: =FALSE() -> FALSE | M26: PB01_RETENTION | N26: Personal email from AM, then call | O26: Read brief; send outreach to book a review call. | P26: 7 | Q26: Root cause logged and next-90-day GMV back to at least the Sep-Nov (H1) level, or the decline arrested. | R26: Customer confirms a planned pause/seasonal gap (log cadence), or no response after 2 attempts (escalate). | S26: No response after 2 attempts, or Key account with further decline -> Portfolio Lead. | T26: FEB_SENSITIVE; H2_SINGLE_MONTH_SPIKE | U26: Draft ready (not sent) | V26: RET_AM | W26: Hi {first_name}, I'd like to set up a short call to review how sourcing through Fleek is working for you at the moment and what you're planning to buy over the next few months. It will help me make sure the stock I source for you (handpicked stock) is the right fit. Would sometime later this week or early next week suit you? Best, {sender_name} | X26: WHY NOW: Commercially important, broker-led spend is falling. WHAT WE KNOW: - Core, Broker-Reliant, Account Managed; £3,579 6m GMV; Reseller, United States; tenure 12 months. - Momentum: Declining (Sep-Nov £2,692 -> Dec-Feb £887); Recently Active (last GMV month: February); 6 orders over 3 month(s). - Dependency: High (broker reliance 72%; 4 AM-placed / 2 self-serve orders). - Engagement: 13 product views, 6 app days, 1 offer(s), 8 Fleek chats, 1 video requests; basket Handpick-only. - Warnings: FEB_SENSITIVE; H2_SINGLE_MONTH_SPIKE. WHAT TO DO: Book a conversation. Explore stock availability, price, assortment fit, buying cadence, competitor/offline wholesaler use and operational friction. Agree a recovery plan. WHAT NOT TO DO: Do not reduce AM support or push migration; do not suggest the customer is at fault; do not propose chat/video/feature usage as the fix. SUCCESS: Root cause logged and next-90-day GMV back to at least the Sep-Nov (H1) level, or the decline arrested. | AC26: Recently Active | AD26: Existing Customer | AE26: =FALSE() -> FALSE | AF26: Not Eligible | AG26: Regular | AH26: N/A | AI26: Stay in playbook while momentum is Declining; exit when momentum is Stable/Growing for a full run; if the account lapses, NBA moves to Verify/Win-Back. | AJ26: BASELINE | AK26: BASELINE | AL26: 923b662583c0
A27: ACC-041 | B27: P1 | C27: Core | D27: 3549 | E27: 2. Protect / Retain First | F27: Retention Conversation | G27: DECLINING_KEY_CORE | H27: Ready — Human | I27: Draft Ready | J27: Account Manager | K27: =FALSE() -> FALSE | L27: =FALSE() -> FALSE | M27: PB01_RETENTION | N27: Personal email from AM, then call | O27: Read brief; send outreach to book a review call. | P27: 7 | Q27: Root cause logged and next-90-day GMV back to at least the Sep-Nov (H1) level, or the decline arrested. | R27: Customer confirms a planned pause/seasonal gap (log cadence), or no response after 2 attempts (escalate). | S27: No response after 2 attempts, or Key account with further decline -> Portfolio Lead. | T27: MATERIAL_BROKER_INCONSISTENCY; NO_FEB_GMV (Feb unconfirmed) | U27: Draft ready (not sent) | V27: RET_AM | W27: Hi {first_name}, I'd like to set up a short call to review how sourcing through Fleek is working for you at the moment and what you're planning to buy over the next few months. It will help me make sure the stock I source for you (bundles and handpicked stock) is the right fit. Would sometime later this week or early next week suit you? Best, {sender_name} | X27: WHY NOW: Commercially important, broker-led spend is falling. WHAT WE KNOW: - Core, Broker-Reliant, Account Managed; £3,549 6m GMV; Reseller, France; tenure 28 months. - Momentum: Declining (Sep-Nov £2,505 -> Dec-Feb £1,045); Recently Active (last GMV month: January); 7 orders over 5 month(s). - Dependency: High (broker reliance 61%; 4 AM-placed / 3 self-serve orders). - Engagement: 2 product views, 6 app days, 0 offer(s), 25 Fleek chats, 0 video requests; basket Mixed. - Warnings: MATERIAL_BROKER_INCONSISTENCY; NO_FEB_GMV (Feb unconfirmed). WHAT TO DO: Book a conversation. Explore stock availability, price, assortment fit, buying cadence, competitor/offline wholesaler use and operational friction. Agree a recovery plan. WHAT NOT TO DO: Do not reduce AM support or push migration; do not suggest the customer is at fault; do not propose chat/video/feature usage as the fix. SUCCESS: Root cause logged and next-90-day GMV back to at least the Sep-Nov (H1) level, or the decline arrested. | AC27: Recently Active | AD27: Existing Customer | AE27: =FALSE() -> FALSE | AF27: Not Eligible | AG27: Regular | AH27: N/A | AI27: Stay in playbook while momentum is Declining; exit when momentum is Stable/Growing for a full run; if the account lapses, NBA moves to Verify/Win-Back. | AJ27: BASELINE | AK27: BASELINE | AL27: 664c8c477044
A28: ACC-216 | B28: P1 | C28: Core | D28: 3497 | E28: 6. Growth Opportunity | F28: Verify Demand / Win-Back | G28: RECENT_INACTIVITY | H28: Ready — Human | I28: Draft Ready | J28: Customer Success / Growth | K28: =TRUE() -> TRUE | L28: =FALSE() -> FALSE | M28: PB02_VERIFY_WINBACK | N28: Personal email, then call | O28: Send check-in; hold automated growth messages. | P28: 14 | Q28: Cadence recorded and account reclassified, or a new order within 90 days (60 days for recent-inactivity checks). | R28: Customer confirms infrequent/seasonal buying (set a reminder for their window) or confirms churn (log reason). | S28: Key account with no response after 2 attempts -> Portfolio Lead. | T28: H2_SINGLE_MONTH_SPIKE | U28: Draft ready (not sent) | V28: CHECKIN | W28: Hi {first_name}, I wanted to check in on how your stock planning looks for the next couple of months. Is there anything you're looking for that you haven't been able to find on Fleek? If it helps, I'm happy to jump on a quick call or you can simply reply with what you need. Best, {sender_name} | X28: WHY NOW: Growth-type account with an established pattern but no January/February GMV. WHAT WE KNOW: - Core, Self-Serve, Self Serve; £3,497 6m GMV; Reseller, France; tenure 5 months. - Momentum: Growing (Sep-Nov £1,394 -> Dec-Feb £2,103); Recent Inactivity (last GMV month: December); 11 orders over 3 month(s). - Dependency: Low (broker reliance 0%; 0 AM-placed / 11 self-serve orders). - Engagement: 1416 product views, 50 app days, 13 offer(s), 16 Fleek chats, 0 video requests; basket Bundle-only. - Warnings: H2_SINGLE_MONTH_SPIKE. WHAT TO DO: Check the account is still buying and why there was no January/February GMV before any automated growth action. WHAT NOT TO DO: Do not trigger automated growth messages until the check is complete. SUCCESS: Cadence recorded and account reclassified, or a new order within 90 days (60 days for recent-inactivity checks). | AC28: Recent Inactivity | AD28: Existing Customer | AE28: =FALSE() -> FALSE | AF28: Not Eligible | AG28: Regular | AH28: N/A | AI28: If an order appears, the account re-segments automatically; if confirmed seasonal, suppress re-contact until the stated window. | AJ28: BASELINE | AK28: BASELINE | AL28: 0ffb95bd9c91
A29: ACC-042 | B29: P1 | C29: Core | D29: 3478 | E29: 8. Retention / Reactivation | F29: Verify Demand / Win-Back | G29: LAPSED_THIN_HISTORY | H29: Ready — Human | I29: Draft Ready | J29: Account Manager | K29: =FALSE() -> FALSE | L29: =FALSE() -> FALSE | M29: PB02_VERIFY_WINBACK | N29: Personal email from AM, then call | O29: Send cadence check-in (verify, don't assume churn). | P29: 14 | Q29: Cadence recorded and account reclassified, or a new order within 90 days (60 days for recent-inactivity checks). | R29: Customer confirms infrequent/seasonal buying (set a reminder for their window) or confirms churn (log reason). | S29: Key account with no response after 2 attempts -> Portfolio Lead. | T29: LOW_CONFIDENCE | U29: Draft ready (not sent) | V29: VERIFY_CADENCE | W29: Hi {first_name}, Thanks for your previous orders with Fleek. I wanted to check how you usually plan your stock buying (seasonal, project by project, or ongoing) so we can get in touch at the right moments rather than too often. Happy to talk on a quick call, or just reply here with what works for you. Best, {sender_name} | X29: WHY NOW: Apparent lapse rests on 1-2 orders or one buying month; cadence is unknown. WHAT WE KNOW: - Core, AM-Owned / Self-Serving, Account Managed; £3,478 6m GMV; Reseller, Switzerland; tenure 34 months. - Momentum: Lapsed; No Meaningful History (last GMV month: September); 1 orders over 1 month(s). - Dependency: Low (broker reliance 6%; 0 AM-placed / 1 self-serve orders). - Engagement: 1 product views, 1 app days, 0 offer(s), 53 Fleek chats, 0 video requests; basket Handpick-only. - Warnings: LOW_CONFIDENCE. WHAT TO DO: Do not assume churn. Verify expected purchase frequency first, then set the next contact window. WHAT NOT TO DO: Do not treat as churn or run a discount-led win-back. SUCCESS: Cadence recorded and account reclassified, or a new order within 90 days (60 days for recent-inactivity checks). | AC29: No Meaningful History | AD29: Existing Customer | AE29: =FALSE() -> FALSE | AF29: Not Eligible | AG29: Lumpy | AH29: N/A | AI29: If an order appears, the account re-segments automatically; if confirmed seasonal, suppress re-contact until the stated window. | AJ29: BASELINE | AK29: BASELINE | AL29: 931083a5e42a
A30: ACC-043 | B30: P1 | C30: Core | D30: 3434 | E30: 2. Protect / Retain First | F30: Retention Conversation | G30: DECLINING_KEY_CORE | H30: Ready — Human | I30: Draft Ready | J30: Account Manager | K30: =FALSE() -> FALSE | L30: =FALSE() -> FALSE | M30: PB01_RETENTION | N30: Personal email from AM, then call | O30: Read brief; send outreach to book a review call. | P30: 7 | Q30: Root cause logged and next-90-day GMV back to at least the Sep-Nov (H1) level, or the decline arrested. | R30: Customer confirms a planned pause/seasonal gap (log cadence), or no response after 2 attempts (escalate). | S30: No response after 2 attempts, or Key account with further decline -> Portfolio Lead. | T30: H2_SINGLE_MONTH_SPIKE; NO_FEB_GMV (Feb unconfirmed) | U30: Draft ready (not sent) | V30: RET_AM | W30: Hi {first_name}, I'd like to set up a short call to review how sourcing through Fleek is working for you at the moment and what you're planning to buy over the next few months. It will help me make sure the stock I source for you (bundles and handpicked stock) is the right fit. Would sometime later this week or early next week suit you? Best, {sender_name} | X30: WHY NOW: Commercially important, broker-led spend is falling. WHAT WE KNOW: - Core, Broker-Reliant, Account Managed; £3,434 6m GMV; Reseller, France; tenure 20 months. - Momentum: Declining (Sep-Nov £2,455 -> Dec-Feb £980); Recently Active (last GMV month: January); 5 orders over 3 month(s). - Dependency: High (broker reliance 64%; 3 AM-placed / 2 self-serve orders). - Engagement: 3 product views, 5 app days, 1 offer(s), 36 Fleek chats, 0 video requests; basket Mixed. - Warnings: H2_SINGLE_MONTH_SPIKE; NO_FEB_GMV (Feb unconfirmed). WHAT TO DO: Book a conversation. Explore stock availability, price, assortment fit, buying cadence, competitor/offline wholesaler use and operational friction. Agree a recovery plan. WHAT NOT TO DO: Do not reduce AM support or push migration; do not suggest the customer is at fault; do not propose chat/video/feature usage as the fix. SUCCESS: Root cause logged and next-90-day GMV back to at least the Sep-Nov (H1) level, or the decline arrested. | AC30: Recently Active | AD30: Existing Customer | AE30: =FALSE() -> FALSE | AF30: Not Eligible | AG30: Regular | AH30: N/A | AI30: Stay in playbook while momentum is Declining; exit when momentum is Stable/Growing for a full run; if the account lapses, NBA moves to Verify/Win-Back. | AJ30: BASELINE | AK30: BASELINE | AL30: 635522c38afb
A31: ACC-044 | B31: P1 | C31: Core | D31: 3383 | E31: 3. Win-Back / Verify | F31: Verify Demand / Win-Back | G31: LAPSED_THIN_HISTORY | H31: Ready — Human | I31: Draft Ready | J31: Account Manager | K31: =FALSE() -> FALSE | L31: =FALSE() -> FALSE | M31: PB02_VERIFY_WINBACK | N31: Personal email from AM, then call | O31: Send cadence check-in (verify, don't assume churn). | P31: 14 | Q31: Cadence recorded and account reclassified, or a new order within 90 days (60 days for recent-inactivity checks). | R31: Customer confirms infrequent/seasonal buying (set a reminder for their window) or confirms churn (log reason). | S31: Key account with no response after 2 attempts -> Portfolio Lead. | U31: Draft ready (not sent) | V31: VERIFY_CADENCE | W31: Hi {first_name}, Thanks for your previous orders with Fleek. I wanted to check how you usually plan your stock buying (seasonal, project by project, or ongoing) so we can get in touch at the right moments rather than too often. Happy to talk on a quick call, or just reply here with what works for you. Best, {sender_name} | X31: WHY NOW: Apparent lapse rests on 1-2 orders or one buying month; cadence is unknown. WHAT WE KNOW: - Core, Broker-Reliant, Account Managed; £3,383 6m GMV; Retailer, France; tenure 8 months. - Momentum: Lapsed; No Meaningful History (last GMV month: September); 3 orders over 1 month(s). - Dependency: High (broker reliance 66%; 2 AM-placed / 1 self-serve orders). - Engagement: 3 product views, 0 app days, 1 offer(s), 8 Fleek chats, 0 video requests; basket Bundle-only. WHAT TO DO: Do not assume churn. Verify expected purchase frequency first, then set the next contact window. WHAT NOT TO DO: Do not treat as churn or run a discount-led win-back. SUCCESS: Cadence recorded and account reclassified, or a new order within 90 days (60 days for recent-inactivity checks). | AC31: No Meaningful History | AD31: Existing Customer | AE31: =FALSE() -> FALSE | AF31: Not Eligible | AG31: Lumpy | AH31: N/A | AI31: If an order appears, the account re-segments automatically; if confirmed seasonal, suppress re-contact until the stated window. | AJ31: BASELINE | AK31: BASELINE | AL31: a9062c502f88
A32: ACC-045 | B32: P1 | C32: Core | D32: 3331 | E32: 2. Protect / Retain First | F32: Retention Conversation | G32: DECLINING_KEY_CORE | H32: Ready — Human | I32: Draft Ready | J32: Account Manager | K32: =FALSE() -> FALSE | L32: =FALSE() -> FALSE | M32: PB01_RETENTION | N32: Personal email from AM, then call | O32: Read brief; send outreach to book a review call. | P32: 7 | Q32: Root cause logged and next-90-day GMV back to at least the Sep-Nov (H1) level, or the decline arrested. | R32: Customer confirms a planned pause/seasonal gap (log cadence), or no response after 2 attempts (escalate). | S32: No response after 2 attempts, or Key account with further decline -> Portfolio Lead. | U32: Draft ready (not sent) | V32: RET_AM | W32: Hi {first_name}, I'd like to set up a short call to review how sourcing through Fleek is working for you at the moment and what you're planning to buy over the next few months. It will help me make sure the stock I source for you (bundles and handpicked stock) is the right fit. Would sometime later this week or early next week suit you? Best, {sender_name} | X32: WHY NOW: Commercially important, broker-led spend is falling. WHAT WE KNOW: - Core, Broker-Reliant, Account Managed; £3,331 6m GMV; Reseller, New Zealand; tenure 7 months. - Momentum: Declining (Sep-Nov £2,556 -> Dec-Feb £775); Recently Active (last GMV month: February); 18 orders over 5 month(s). - Dependency: Medium (broker reliance 52%; 9 AM-placed / 9 self-serve orders). - Engagement: 13 product views, 2 app days, 2 offer(s), 9 Fleek chats, 1 video requests; basket Mixed. WHAT TO DO: Book a conversation. Explore stock availability, price, assortment fit, buying cadence, competitor/offline wholesaler use and operational friction. Agree a recovery plan. WHAT NOT TO DO: Do not reduce AM support or push migration; do not suggest the customer is at fault; do not propose chat/video/feature usage as the fix. SUCCESS: Root cause logged and next-90-day GMV back to at least the Sep-Nov (H1) level, or the decline arrested. | AC32: Recently Active | AD32: Existing Customer | AE32: =FALSE() -> FALSE | AF32: Not Eligible | AG32: Regular | AH32: N/A | AI32: Stay in playbook while momentum is Declining; exit when momentum is Stable/Growing for a full run; if the account lapses, NBA moves to Verify/Win-Back. | AJ32: BASELINE | AK32: BASELINE | AL32: c17333135b8d
A33: ACC-046 | B33: P1 | C33: Core | D33: 3283 | E33: 2. Protect / Retain First | F33: Retention Conversation | G33: DECLINING_KEY_CORE | H33: Ready — Human | I33: Draft Ready | J33: Account Manager | K33: =FALSE() -> FALSE | L33: =FALSE() -> FALSE | M33: PB01_RETENTION | N33: Personal email from AM, then call | O33: Read brief; send outreach to book a review call. | P33: 7 | Q33: Root cause logged and next-90-day GMV back to at least the Sep-Nov (H1) level, or the decline arrested. | R33: Customer confirms a planned pause/seasonal gap (log cadence), or no response after 2 attempts (escalate). | S33: No response after 2 attempts, or Key account with further decline -> Portfolio Lead. | T33: FEB_SENSITIVE; H2_SINGLE_MONTH_SPIKE | U33: Draft ready (not sent) | V33: RET_AM | W33: Hi {first_name}, I'd like to set up a short call to review how sourcing through Fleek is working for you at the moment and what you're planning to buy over the next few months. It will help me make sure the stock I source for you (handpicked stock) is the right fit. Would sometime later this week or early next week suit you? Best, {sender_name} | X33: WHY NOW: Commercially important, broker-led spend is falling. WHAT WE KNOW: - Core, Broker-Reliant, Account Managed; £3,283 6m GMV; Reseller, Portugal; tenure 11 months. - Momentum: Declining (Sep-Nov £2,081 -> Dec-Feb £1,202); Recently Active (last GMV month: February); 3 orders over 2 month(s). - Dependency: High (broker reliance 60%; 2 AM-placed / 1 self-serve orders). - Engagement: 1 product views, 1 app days, 1 offer(s), 27 Fleek chats, 0 video requests; basket Handpick-only. - Warnings: FEB_SENSITIVE; H2_SINGLE_MONTH_SPIKE. WHAT TO DO: Book a conversation. Explore stock availability, price, assortment fit, buying cadence, competitor/offline wholesaler use and operational friction. Agree a recovery plan. WHAT NOT TO DO: Do not reduce AM support or push migration; do not suggest the customer is at fault; do not propose chat/video/feature usage as the fix. SUCCESS: Root cause logged and next-90-day GMV back to at least the Sep-Nov (H1) level, or the decline arrested. | AC33: Recently Active | AD33: Existing Customer | AE33: =FALSE() -> FALSE | AF33: Not Eligible | AG33: Lumpy | AH33: N/A | AI33: Stay in playbook while momentum is Declining; exit when momentum is Stable/Growing for a full run; if the account lapses, NBA moves to Verify/Win-Back. | AJ33: BASELINE | AK33: BASELINE | AL33: 22073667808a
A34: ACC-050 | B34: P1 | C34: Core | D34: 3044 | E34: 3. Win-Back / Verify | F34: Verify Demand / Win-Back | G34: LAPSED_THIN_HISTORY | H34: Ready — Human | I34: Draft Ready | J34: Account Manager | K34: =FALSE() -> FALSE | L34: =FALSE() -> FALSE | M34: PB02_VERIFY_WINBACK | N34: Personal email from AM, then call | O34: Send cadence check-in (verify, don't assume churn). | P34: 14 | Q34: Cadence recorded and account reclassified, or a new order within 90 days (60 days for recent-inactivity checks). | R34: Customer confirms infrequent/seasonal buying (set a reminder for their window) or confirms churn (log reason). | S34: Key account with no response after 2 attempts -> Portfolio Lead. | U34: Draft ready (not sent) | V34: VERIFY_CADENCE | W34: Hi {first_name}, Thanks for your previous orders with Fleek. I wanted to check how you usually plan your stock buying (seasonal, project by project, or ongoing) so we can get in touch at the right moments rather than too often. Happy to talk on a quick call, or just reply here with what works for you. Best, {sender_name} | X34: WHY NOW: Apparent lapse rests on 1-2 orders or one buying month; cadence is unknown. WHAT WE KNOW: - Core, Broker-Reliant, Account Managed; £3,044 6m GMV; Reseller, Germany; tenure 7 months. - Momentum: Lapsed; No Meaningful History (last GMV month: October); 6 orders over 1 month(s). - Dependency: Medium (broker reliance 46%; 3 AM-placed / 3 self-serve orders). - Engagement: 9 product views, 5 app days, 1 offer(s), 79 Fleek chats, 1 video requests; basket Mixed. WHAT TO DO: Do not assume churn. Verify expected purchase frequency first, then set the next contact window. WHAT NOT TO DO: Do not treat as churn or run a discount-led win-back. SUCCESS: Cadence recorded and account reclassified, or a new order within 90 days (60 days for recent-inactivity checks). | AC34: No Meaningful History | AD34: Existing Customer | AE34: =FALSE() -> FALSE | AF34: Not Eligible | AG34: Lumpy | AH34: N/A | AI34: If an order appears, the account re-segments automatically; if confirmed seasonal, suppress re-contact until the stated window. | AJ34: BASELINE | AK34: BASELINE | AL34: 40b9f8023762
A35: ACC-051 | B35: P1 | C35: Core | D35: 2992 | E35: 8. Retention / Reactivation | F35: Retention Conversation | G35: ENGAGED_BUT_SHRINKING | H35: Ready — Human | I35: Draft Ready | J35: Account Manager | K35: =FALSE() -> FALSE | L35: =FALSE() -> FALSE | M35: PB01_RETENTION | N35: Personal email from AM, then call | O35: Read brief; send outreach to book a call. | P35: 7 | Q35: Root cause logged and next-90-day GMV back to at least the Sep-Nov (H1) level, or the decline arrested. | R35: Customer confirms a planned pause/seasonal gap (log cadence), or no response after 2 attempts (escalate). | S35: No response after 2 attempts, or Key account with further decline -> Portfolio Lead. | U35: Draft ready (not sent) | V35: RET_AM | W35: Hi {first_name}, I'd like to set up a short call to review how sourcing through Fleek is working for you at the moment and what you're planning to buy over the next few months. It will help me make sure the stock I source for you (bundles and handpicked stock) is the right fit. Would sometime later this week or early next week suit you? Best, {sender_name} | X35: WHY NOW: Heavily self-serving account whose spend is falling; product adoption is not the issue. WHAT WE KNOW: - Core, AM-Owned / Self-Serving, Account Managed; £2,992 6m GMV; Reseller, Austria; tenure 8 months. - Momentum: Declining (Sep-Nov £1,724 -> Dec-Feb £1,268); Recently Active (last GMV month: February); 7 orders over 4 month(s). - Dependency: Low (broker reliance 12%; 1 AM-placed / 6 self-serve orders). - Engagement: 2403 product views, 113 app days, 4 offer(s), 18 Fleek chats, 0 video requests; basket Mixed. WHAT TO DO: Book a conversation. The customer already uses the product heavily: explore stock availability, price, offer outcomes and competitor use. WHAT NOT TO DO: Do not send more product nudges - engagement is not the problem. SUCCESS: Root cause logged and next-90-day GMV back to at least the Sep-Nov (H1) level, or the decline arrested. | AC35: Recently Active | AD35: Existing Customer | AE35: =FALSE() -> FALSE | AF35: Not Eligible | AG35: Regular | AH35: N/A | AI35: Stay in playbook while momentum is Declining; exit when momentum is Stable/Growing for a full run; if the account lapses, NBA moves to Verify/Win-Back. | AJ35: BASELINE | AK35: BASELINE | AL35: 8f849ec07bb5
A36: ACC-052 | B36: P1 | C36: Core | D36: 2952 | E36: 2. Protect / Retain First | F36: Retention Conversation | G36: DECLINING_KEY_CORE | H36: Ready — Human | I36: Draft Ready | J36: Account Manager | K36: =FALSE() -> FALSE | L36: =FALSE() -> FALSE | M36: PB01_RETENTION | N36: Personal email from AM, then call | O36: Read brief; send outreach to book a review call. | P36: 7 | Q36: Root cause logged and next-90-day GMV back to at least the Sep-Nov (H1) level, or the decline arrested. | R36: Customer confirms a planned pause/seasonal gap (log cadence), or no response after 2 attempts (escalate). | S36: No response after 2 attempts, or Key account with further decline -> Portfolio Lead. | T36: H2_SINGLE_MONTH_SPIKE | U36: Draft ready (not sent) | V36: RET_AM | W36: Hi {first_name}, I'd like to set up a short call to review how sourcing through Fleek is working for you at the moment and what you're planning to buy over the next few months. It will help me make sure the stock I source for you (bundles and handpicked stock) is the right fit. Would sometime later this week or early next week suit you? Best, {sender_name} | X36: WHY NOW: Commercially important, broker-led spend is falling. WHAT WE KNOW: - Core, Broker-Reliant, Account Managed; £2,952 6m GMV; Reseller, United Kingdom; tenure 6 months. - Momentum: Declining (Sep-Nov £2,249 -> Dec-Feb £703); Recent Inactivity (last GMV month: December); 8 orders over 3 month(s). - Dependency: High (broker reliance 64%; 5 AM-placed / 3 self-serve orders). - Engagement: 8 product views, 6 app days, 2 offer(s), 10 Fleek chats, 4 video requests; basket Mixed. - Warnings: H2_SINGLE_MONTH_SPIKE. WHAT TO DO: Book a conversation. Explore stock availability, price, assortment fit, buying cadence, competitor/offline wholesaler use and operational friction. Agree a recovery plan. WHAT NOT TO DO: Do not reduce AM support or push migration; do not suggest the customer is at fault; do not propose chat/video/feature usage as the fix. SUCCESS: Root cause logged and next-90-day GMV back to at least the Sep-Nov (H1) level, or the decline arrested. | AC36: Recent Inactivity | AD36: Existing Customer | AE36: =FALSE() -> FALSE | AF36: Not Eligible | AG36: Regular | AH36: N/A | AI36: Stay in playbook while momentum is Declining; exit when momentum is Stable/Growing for a full run; if the account lapses, NBA moves to Verify/Win-Back. | AJ36: BASELINE | AK36: BASELINE | AL36: 3949b831e958
A37: ACC-053 | B37: P1 | C37: Core | D37: 2581 | E37: 2. Protect / Retain First | F37: Retention Conversation | G37: DECLINING_KEY_CORE | H37: Ready — Human | I37: Draft Ready | J37: Account Manager | K37: =FALSE() -> FALSE | L37: =FALSE() -> FALSE | M37: PB01_RETENTION | N37: Personal email from AM, then call | O37: Read brief; send outreach to book a review call. | P37: 7 | Q37: Root cause logged and next-90-day GMV back to at least the Sep-Nov (H1) level, or the decline arrested. | R37: Customer confirms a planned pause/seasonal gap (log cadence), or no response after 2 attempts (escalate). | S37: No response after 2 attempts, or Key account with further decline -> Portfolio Lead. | T37: FEB_SENSITIVE; H2_SINGLE_MONTH_SPIKE | U37: Draft ready (not sent) | V37: RET_AM | W37: Hi {first_name}, I'd like to set up a short call to review how sourcing through Fleek is working for you at the moment and what you're planning to buy over the next few months. It will help me make sure the stock I source for you (bundles and handpicked stock) is the right fit. Would sometime later this week or early next week suit you? Best, {sender_name} | X37: WHY NOW: Commercially important, broker-led spend is falling. WHAT WE KNOW: - Core, Broker-Reliant, Account Managed; £2,581 6m GMV; Reseller, Czech Republic; tenure 14 months. - Momentum: Declining (Sep-Nov £2,493 -> Dec-Feb £87); Recently Active (last GMV month: February); 7 orders over 4 month(s). - Dependency: High (broker reliance 82%; 6 AM-placed / 1 self-serve orders). - Engagement: 3 product views, 7 app days, 1 offer(s), 166 Fleek chats, 0 video requests; basket Mixed. - Warnings: FEB_SENSITIVE; H2_SINGLE_MONTH_SPIKE. WHAT TO DO: Book a conversation. Explore stock availability, price, assortment fit, buying cadence, competitor/offline wholesaler use and operational friction. Agree a recovery plan. WHAT NOT TO DO: Do not reduce AM support or push migration; do not suggest the customer is at fault; do not propose chat/video/feature usage as the fix. SUCCESS: Root cause logged and next-90-day GMV back to at least the Sep-Nov (H1) level, or the decline arrested. | AC37: Recently Active | AD37: Existing Customer | AE37: =FALSE() -> FALSE | AF37: Not Eligible | AG37: Regular | AH37: N/A | AI37: Stay in playbook while momentum is Declining; exit when momentum is Stable/Growing for a full run; if the account lapses, NBA moves to Verify/Win-Back. | AJ37: BASELINE | AK37: BASELINE | AL37: 09ce1ffaedd3
A38: ACC-054 | B38: P1 | C38: Core | D38: 2516 | E38: 2. Protect / Retain First | F38: Retention Conversation | G38: DECLINING_KEY_CORE | H38: Ready — Human | I38: Draft Ready | J38: Account Manager | K38: =FALSE() -> FALSE | L38: =FALSE() -> FALSE | M38: PB01_RETENTION | N38: Personal email from AM, then call | O38: Read brief; send outreach to book a review call. | P38: 7 | Q38: Root cause logged and next-90-day GMV back to at least the Sep-Nov (H1) level, or the decline arrested. | R38: Customer confirms a planned pause/seasonal gap (log cadence), or no response after 2 attempts (escalate). | S38: No response after 2 attempts, or Key account with further decline -> Portfolio Lead. | U38: Draft ready (not sent) | V38: RET_AM | W38: Hi {first_name}, I'd like to set up a short call to review how sourcing through Fleek is working for you at the moment and what you're planning to buy over the next few months. It will help me make sure the stock I source for you (bundles and handpicked stock) is the right fit. Would sometime later this week or early next week suit you? Best, {sender_name} | X38: WHY NOW: Commercially important, broker-led spend is falling. WHAT WE KNOW: - Core, Broker-Reliant, Account Managed; £2,516 6m GMV; Reseller, United Kingdom; tenure 6 months. - Momentum: Declining (Sep-Nov £2,117 -> Dec-Feb £399); Recently Active (last GMV month: February); 9 orders over 5 month(s). - Dependency: High (broker reliance 77%; 7 AM-placed / 2 self-serve orders). - Engagement: 4 product views, 3 app days, 1 offer(s), 2 Fleek chats, 0 video requests; basket Mixed. WHAT TO DO: Book a conversation. Explore stock availability, price, assortment fit, buying cadence, competitor/offline wholesaler use and operational friction. Agree a recovery plan. WHAT NOT TO DO: Do not reduce AM support or push migration; do not suggest the customer is at fault; do not propose chat/video/feature usage as the fix. SUCCESS: Root cause logged and next-90-day GMV back to at least the Sep-Nov (H1) level, or the decline arrested. | AC38: Recently Active | AD38: Existing Customer | AE38: =FALSE() -> FALSE | AF38: Not Eligible | AG38: Regular | AH38: N/A | AI38: Stay in playbook while momentum is Declining; exit when momentum is Stable/Growing for a full run; if the account lapses, NBA moves to Verify/Win-Back. | AJ38: BASELINE | AK38: BASELINE | AL38: 44941c7c6027
A39: ACC-055 | B39: P1 | C39: Core | D39: 2514 | E39: 2. Protect / Retain First | F39: Retention Conversation | G39: DECLINING_KEY_CORE | H39: Ready — Human | I39: Draft Ready | J39: Account Manager | K39: =FALSE() -> FALSE | L39: =FALSE() -> FALSE | M39: PB01_RETENTION | N39: Personal email from AM, then call | O39: Read brief; send outreach to book a review call. | P39: 7 | Q39: Root cause logged and next-90-day GMV back to at least the Sep-Nov (H1) level, or the decline arrested. | R39: Customer confirms a planned pause/seasonal gap (log cadence), or no response after 2 attempts (escalate). | S39: No response after 2 attempts, or Key account with further decline -> Portfolio Lead. | U39: Draft ready (not sent) | V39: RET_AM | W39: Hi {first_name}, I'd like to set up a short call to review how sourcing through Fleek is working for you at the moment and what you're planning to buy over the next few months. It will help me make sure the stock I source for you (bundles) is the right fit. Would sometime later this week or early next week suit you? Best, {sender_name} | X39: WHY NOW: Commercially important, broker-led spend is falling. WHAT WE KNOW: - Core, Broker-Reliant, Account Managed; £2,514 6m GMV; Reseller, United Kingdom; tenure 17 months. - Momentum: Declining (Sep-Nov £2,221 -> Dec-Feb £293); Recently Active (last GMV month: February); 12 orders over 5 month(s). - Dependency: High (broker reliance 77%; 9 AM-placed / 3 self-serve orders). - Engagement: 14 product views, 5 app days, 2 offer(s), 13 Fleek chats, 0 video requests; basket Bundle-only. WHAT TO DO: Book a conversation. Explore stock availability, price, assortment fit, buying cadence, competitor/offline wholesaler use and operational friction. Agree a recovery plan. WHAT NOT TO DO: Do not reduce AM support or push migration; do not suggest the customer is at fault; do not propose chat/video/feature usage as the fix. SUCCESS: Root cause logged and next-90-day GMV back to at least the Sep-Nov (H1) level, or the decline arrested. | AC39: Recently Active | AD39: Existing Customer | AE39: =FALSE() -> FALSE | AF39: Not Eligible | AG39: Regular | AH39: N/A | AI39: Stay in playbook while momentum is Declining; exit when momentum is Stable/Growing for a full run; if the account lapses, NBA moves to Verify/Win-Back. | AJ39: BASELINE | AK39: BASELINE | AL39: 84ba41df31ac
A40: ACC-059 | B40: P1 | C40: Core | D40: 2262 | E40: 2. Protect / Retain First | F40: Retention Conversation | G40: DECLINING_KEY_CORE | H40: Ready — Human | I40: Draft Ready | J40: Account Manager | K40: =FALSE() -> FALSE | L40: =FALSE() -> FALSE | M40: PB01_RETENTION | N40: Personal email from AM, then call | O40: Read brief; send outreach to book a review call. | P40: 7 | Q40: Root cause logged and next-90-day GMV back to at least the Sep-Nov (H1) level, or the decline arrested. | R40: Customer confirms a planned pause/seasonal gap (log cadence), or no response after 2 attempts (escalate). | S40: No response after 2 attempts, or Key account with further decline -> Portfolio Lead. | T40: BORDERLINE_MOMENTUM; FEB_SENSITIVE; H2_SINGLE_MONTH_SPIKE | U40: Draft ready (not sent) | V40: RET_AM | W40: Hi {first_name}, I'd like to set up a short call to review how sourcing through Fleek is working for you at the moment and what you're planning to buy over the next few months. It will help me make sure the stock I source for you (handpicked stock) is the right fit. Would sometime later this week or early next week suit you? Best, {sender_name} | X40: WHY NOW: Commercially important, broker-led spend is falling. WHAT WE KNOW: - Core, Broker-Reliant, Account Managed; £2,262 6m GMV; Reseller, United Kingdom; tenure 21 months. - Momentum: Declining (Sep-Nov £1,268 -> Dec-Feb £995); Recent Inactivity (last GMV month: December); 3 orders over 3 month(s). - Dependency: High (broker reliance 75%; 2 AM-placed / 1 self-serve orders). - Engagement: 8 product views, 1 app days, 1 offer(s), 30 Fleek chats, 1 video requests; basket Handpick-only. - Warnings: BORDERLINE_MOMENTUM; FEB_SENSITIVE; H2_SINGLE_MONTH_SPIKE. WHAT TO DO: Book a conversation. Explore stock availability, price, assortment fit, buying cadence, competitor/offline wholesaler use and operational friction. Agree a recovery plan. WHAT NOT TO DO: Do not reduce AM support or push migration; do not suggest the customer is at fault; do not propose chat/video/feature usage as the fix. SUCCESS: Root cause logged and next-90-day GMV back to at least the Sep-Nov (H1) level, or the decline arrested. | AC40: Recent Inactivity | AD40: Existing Customer | AE40: =FALSE() -> FALSE | AF40: Not Eligible | AG40: Lumpy | AH40: N/A | AI40: Stay in playbook while momentum is Declining; exit when momentum is Stable/Growing for a full run; if the account lapses, NBA moves to Verify/Win-Back. | AJ40: BASELINE | AK40: BASELINE | AL40: 70b8c061b647
A41: ACC-060 | B41: P1 | C41: Core | D41: 2214 | E41: 3. Win-Back / Verify | F41: Verify Demand / Win-Back | G41: LAPSED_THIN_HISTORY | H41: Ready — Human | I41: Draft Ready | J41: Account Manager | K41: =FALSE() -> FALSE | L41: =FALSE() -> FALSE | M41: PB02_VERIFY_WINBACK | N41: Personal email from AM, then call | O41: Send cadence check-in (verify, don't assume churn). | P41: 14 | Q41: Cadence recorded and account reclassified, or a new order within 90 days (60 days for recent-inactivity checks). | R41: Customer confirms infrequent/seasonal buying (set a reminder for their window) or confirms churn (log reason). | S41: Key account with no response after 2 attempts -> Portfolio Lead. | T41: MATERIAL_BROKER_INCONSISTENCY | U41: Draft ready (not sent) | V41: VERIFY_CADENCE | W41: Hi {first_name}, Thanks for your previous orders with Fleek. I wanted to check how you usually plan your stock buying (seasonal, project by project, or ongoing) so we can get in touch at the right moments rather than too often. Happy to talk on a quick call, or just reply here with what works for you. Best, {sender_name} | X41: WHY NOW: Apparent lapse rests on 1-2 orders or one buying month; cadence is unknown. WHAT WE KNOW: - Core, Broker-Reliant, Account Managed; £2,214 6m GMV; Retailer, France; tenure 28 months. - Momentum: Lapsed; No Meaningful History (last GMV month: September); 3 orders over 1 month(s). - Dependency: High (broker reliance 80%; 2 AM-placed / 1 self-serve orders). - Engagement: 1 product views, 4 app days, 1 offer(s), 96 Fleek chats, 0 video requests; basket Bundle-only. - Warnings: MATERIAL_BROKER_INCONSISTENCY. WHAT TO DO: Do not assume churn. Verify expected purchase frequency first, then set the next contact window. WHAT NOT TO DO: Do not treat as churn or run a discount-led win-back. SUCCESS: Cadence recorded and account reclassified, or a new order within 90 days (60 days for recent-inactivity checks). | AC41: No Meaningful History | AD41: Existing Customer | AE41: =FALSE() -> FALSE | AF41: Not Eligible | AG41: Lumpy | AH41: N/A | AI41: If an order appears, the account re-segments automatically; if confirmed seasonal, suppress re-contact until the stated window. | AJ41: BASELINE | AK41: BASELINE | AL41: 78939faa3343
A42: ACC-061 | B42: P1 | C42: Core | D42: 2116 | E42: 2. Protect / Retain First | F42: Retention Conversation | G42: DECLINING_KEY_CORE | H42: Ready — Human | I42: Draft Ready | J42: Account Manager | K42: =FALSE() -> FALSE | L42: =FALSE() -> FALSE | M42: PB01_RETENTION | N42: Personal email from AM, then call | O42: Read brief; send outreach to book a review call. | P42: 7 | Q42: Root cause logged and next-90-day GMV back to at least the Sep-Nov (H1) level, or the decline arrested. | R42: Customer confirms a planned pause/seasonal gap (log cadence), or no response after 2 attempts (escalate). | S42: No response after 2 attempts, or Key account with further decline -> Portfolio Lead. | T42: H2_SINGLE_MONTH_SPIKE | U42: Draft ready (not sent) | V42: RET_AM | W42: Hi {first_name}, I'd like to set up a short call to review how sourcing through Fleek is working for you at the moment and what you're planning to buy over the next few months. It will help me make sure the stock I source for you (bundles) is the right fit. Would sometime later this week or early next week suit you? Best, {sender_name} | X42: WHY NOW: Commercially important, broker-led spend is falling. WHAT WE KNOW: - Core, Broker-Reliant, Account Managed; £2,116 6m GMV; Reseller, Portugal; tenure 7 months. - Momentum: Declining (Sep-Nov £1,553 -> Dec-Feb £563); Recent Inactivity (last GMV month: December); 4 orders over 3 month(s). - Dependency: High (broker reliance 63%; 3 AM-placed / 1 self-serve orders). - Engagement: 11 product views, 3 app days, 1 offer(s), 2 Fleek chats, 0 video requests; basket Bundle-only. - Warnings: H2_SINGLE_MONTH_SPIKE. WHAT TO DO: Book a conversation. Explore stock availability, price, assortment fit, buying cadence, competitor/offline wholesaler use and operational friction. Agree a recovery plan. WHAT NOT TO DO: Do not reduce AM support or push migration; do not suggest the customer is at fault; do not propose chat/video/feature usage as the fix. SUCCESS: Root cause logged and next-90-day GMV back to at least the Sep-Nov (H1) level, or the decline arrested. | AC42: Recent Inactivity | AD42: Existing Customer | AE42: =FALSE() -> FALSE | AF42: Not Eligible | AG42: Lumpy | AH42: N/A | AI42: Stay in playbook while momentum is Declining; exit when momentum is Stable/Growing for a full run; if the account lapses, NBA moves to Verify/Win-Back. | AJ42: BASELINE | AK42: BASELINE | AL42: e28cb5549b54
A43: ACC-062 | B43: P1 | C43: Core | D43: 2031 | E43: 3. Win-Back / Verify | F43: Verify Demand / Win-Back | G43: LAPSED_ESTABLISHED | H43: Ready — Human | I43: Draft Ready | J43: Account Manager | K43: =FALSE() -> FALSE | L43: =FALSE() -> FALSE | M43: PB02_VERIFY_WINBACK | N43: Personal email from AM, then call | O43: Send win-back check-in. | P43: 14 | Q43: Cadence recorded and account reclassified, or a new order within 90 days (60 days for recent-inactivity checks). | R43: Customer confirms infrequent/seasonal buying (set a reminder for their window) or confirms churn (log reason). | S43: Key account with no response after 2 attempts -> Portfolio Lead. | U43: Draft ready (not sent) | V43: WINBACK | W43: Hi {first_name}, It's been a little while since we last caught up, so I wanted to check in on your buying plans for the coming months. If you're sourcing bundles again soon, I'd be glad to talk through what you're looking for and how we can help. Would a quick call be useful? Best, {sender_name} | X43: WHY NOW: Established buyer with a repeat pattern has had no GMV since November or earlier. WHAT WE KNOW: - Core, Broker-Reliant, Account Managed; £2,031 6m GMV; Reseller, United Kingdom; tenure 14 months. - Momentum: Lapsed; Recent Inactivity (last GMV month: November); 5 orders over 3 month(s). - Dependency: Medium (broker reliance 47%; 2 AM-placed / 3 self-serve orders). - Engagement: 0 product views, 6 app days, 0 offer(s), 5 Fleek chats, 0 video requests; basket Bundle-only. WHAT TO DO: Win-back conversation about upcoming buying needs and what would bring them back. WHAT NOT TO DO: Do not say 'you churned' or 'you've stopped buying'. SUCCESS: Cadence recorded and account reclassified, or a new order within 90 days (60 days for recent-inactivity checks). | AC43: Recent Inactivity | AD43: Existing Customer | AE43: =FALSE() -> FALSE | AF43: Not Eligible | AG43: Regular | AH43: N/A | AI43: If an order appears, the account re-segments automatically; if confirmed seasonal, suppress re-contact until the stated window. | AJ43: BASELINE | AK43: BASELINE | AL43: 83b24c3c09c6
A44: ACC-001 | B44: P2 | C44: Key | D44: 170132 | E44: 1. Migration Candidate | F44: Guided Self-Serve Migration | G44: MIGRATION_KEY_SIGNOFF | H44: Human Sign-Off Required | I44: Awaiting Sign-Off | J44: Portfolio Lead + Account Manager | K44: =FALSE() -> FALSE | L44: =FALSE() -> FALSE | M44: PB03_GUIDED_MIGRATION | N44: AM call + in-app walkthrough; automated milestone tracking | O44: Portfolio Lead + AM sign-off decision on a gradual self-serve shift. | P44: 15 | Q44: Day 90: Self-Serve Capability Demonstrated (>=25 PDP views, >=6 app days, self-serve share above baseline) with GMV guardrail held. | R44: GMV guardrail breached (At Risk) -> restore high-touch support; no behaviour change at day 90 -> reassess suitability. | S44: At Risk at day 45; any Key account change; customer pushback on the change. | T44: KEY_SIGNOFF; BORDERLINE_MOMENTUM; FEB_SENSITIVE | U44: Withheld until sign-off is recorded | X44: WHY NOW: Key broker-reliant account with healthy spend; downside risk too large for automated initiation. WHAT WE KNOW: - Key, Broker-Reliant, Account Managed; £170,132 6m GMV; Retailer, United Kingdom; tenure 26 months. - Momentum: Stable (Sep-Nov £93,545 -> Dec-Feb £76,587); Recently Active (last GMV month: February); 46 orders over 6 month(s). - Dependency: High (broker reliance 69%; 32 AM-placed / 14 self-serve orders). - Engagement: 2 product views, 3 app days, 0 offer(s), 139 Fleek chats, 3 video requests; basket Mixed. - Warnings: KEY_SIGNOFF; BORDERLINE_MOMENTUM; FEB_SENSITIVE. WHAT TO DO: Portfolio Lead and AM decide whether a gradual self-serve shift is appropriate. Record approve / decline and conditions. WHAT NOT TO DO: No migration communication before sign-off. SUCCESS: Day 90: Self-Serve Capability Demonstrated (>=25 PDP views, >=6 app days, self-serve share above baseline) with GMV guardrail held. | AC44: Recently Active | AD44: Existing Customer | AE44: =FALSE() -> FALSE | AF44: Not Eligible | AG44: Regular | AH44: Baseline | AI44: Enter 90-day monitoring inputs; migration_progress_status updates (Baseline/Progressing/Capability/At Risk). Day-90 outcomes: Capability Demonstrated, Progressing - Extend, At Risk - Restore support, No Change - Reassess. | AJ44: BASELINE | AK44: BASELINE | AL44: 0fcb61d89d13
A45: ACC-003 | B45: P2 | C45: Key | D45: 41039 | E45: 1. Migration Candidate | F45: Guided Self-Serve Migration | G45: MIGRATION_KEY_SIGNOFF | H45: Human Sign-Off Required | I45: Awaiting Sign-Off | J45: Portfolio Lead + Account Manager | K45: =FALSE() -> FALSE | L45: =FALSE() -> FALSE | M45: PB03_GUIDED_MIGRATION | N45: AM call + in-app walkthrough; automated milestone tracking | O45: Portfolio Lead + AM sign-off decision on a gradual self-serve shift. | P45: 15 | Q45: Day 90: Self-Serve Capability Demonstrated (>=25 PDP views, >=6 app days, self-serve share above baseline) with GMV guardrail held. | R45: GMV guardrail breached (At Risk) -> restore high-touch support; no behaviour change at day 90 -> reassess suitability. | S45: At Risk at day 45; any Key account change; customer pushback on the change. | T45: KEY_SIGNOFF; BORDERLINE_MOMENTUM; FEB_SENSITIVE | U45: Withheld until sign-off is recorded | X45: WHY NOW: Key broker-reliant account with healthy spend; downside risk too large for automated initiation. WHAT WE KNOW: - Key, Broker-Reliant, Account Managed; £41,039 6m GMV; Reseller, Germany; tenure 16 months. - Momentum: Stable (Sep-Nov £22,792 -> Dec-Feb £18,249); Recently Active (last GMV month: February); 36 orders over 6 month(s). - Dependency: High (broker reliance 74%; 27 AM-placed / 9 self-serve orders). - Engagement: 5 product views, 1 app days, 2 offer(s), 129 Fleek chats, 18 video requests; basket Mixed. - Warnings: KEY_SIGNOFF; BORDERLINE_MOMENTUM; FEB_SENSITIVE. WHAT TO DO: Portfolio Lead and AM decide whether a gradual self-serve shift is appropriate. Record approve / decline and conditions. WHAT NOT TO DO: No migration communication before sign-off. SUCCESS: Day 90: Self-Serve Capability Demonstrated (>=25 PDP views, >=6 app days, self-serve share above baseline) with GMV guardrail held. | AC45: Recently Active | AD45: Existing Customer | AE45: =FALSE() -> FALSE | AF45: Not Eligible | AG45: Regular | AH45: Baseline | AI45: Enter 90-day monitoring inputs; migration_progress_status updates (Baseline/Progressing/Capability/At Risk). Day-90 outcomes: Capability Demonstrated, Progressing - Extend, At Risk - Restore support, No Change - Reassess. | AJ45: BASELINE | AK45: BASELINE | AL45: 540a58c7127b
A46: ACC-004 | B46: P2 | C46: Key | D46: 27099 | E46: 1. Migration Candidate | F46: Guided Self-Serve Migration | G46: MIGRATION_KEY_SIGNOFF | H46: Human Sign-Off Required | I46: Awaiting Sign-Off | J46: Portfolio Lead + Account Manager | K46: =FALSE() -> FALSE | L46: =FALSE() -> FALSE | M46: PB03_GUIDED_MIGRATION | N46: AM call + in-app walkthrough; automated milestone tracking | O46: Portfolio Lead + AM sign-off decision on a gradual self-serve shift. | P46: 15 | Q46: Day 90: Self-Serve Capability Demonstrated (>=25 PDP views, >=6 app days, self-serve share above baseline) with GMV guardrail held. | R46: GMV guardrail breached (At Risk) -> restore high-touch support; no behaviour change at day 90 -> reassess suitability. | S46: At Risk at day 45; any Key account change; customer pushback on the change. | T46: KEY_SIGNOFF; BORDERLINE_MOMENTUM | U46: Withheld until sign-off is recorded | X46: WHY NOW: Key broker-reliant account with healthy spend; downside risk too large for automated initiation. WHAT WE KNOW: - Key, Broker-Reliant, Account Managed; £27,099 6m GMV; Reseller, Australia; tenure 22 months. - Momentum: Stable (Sep-Nov £14,705 -> Dec-Feb £12,395); Recently Active (last GMV month: February); 19 orders over 6 month(s). - Dependency: High (broker reliance 62%; 12 AM-placed / 7 self-serve orders). - Engagement: 3 product views, 8 app days, 2 offer(s), 20 Fleek chats, 1 video requests; basket Handpick-only. - Warnings: KEY_SIGNOFF; BORDERLINE_MOMENTUM. WHAT TO DO: Portfolio Lead and AM decide whether a gradual self-serve shift is appropriate. Record approve / decline and conditions. WHAT NOT TO DO: No migration communication before sign-off. SUCCESS: Day 90: Self-Serve Capability Demonstrated (>=25 PDP views, >=6 app days, self-serve share above baseline) with GMV guardrail held. | AC46: Recently Active | AD46: Existing Customer | AE46: =FALSE() -> FALSE | AF46: Not Eligible | AG46: Regular | AH46: Baseline | AI46: Enter 90-day monitoring inputs; migration_progress_status updates (Baseline/Progressing/Capability/At Risk). Day-90 outcomes: Capability Demonstrated, Progressing - Extend, At Risk - Restore support, No Change - Reassess. | AJ46: BASELINE | AK46: BASELINE | AL46: 08d49164fd60
A47: ACC-006 | B47: P2 | C47: Key | D47: 23205 | E47: 1. Migration Candidate | F47: Guided Self-Serve Migration | G47: MIGRATION_KEY_SIGNOFF | H47: Human Sign-Off Required | I47: Awaiting Sign-Off | J47: Portfolio Lead + Account Manager | K47: =FALSE() -> FALSE | L47: =FALSE() -> FALSE | M47: PB03_GUIDED_MIGRATION | N47: AM call + in-app walkthrough; automated milestone tracking | O47: Portfolio Lead + AM sign-off decision on a gradual self-serve shift. | P47: 15 | Q47: Day 90: Self-Serve Capability Demonstrated (>=25 PDP views, >=6 app days, self-serve share above baseline) with GMV guardrail held. | R47: GMV guardrail breached (At Risk) -> restore high-touch support; no behaviour change at day 90 -> reassess suitability. | S47: At Risk at day 45; any Key account change; customer pushback on the change. | T47: KEY_SIGNOFF | U47: Withheld until sign-off is recorded | X47: WHY NOW: Key broker-reliant account with healthy spend; downside risk too large for automated initiation. WHAT WE KNOW: - Key, Broker-Reliant, Account Managed; £23,205 6m GMV; Reseller, Germany; tenure 7 months. - Momentum: Growing (Sep-Nov £8,249 -> Dec-Feb £14,956); Recently Active (last GMV month: February); 14 orders over 5 month(s). - Dependency: High (broker reliance 84%; 12 AM-placed / 2 self-serve orders). - Engagement: 8 product views, 3 app days, 1 offer(s), 115 Fleek chats, 24 video requests; basket Handpick-only. - Warnings: KEY_SIGNOFF. WHAT TO DO: Portfolio Lead and AM decide whether a gradual self-serve shift is appropriate. Record approve / decline and conditions. WHAT NOT TO DO: No migration communication before sign-off. SUCCESS: Day 90: Self-Serve Capability Demonstrated (>=25 PDP views, >=6 app days, self-serve share above baseline) with GMV guardrail held. | AC47: Recently Active | AD47: Existing Customer | AE47: =FALSE() -> FALSE | AF47: Not Eligible | AG47: Regular | AH47: Baseline | AI47: Enter 90-day monitoring inputs; migration_progress_status updates (Baseline/Progressing/Capability/At Risk). Day-90 outcomes: Capability Demonstrated, Progressing - Extend, At Risk - Restore support, No Change - Reassess. | AJ47: BASELINE | AK47: BASELINE | AL47: e3d57b7950e8
A48: ACC-007 | B48: P2 | C48: Key | D48: 22089 | E48: 1. Migration Candidate | F48: Guided Self-Serve Migration | G48: MIGRATION_KEY_SIGNOFF | H48: Human Sign-Off Required | I48: Awaiting Sign-Off | J48: Portfolio Lead + Account Manager | K48: =FALSE() -> FALSE | L48: =FALSE() -> FALSE | M48: PB03_GUIDED_MIGRATION | N48: AM call + in-app walkthrough; automated milestone tracking | O48: Portfolio Lead + AM sign-off decision on a gradual self-serve shift. | P48: 15 | Q48: Day 90: Self-Serve Capability Demonstrated (>=25 PDP views, >=6 app days, self-serve share above baseline) with GMV guardrail held. | R48: GMV guardrail breached (At Risk) -> restore high-touch support; no behaviour change at day 90 -> reassess suitability. | S48: At Risk at day 45; any Key account change; customer pushback on the change. | T48: KEY_SIGNOFF | U48: Withheld until sign-off is recorded | X48: WHY NOW: Key broker-reliant account with healthy spend; downside risk too large for automated initiation. WHAT WE KNOW: - Key, Broker-Reliant, Account Managed; £22,089 6m GMV; Reseller, Austria; tenure 10 months. - Momentum: Growing (Sep-Nov £5,524 -> Dec-Feb £16,565); Recently Active (last GMV month: February); 23 orders over 5 month(s). - Dependency: High (broker reliance 72%; 17 AM-placed / 6 self-serve orders). - Engagement: 1 product views, 1 app days, 0 offer(s), 69 Fleek chats, 2 video requests; basket Mixed. - Warnings: KEY_SIGNOFF. WHAT TO DO: Portfolio Lead and AM decide whether a gradual self-serve shift is appropriate. Record approve / decline and conditions. WHAT NOT TO DO: No migration communication before sign-off. SUCCESS: Day 90: Self-Serve Capability Demonstrated (>=25 PDP views, >=6 app days, self-serve share above baseline) with GMV guardrail held. | AC48: Recently Active | AD48: Existing Customer | AE48: =FALSE() -> FALSE | AF48: Not Eligible | AG48: Regular | AH48: Baseline | AI48: Enter 90-day monitoring inputs; migration_progress_status updates (Baseline/Progressing/Capability/At Risk). Day-90 outcomes: Capability Demonstrated, Progressing - Extend, At Risk - Restore support, No Change - Reassess. | AJ48: BASELINE | AK48: BASELINE | AL48: 5d2eb2a4b67f
A49: ACC-011 | B49: P2 | C49: Key | D49: 15600 | E49: 4. Establish / Re-establish / Observe | F49: Establish / Re-establish | G49: RETURNED_CUSTOMER | H49: Ready — Human | I49: Draft Ready | J49: Account Manager | K49: =FALSE() -> FALSE | L49: =FALSE() -> FALSE | M49: PB04_ESTABLISH | N49: Personal email from AM, then call | O49: Send welcome-back outreach; book a call. | P49: 10 | Q49: New: 2+ orders across 2+ months within 90 days. Returned: orders in at least 2 of the next 3 months. | R49: Second order placed (new) or cadence agreed (returned). | S49: Returned Key account with no response after 2 attempts -> Portfolio Lead. | T49: MATERIAL_BROKER_INCONSISTENCY; LOW_CONFIDENCE | U49: Draft ready (not sent) | V49: EST_RETURNED | W49: Hi {first_name}, Great to see you ordering with Fleek again. I'd love to catch up on what you're sourcing at the moment and how often you're planning to buy, so we can make sure the right handpicked stock is in front of you. Would a quick call in the next week or two work? Best, {sender_name} | X49: WHY NOW: Long-tenured customer returned in Dec-Feb after no Sep-Nov spend. WHAT WE KNOW: - Key, Broker-Reliant, Account Managed; £15,600 6m GMV; Reseller, France; tenure 34 months. - Momentum: H2 Active / No H1 GMV; No Meaningful History (last GMV month: December); 1 orders over 1 month(s). - Dependency: Medium (broker reliance 50%; 1 AM-placed / 0 self-serve orders). - Engagement: 14 product views, 6 app days, 1 offer(s), 50 Fleek chats, 0 video requests; basket Handpick-only. - Warnings: MATERIAL_BROKER_INCONSISTENCY; LOW_CONFIDENCE. WHAT TO DO: Welcome-back conversation: what brought them back, what they are sourcing now, how often they plan to buy. WHAT NOT TO DO: Do not treat them as a brand-new customer. SUCCESS: New: 2+ orders across 2+ months within 90 days. Returned: orders in at least 2 of the next 3 months. | AC49: No Meaningful History | AD49: Returned Customer | AE49: =FALSE() -> FALSE | AF49: Not Eligible | AG49: Lumpy | AH49: N/A | AI49: Once H1/H2 history exists the account leaves this playbook automatically via re-segmentation. | AJ49: BASELINE | AK49: BASELINE | AL49: 7524c507b827
A50: ACC-012 | B50: P2 | C50: Key | D50: 14611 | E50: 1. Migration Candidate | F50: Guided Self-Serve Migration | G50: MIGRATION_KEY_SIGNOFF | H50: Human Sign-Off Required | I50: Awaiting Sign-Off | J50: Portfolio Lead + Account Manager | K50: =FALSE() -> FALSE | L50: =FALSE() -> FALSE | M50: PB03_GUIDED_MIGRATION | N50: AM call + in-app walkthrough; automated milestone tracking | O50: Portfolio Lead + AM sign-off decision on a gradual self-serve shift. | P50: 15 | Q50: Day 90: Self-Serve Capability Demonstrated (>=25 PDP views, >=6 app days, self-serve share above baseline) with GMV guardrail held. | R50: GMV guardrail breached (At Risk) -> restore high-touch support; no behaviour change at day 90 -> reassess suitability. | S50: At Risk at day 45; any Key account change; customer pushback on the change. | T50: KEY_SIGNOFF; MATERIAL_BROKER_INCONSISTENCY | U50: Withheld until sign-off is recorded | X50: WHY NOW: Key broker-reliant account with healthy spend; downside risk too large for automated initiation. WHAT WE KNOW: - Key, Broker-Reliant, Account Managed; £14,611 6m GMV; Reseller, United Kingdom; tenure 17 months. - Momentum: Growing (Sep-Nov £6,126 -> Dec-Feb £8,485); Recently Active (last GMV month: February); 28 orders over 6 month(s). - Dependency: High (broker reliance 59%; 17 AM-placed / 11 self-serve orders). - Engagement: 3 product views, 2 app days, 0 offer(s), 182 Fleek chats, 1 video requests; basket Mixed. - Warnings: KEY_SIGNOFF; MATERIAL_BROKER_INCONSISTENCY. WHAT TO DO: Portfolio Lead and AM decide whether a gradual self-serve shift is appropriate. Record approve / decline and conditions. WHAT NOT TO DO: No migration communication before sign-off. SUCCESS: Day 90: Self-Serve Capability Demonstrated (>=25 PDP views, >=6 app days, self-serve share above baseline) with GMV guardrail held. | AC50: Recently Active | AD50: Existing Customer | AE50: =FALSE() -> FALSE | AF50: Not Eligible | AG50: Regular | AH50: Baseline | AI50: Enter 90-day monitoring inputs; migration_progress_status updates (Baseline/Progressing/Capability/At Risk). Day-90 outcomes: Capability Demonstrated, Progressing - Extend, At Risk - Restore support, No Change - Reassess. | AJ50: BASELINE | AK50: BASELINE | AL50: b5cb9babc36d
A51: ACC-016 | B51: P2 | C51: Key | D51: 11252 | E51: 1. Migration Candidate | F51: Guided Self-Serve Migration | G51: MIGRATION_KEY_SIGNOFF | H51: Human Sign-Off Required | I51: Awaiting Sign-Off | J51: Portfolio Lead + Account Manager | K51: =FALSE() -> FALSE | L51: =FALSE() -> FALSE | M51: PB03_GUIDED_MIGRATION | N51: AM call + in-app walkthrough; automated milestone tracking | O51: Portfolio Lead + AM sign-off decision on a gradual self-serve shift. | P51: 15 | Q51: Day 90: Self-Serve Capability Demonstrated (>=25 PDP views, >=6 app days, self-serve share above baseline) with GMV guardrail held. | R51: GMV guardrail breached (At Risk) -> restore high-touch support; no behaviour change at day 90 -> reassess suitability. | S51: At Risk at day 45; any Key account change; customer pushback on the change. | T51: KEY_SIGNOFF; NO_FEB_GMV (Feb unconfirmed) | U51: Withheld until sign-off is recorded | X51: WHY NOW: Key broker-reliant account with healthy spend; downside risk too large for automated initiation. WHAT WE KNOW: - Key, Broker-Reliant, Account Managed; £11,252 6m GMV; Reseller, Australia; tenure 10 months. - Momentum: Growing (Sep-Nov £4,217 -> Dec-Feb £7,035); Recently Active (last GMV month: January); 26 orders over 5 month(s). - Dependency: High (broker reliance 68%; 18 AM-placed / 8 self-serve orders). - Engagement: 4 product views, 1 app days, 1 offer(s), 16 Fleek chats, 3 video requests; basket Bundle-only. - Warnings: KEY_SIGNOFF; NO_FEB_GMV (Feb unconfirmed). WHAT TO DO: Portfolio Lead and AM decide whether a gradual self-serve shift is appropriate. Record approve / decline and conditions. WHAT NOT TO DO: No migration communication before sign-off. SUCCESS: Day 90: Self-Serve Capability Demonstrated (>=25 PDP views, >=6 app days, self-serve share above baseline) with GMV guardrail held. | AC51: Recently Active | AD51: Existing Customer | AE51: =FALSE() -> FALSE | AF51: Not Eligible | AG51: Regular | AH51: Baseline | AI51: Enter 90-day monitoring inputs; migration_progress_status updates (Baseline/Progressing/Capability/At Risk). Day-90 outcomes: Capability Demonstrated, Progressing - Extend, At Risk - Restore support, No Change - Reassess. | AJ51: BASELINE | AK51: BASELINE | AL51: 37d831150a2a
A52: ACC-212 | B52: P2 | C52: Core | D52: 8581 | E52: 6. Growth Opportunity | F52: Reinforce Successful Behaviour | G52: HEALTHY_STRONG_SELF_SERVE | H52: Ready — Automated | I52: Draft Ready | J52: Automation | K52: =FALSE() -> FALSE | L52: =FALSE() -> FALSE | M52: PB06_REINFORCE | N52: Email / in-app message | O52: Queue automated message (Reinforce Successful Behaviour). | P52: 30 | Q52: GMV run-rate maintained or higher, with GMV in each month of the next quarter. | R52: Account shows Recent Inactivity (playbook must not run) or momentum turns Declining. | S52: Recent Inactivity -> Verify check (human). | U52: Draft ready (not sent) | V52: REINFORCE | W52: Hi {first_name}, Thanks for being an active Fleek buyer. Just a quick note to keep an eye on the app for bundles and handpicked stock that fits your range, and to let you know we're here if there's anything specific you're trying to source. Reply any time and we'll help. Best, {sender_name} | AC52: Recently Active | AD52: Existing Customer | AE52: =FALSE() -> FALSE | AF52: Not Eligible | AG52: Regular | AH52: N/A | AI52: Suppressed if Recent Inactivity; otherwise no repeat inside 30 days. | AJ52: BASELINE | AK52: BASELINE | AL52: aa1e187383b5
A53: ACC-019 | B53: P2 | C53: Core | D53: 7716 | E53: 1. Migration Candidate | F53: Guided Self-Serve Migration | G53: MIGRATION_PHASE1_READY | H53: Ready — Hybrid | I53: Draft Ready | J53: Account Manager | K53: =FALSE() -> FALSE | L53: =FALSE() -> FALSE | M53: PB03_GUIDED_MIGRATION | N53: AM call + in-app walkthrough; automated milestone tracking | O53: Day 0: AM walkthrough call on independent stock discovery. | P53: 15 | Q53: Day 90: Self-Serve Capability Demonstrated (>=25 PDP views, >=6 app days, self-serve share above baseline) with GMV guardrail held. | R53: GMV guardrail breached (At Risk) -> restore high-touch support; no behaviour change at day 90 -> reassess suitability. | S53: At Risk at day 45; any Key account change; customer pushback on the change. | U53: Draft ready (not sent) | V53: MIG_DAY0 | W53: Hi {first_name}, Alongside the stock I source for you, I'd like to show you how to browse Fleek's full range directly in the app, so you can look through handpicked stock whenever it suits you, make an offer where it fits and place orders yourself. I'm still here for anything you need. Could we do a short walkthrough together this week? Best, {sender_name} | X53: WHY NOW: Broker-reliant Core account with healthy, regular spend and repeat self-serve checkout, but little independent browsing. WHAT WE KNOW: - Core, Broker-Reliant, Account Managed; £7,716 6m GMV; Reseller, United States; tenure 10 months. - Momentum: Growing (Sep-Nov £1,446 -> Dec-Feb £6,269); Recently Active (last GMV month: February); 7 orders over 5 month(s). - Dependency: High (broker reliance 59%; 4 AM-placed / 3 self-serve orders). - Engagement: 15 product views, 2 app days, 1 offer(s), 16 Fleek chats, 12 video requests; basket Handpick-only. WHAT TO DO: Run the Phase 1 plan: Day 0 app walkthrough focused on finding stock independently; check-in Day 15-30; formal review Day 45; outcome Day 90. WHAT NOT TO DO: Do not remove AM support; do not mention cost reduction or 'migration'. SUCCESS: Day 90: Self-Serve Capability Demonstrated (>=25 PDP views, >=6 app days, self-serve share above baseline) with GMV guardrail held. | AC53: Recently Active | AD53: Existing Customer | AE53: =FALSE() -> FALSE | AF53: Ready | AG53: Regular | AH53: Baseline | AI53: Enter 90-day monitoring inputs; migration_progress_status updates (Baseline/Progressing/Capability/At Risk). Day-90 outcomes: Capability Demonstrated, Progressing - Extend, At Risk - Restore support, No Change - Reassess. | AJ53: BASELINE | AK53: BASELINE | AL53: 007fe44db0d2
A54: ACC-020 | B54: P2 | C54: Core | D54: 6452 | E54: 1. Migration Candidate | F54: Guided Self-Serve Migration | G54: MIGRATION_PHASE1_REVIEW | H54: Human Review Required | I54: Awaiting Human Review | J54: Account Manager | K54: =FALSE() -> FALSE | L54: =FALSE() -> FALSE | M54: PB03_GUIDED_MIGRATION | N54: AM call + in-app walkthrough; automated milestone tracking | O54: AM resolves the Phase 1 guardrail(s) before any customer contact. | P54: 15 | Q54: Day 90: Self-Serve Capability Demonstrated (>=25 PDP views, >=6 app days, self-serve share above baseline) with GMV guardrail held. | R54: GMV guardrail breached (At Risk) -> restore high-touch support; no behaviour change at day 90 -> reassess suitability. | S54: At Risk at day 45; any Key account change; customer pushback on the change. | T54: PHASE1_MANUAL_REVIEW; LUMPY_CADENCE; MATERIAL_BROKER_INCONSISTENCY; H2_SINGLE_MONTH_SPIKE | U54: Withheld until human review is complete | X54: WHY NOW: Meets Phase 1 entry criteria but a guardrail (borderline/February-sensitive momentum, lumpy cadence or broker % inconsistency) must be resolved. WHAT WE KNOW: - Core, Broker-Reliant, Account Managed; £6,452 6m GMV; Reseller, France; tenure 31 months. - Momentum: Stable (Sep-Nov £3,474 -> Dec-Feb £2,978); Recently Active (last GMV month: February); 3 orders over 3 month(s). - Dependency: Medium (broker reliance 48%; 1 AM-placed / 2 self-serve orders). - Engagement: 3 product views, 7 app days, 0 offer(s), 14 Fleek chats, 2 video requests; basket Mixed. - Warnings: PHASE1_MANUAL_REVIEW; LUMPY_CADENCE; MATERIAL_BROKER_INCONSISTENCY; H2_SINGLE_MONTH_SPIKE. WHAT TO DO: Resolve the listed guardrail(s) (verify order history / momentum), then decide Ready or not suitable. Record the decision. WHAT NOT TO DO: Do not contact the customer about self-serve changes until review is complete. SUCCESS: Day 90: Self-Serve Capability Demonstrated (>=25 PDP views, >=6 app days, self-serve share above baseline) with GMV guardrail held. | AC54: Recently Active | AD54: Existing Customer | AE54: =FALSE() -> FALSE | AF54: Manual Review | AG54: Lumpy | AH54: Baseline | AI54: Enter 90-day monitoring inputs; migration_progress_status updates (Baseline/Progressing/Capability/At Risk). Day-90 outcomes: Capability Demonstrated, Progressing - Extend, At Risk - Restore support, No Change - Reassess. | AJ54: BASELINE | AK54: BASELINE | AL54: 52e8620a3f1a
A55: ACC-024 | B55: P2 | C55: Core | D55: 5214 | E55: 1. Migration Candidate | F55: Guided Self-Serve Migration | G55: MIGRATION_PHASE1_REVIEW | H55: Human Review Required | I55: Awaiting Human Review | J55: Account Manager | K55: =FALSE() -> FALSE | L55: =FALSE() -> FALSE | M55: PB03_GUIDED_MIGRATION | N55: AM call + in-app walkthrough; automated milestone tracking | O55: AM resolves the Phase 1 guardrail(s) before any customer contact. | P55: 15 | Q55: Day 90: Self-Serve Capability Demonstrated (>=25 PDP views, >=6 app days, self-serve share above baseline) with GMV guardrail held. | R55: GMV guardrail breached (At Risk) -> restore high-touch support; no behaviour change at day 90 -> reassess suitability. | S55: At Risk at day 45; any Key account change; customer pushback on the change. | T55: PHASE1_MANUAL_REVIEW; BORDERLINE_MOMENTUM | U55: Withheld until human review is complete | X55: WHY NOW: Meets Phase 1 entry criteria but a guardrail (borderline/February-sensitive momentum, lumpy cadence or broker % inconsistency) must be resolved. WHAT WE KNOW: - Core, Broker-Reliant, Account Managed; £5,214 6m GMV; Reseller, United Kingdom; tenure 11 months. - Momentum: Stable (Sep-Nov £2,883 -> Dec-Feb £2,330); Recently Active (last GMV month: February); 14 orders over 5 month(s). - Dependency: High (broker reliance 64%; 9 AM-placed / 5 self-serve orders). - Engagement: 12 product views, 6 app days, 2 offer(s), 27 Fleek chats, 0 video requests; basket Bundle-only. - Warnings: PHASE1_MANUAL_REVIEW; BORDERLINE_MOMENTUM. WHAT TO DO: Resolve the listed guardrail(s) (verify order history / momentum), then decide Ready or not suitable. Record the decision. WHAT NOT TO DO: Do not contact the customer about self-serve changes until review is complete. SUCCESS: Day 90: Self-Serve Capability Demonstrated (>=25 PDP views, >=6 app days, self-serve share above baseline) with GMV guardrail held. | AC55: Recently Active | AD55: Existing Customer | AE55: =FALSE() -> FALSE | AF55: Manual Review | AG55: Regular | AH55: Baseline | AI55: Enter 90-day monitoring inputs; migration_progress_status updates (Baseline/Progressing/Capability/At Risk). Day-90 outcomes: Capability Demonstrated, Progressing - Extend, At Risk - Restore support, No Change - Reassess. | AJ55: BASELINE | AK55: BASELINE | AL55: 49dad3347eeb
A56: ACC-025 | B56: P2 | C56: Core | D56: 5014 | E56: 6. Growth Opportunity | F56: Reinforce Successful Behaviour | G56: HEALTHY_STRONG_SELF_SERVE | H56: Ready — Automated | I56: Draft Ready | J56: Automation | K56: =FALSE() -> FALSE | L56: =TRUE() -> TRUE | M56: PB06_REINFORCE | N56: Email / in-app message | O56: Queue automated message (Reinforce Successful Behaviour). | P56: 30 | Q56: GMV run-rate maintained or higher, with GMV in each month of the next quarter. | R56: Account shows Recent Inactivity (playbook must not run) or momentum turns Declining. | S56: Recent Inactivity -> Verify check (human). | T56: H2_SINGLE_MONTH_SPIKE | U56: Draft ready (not sent) | V56: REINFORCE | W56: Hi {first_name}, Thanks for being an active Fleek buyer. Just a quick note to keep an eye on the app for bundles and handpicked stock that fits your range, and to let you know we're here if there's anything specific you're trying to source. Reply any time and we'll help. Best, {sender_name} | AC56: Recently Active | AD56: Existing Customer | AE56: =FALSE() -> FALSE | AF56: Not Eligible | AG56: Regular | AH56: N/A | AI56: Suppressed if Recent Inactivity; otherwise no repeat inside 30 days. | AJ56: BASELINE | AK56: BASELINE | AL56: ca096fe30dd8
A57: ACC-213 | B57: P2 | C57: Core | D57: 4899 | E57: 6. Growth Opportunity | F57: Reinforce Successful Behaviour | G57: HEALTHY_STRONG_SELF_SERVE | H57: Ready — Automated | I57: Draft Ready | J57: Automation | K57: =FALSE() -> FALSE | L57: =FALSE() -> FALSE | M57: PB06_REINFORCE | N57: Email / in-app message | O57: Queue automated message (Reinforce Successful Behaviour). | P57: 30 | Q57: GMV run-rate maintained or higher, with GMV in each month of the next quarter. | R57: Account shows Recent Inactivity (playbook must not run) or momentum turns Declining. | S57: Recent Inactivity -> Verify check (human). | T57: NO_FEB_GMV (Feb unconfirmed) | U57: Draft ready (not sent) | V57: REINFORCE | W57: Hi {first_name}, Thanks for being an active Fleek buyer. Just a quick note to keep an eye on the app for bundles and handpicked stock that fits your range, and to let you know we're here if there's anything specific you're trying to source. Reply any time and we'll help. Best, {sender_name} | AC57: Recently Active | AD57: Existing Customer | AE57: =FALSE() -> FALSE | AF57: Not Eligible | AG57: Regular | AH57: N/A | AI57: Suppressed if Recent Inactivity; otherwise no repeat inside 30 days. | AJ57: BASELINE | AK57: BASELINE | AL57: 91cb14df2473
A58: ACC-027 | B58: P2 | C58: Core | D58: 4678 | E58: 1. Migration Candidate | F58: Guided Self-Serve Migration | G58: MIGRATION_PHASE1_READY | H58: Ready — Hybrid | I58: Draft Ready | J58: Account Manager | K58: =FALSE() -> FALSE | L58: =FALSE() -> FALSE | M58: PB03_GUIDED_MIGRATION | N58: AM call + in-app walkthrough; automated milestone tracking | O58: Day 0: AM walkthrough call on independent stock discovery. | P58: 15 | Q58: Day 90: Self-Serve Capability Demonstrated (>=25 PDP views, >=6 app days, self-serve share above baseline) with GMV guardrail held. | R58: GMV guardrail breached (At Risk) -> restore high-touch support; no behaviour change at day 90 -> reassess suitability. | S58: At Risk at day 45; any Key account change; customer pushback on the change. | T58: NO_FEB_GMV (Feb unconfirmed) | U58: Draft ready (not sent) | V58: MIG_DAY0 | W58: Hi {first_name}, Alongside the stock I source for you, I'd like to show you how to browse Fleek's full range directly in the app, so you can look through bundles whenever it suits you, make an offer where it fits and place orders yourself. I'm still here for anything you need. Could we do a short walkthrough together this week? Best, {sender_name} | X58: WHY NOW: Broker-reliant Core account with healthy, regular spend and repeat self-serve checkout, but little independent browsing. WHAT WE KNOW: - Core, Broker-Reliant, Account Managed; £4,678 6m GMV; Retailer, Australia; tenure 30 months. - Momentum: Stable (Sep-Nov £2,280 -> Dec-Feb £2,398); Recently Active (last GMV month: January); 25 orders over 5 month(s). - Dependency: High (broker reliance 73%; 18 AM-placed / 7 self-serve orders). - Engagement: 14 product views, 3 app days, 1 offer(s), 4 Fleek chats, 0 video requests; basket Bundle-only. - Warnings: NO_FEB_GMV (Feb unconfirmed). WHAT TO DO: Run the Phase 1 plan: Day 0 app walkthrough focused on finding stock independently; check-in Day 15-30; formal review Day 45; outcome Day 90. WHAT NOT TO DO: Do not remove AM support; do not mention cost reduction or 'migration'. SUCCESS: Day 90: Self-Serve Capability Demonstrated (>=25 PDP views, >=6 app days, self-serve share above baseline) with GMV guardrail held. | AC58: Recently Active | AD58: Existing Customer | AE58: =FALSE() -> FALSE | AF58: Ready | AG58: Regular | AH58: Baseline | AI58: Enter 90-day monitoring inputs; migration_progress_status updates (Baseline/Progressing/Capability/At Risk). Day-90 outcomes: Capability Demonstrated, Progressing - Extend, At Risk - Restore support, No Change - Reassess. | AJ58: BASELINE | AK58: BASELINE | AL58: c2f68f7ca5fd
A59: ACC-030 | B59: P2 | C59: Core | D59: 4415 | E59: 1. Migration Candidate | F59: Guided Self-Serve Migration | G59: MIGRATION_PHASE1_READY | H59: Ready — Hybrid | I59: Draft Ready | J59: Account Manager | K59: =FALSE() -> FALSE | L59: =FALSE() -> FALSE | M59: PB03_GUIDED_MIGRATION | N59: AM call + in-app walkthrough; automated milestone tracking | O59: Day 0: AM walkthrough call on independent stock discovery. | P59: 15 | Q59: Day 90: Self-Serve Capability Demonstrated (>=25 PDP views, >=6 app days, self-serve share above baseline) with GMV guardrail held. | R59: GMV guardrail breached (At Risk) -> restore high-touch support; no behaviour change at day 90 -> reassess suitability. | S59: At Risk at day 45; any Key account change; customer pushback on the change. | T59: H2_SINGLE_MONTH_SPIKE; NO_FEB_GMV (Feb unconfirmed) | U59: Draft ready (not sent) | V59: MIG_DAY0 | W59: Hi {first_name}, Alongside the stock I source for you, I'd like to show you how to browse Fleek's full range directly in the app, so you can look through bundles and handpicked stock whenever it suits you, make an offer where it fits and place orders yourself. I'm still here for anything you need. Could we do a short walkthrough together this week? Best, {sender_name} | X59: WHY NOW: Broker-reliant Core account with healthy, regular spend and repeat self-serve checkout, but little independent browsing. WHAT WE KNOW: - Core, Broker-Reliant, Account Managed; £4,415 6m GMV; Reseller, United Kingdom; tenure 48 months. - Momentum: Growing (Sep-Nov £902 -> Dec-Feb £3,513); Recently Active (last GMV month: January); 5 orders over 4 month(s). - Dependency: High (broker reliance 68%; 3 AM-placed / 2 self-serve orders). - Engagement: 2 product views, 2 app days, 0 offer(s), 15 Fleek chats, 1 video requests; basket Mixed. - Warnings: H2_SINGLE_MONTH_SPIKE; NO_FEB_GMV (Feb unconfirmed). WHAT TO DO: Run the Phase 1 plan: Day 0 app walkthrough focused on finding stock independently; check-in Day 15-30; formal review Day 45; outcome Day 90. WHAT NOT TO DO: Do not remove AM support; do not mention cost reduction or 'migration'. SUCCESS: Day 90: Self-Serve Capability Demonstrated (>=25 PDP views, >=6 app days, self-serve share above baseline) with GMV guardrail held. | AC59: Recently Active | AD59: Existing Customer | AE59: =FALSE() -> FALSE | AF59: Ready | AG59: Regular | AH59: Baseline | AI59: Enter 90-day monitoring inputs; migration_progress_status updates (Baseline/Progressing/Capability/At Risk). Day-90 outcomes: Capability Demonstrated, Progressing - Extend, At Risk - Restore support, No Change - Reassess. | AJ59: BASELINE | AK59: BASELINE | AL59: 159c0643b8b5
A60: ACC-031 | B60: P2 | C60: Core | D60: 4372 | E60: 1. Migration Candidate | F60: Guided Self-Serve Migration | G60: MIGRATION_PHASE1_READY | H60: Ready — Hybrid | I60: Draft Ready | J60: Account Manager | K60: =FALSE() -> FALSE | L60: =FALSE() -> FALSE | M60: PB03_GUIDED_MIGRATION | N60: AM call + in-app walkthrough; automated milestone tracking | O60: Day 0: AM walkthrough call on independent stock discovery. | P60: 15 | Q60: Day 90: Self-Serve Capability Demonstrated (>=25 PDP views, >=6 app days, self-serve share above baseline) with GMV guardrail held. | R60: GMV guardrail breached (At Risk) -> restore high-touch support; no behaviour change at day 90 -> reassess suitability. | S60: At Risk at day 45; any Key account change; customer pushback on the change. | U60: Draft ready (not sent) | V60: MIG_DAY0 | W60: Hi {first_name}, Alongside the stock I source for you, I'd like to show you how to browse Fleek's full range directly in the app, so you can look through bundles and handpicked stock whenever it suits you, make an offer where it fits and place orders yourself. I'm still here for anything you need. Could we do a short walkthrough together this week? Best, {sender_name} | X60: WHY NOW: Broker-reliant Core account with healthy, regular spend and repeat self-serve checkout, but little independent browsing. WHAT WE KNOW: - Core, Broker-Reliant, Account Managed; £4,372 6m GMV; Reseller, France; tenure 9 months. - Momentum: Growing (Sep-Nov £1,194 -> Dec-Feb £3,178); Recently Active (last GMV month: February); 8 orders over 3 month(s). - Dependency: High (broker reliance 79%; 6 AM-placed / 2 self-serve orders). - Engagement: 1 product views, 5 app days, 1 offer(s), 34 Fleek chats, 1 video requests; basket Mixed. WHAT TO DO: Run the Phase 1 plan: Day 0 app walkthrough focused on finding stock independently; check-in Day 15-30; formal review Day 45; outcome Day 90. WHAT NOT TO DO: Do not remove AM support; do not mention cost reduction or 'migration'. SUCCESS: Day 90: Self-Serve Capability Demonstrated (>=25 PDP views, >=6 app days, self-serve share above baseline) with GMV guardrail held. | AC60: Recently Active | AD60: Existing Customer | AE60: =FALSE() -> FALSE | AF60: Ready | AG60: Regular | AH60: Baseline | AI60: Enter 90-day monitoring inputs; migration_progress_status updates (Baseline/Progressing/Capability/At Risk). Day-90 outcomes: Capability Demonstrated, Progressing - Extend, At Risk - Restore support, No Change - Reassess. | AJ60: BASELINE | AK60: BASELINE | AL60: 9699924bde84
A61: ACC-033 | B61: P2 | C61: Core | D61: 3925 | E61: 1. Migration Candidate | F61: Guided Self-Serve Migration | G61: MIGRATION_PHASE1_REVIEW | H61: Human Review Required | I61: Awaiting Human Review | J61: Account Manager | K61: =FALSE() -> FALSE | L61: =FALSE() -> FALSE | M61: PB03_GUIDED_MIGRATION | N61: AM call + in-app walkthrough; automated milestone tracking | O61: AM resolves the Phase 1 guardrail(s) before any customer contact. | P61: 15 | Q61: Day 90: Self-Serve Capability Demonstrated (>=25 PDP views, >=6 app days, self-serve share above baseline) with GMV guardrail held. | R61: GMV guardrail breached (At Risk) -> restore high-touch support; no behaviour change at day 90 -> reassess suitability. | S61: At Risk at day 45; any Key account change; customer pushback on the change. | T61: PHASE1_MANUAL_REVIEW; BORDERLINE_MOMENTUM | U61: Withheld until human review is complete | X61: WHY NOW: Meets Phase 1 entry criteria but a guardrail (borderline/February-sensitive momentum, lumpy cadence or broker % inconsistency) must be resolved. WHAT WE KNOW: - Core, Broker-Reliant, Account Managed; £3,925 6m GMV; Reseller, Netherlands; tenure 7 months. - Momentum: Stable (Sep-Nov £2,126 -> Dec-Feb £1,799); Recently Active (last GMV month: February); 8 orders over 5 month(s). - Dependency: Medium (broker reliance 54%; 4 AM-placed / 4 self-serve orders). - Engagement: 12 product views, 2 app days, 2 offer(s), 14 Fleek chats, 0 video requests; basket Bundle-only. - Warnings: PHASE1_MANUAL_REVIEW; BORDERLINE_MOMENTUM. WHAT TO DO: Resolve the listed guardrail(s) (verify order history / momentum), then decide Ready or not suitable. Record the decision. WHAT NOT TO DO: Do not contact the customer about self-serve changes until review is complete. SUCCESS: Day 90: Self-Serve Capability Demonstrated (>=25 PDP views, >=6 app days, self-serve share above baseline) with GMV guardrail held. | AC61: Recently Active | AD61: Existing Customer | AE61: =FALSE() -> FALSE | AF61: Manual Review | AG61: Regular | AH61: Baseline | AI61: Enter 90-day monitoring inputs; migration_progress_status updates (Baseline/Progressing/Capability/At Risk). Day-90 outcomes: Capability Demonstrated, Progressing - Extend, At Risk - Restore support, No Change - Reassess. | AJ61: BASELINE | AK61: BASELINE | AL61: 16ee29db7b94
A62: ACC-036 | B62: P2 | C62: Core | D62: 3879 | E62: 1. Migration Candidate | F62: Guided Self-Serve Migration | G62: MIGRATION_PHASE1_REVIEW | H62: Human Review Required | I62: Awaiting Human Review | J62: Account Manager | K62: =FALSE() -> FALSE | L62: =FALSE() -> FALSE | M62: PB03_GUIDED_MIGRATION | N62: AM call + in-app walkthrough; automated milestone tracking | O62: AM resolves the Phase 1 guardrail(s) before any customer contact. | P62: 15 | Q62: Day 90: Self-Serve Capability Demonstrated (>=25 PDP views, >=6 app days, self-serve share above baseline) with GMV guardrail held. | R62: GMV guardrail breached (At Risk) -> restore high-touch support; no behaviour change at day 90 -> reassess suitability. | S62: At Risk at day 45; any Key account change; customer pushback on the change. | T62: PHASE1_MANUAL_REVIEW; LUMPY_CADENCE; H2_SINGLE_MONTH_SPIKE; NO_FEB_GMV (Feb unconfirmed) | U62: Withheld until human review is complete | X62: WHY NOW: Meets Phase 1 entry criteria but a guardrail (borderline/February-sensitive momentum, lumpy cadence or broker % inconsistency) must be resolved. WHAT WE KNOW: - Core, Broker-Reliant, Account Managed; £3,879 6m GMV; Retailer, United Kingdom; tenure 13 months. - Momentum: Growing (Sep-Nov £369 -> Dec-Feb £3,510); Recently Active (last GMV month: January); 37 orders over 2 month(s). - Dependency: High (broker reliance 76%; 28 AM-placed / 9 self-serve orders). - Engagement: 2 product views, 6 app days, 1 offer(s), 22 Fleek chats, 0 video requests; basket Mixed. - Warnings: PHASE1_MANUAL_REVIEW; LUMPY_CADENCE; H2_SINGLE_MONTH_SPIKE; NO_FEB_GMV (Feb unconfirmed). WHAT TO DO: Resolve the listed guardrail(s) (verify order history / momentum), then decide Ready or not suitable. Record the decision. WHAT NOT TO DO: Do not contact the customer about self-serve changes until review is complete. SUCCESS: Day 90: Self-Serve Capability Demonstrated (>=25 PDP views, >=6 app days, self-serve share above baseline) with GMV guardrail held. | AC62: Recently Active | AD62: Existing Customer | AE62: =FALSE() -> FALSE | AF62: Manual Review | AG62: Lumpy | AH62: Baseline | AI62: Enter 90-day monitoring inputs; migration_progress_status updates (Baseline/Progressing/Capability/At Risk). Day-90 outcomes: Capability Demonstrated, Progressing - Extend, At Risk - Restore support, No Change - Reassess. | AJ62: BASELINE | AK62: BASELINE | AL62: bf548797d462
A63: ACC-047 | B63: P2 | C63: Core | D63: 3200 | E63: 4. Establish / Re-establish / Observe | F63: Establish / Re-establish | G63: RETURNED_CUSTOMER | H63: Ready — Human | I63: Draft Ready | J63: Account Manager | K63: =FALSE() -> FALSE | L63: =FALSE() -> FALSE | M63: PB04_ESTABLISH | N63: Personal email from AM, then call | O63: Send welcome-back outreach; book a call. | P63: 10 | Q63: New: 2+ orders across 2+ months within 90 days. Returned: orders in at least 2 of the next 3 months. | R63: Second order placed (new) or cadence agreed (returned). | S63: Returned Key account with no response after 2 attempts -> Portfolio Lead. | U63: Draft ready (not sent) | V63: EST_RETURNED | W63: Hi {first_name}, Great to see you ordering with Fleek again. I'd love to catch up on what you're sourcing at the moment and how often you're planning to buy, so we can make sure the right bundles and handpicked stock is in front of you. Would a quick call in the next week or two work? Best, {sender_name} | X63: WHY NOW: Long-tenured customer returned in Dec-Feb after no Sep-Nov spend. WHAT WE KNOW: - Core, Broker-Reliant, Account Managed; £3,200 6m GMV; Reseller, United Kingdom; tenure 10 months. - Momentum: H2 Active / No H1 GMV; Recently Active (last GMV month: February); 6 orders over 2 month(s). - Dependency: Medium (broker reliance 53%; 3 AM-placed / 3 self-serve orders). - Engagement: 2 product views, 8 app days, 1 offer(s), 15 Fleek chats, 3 video requests; basket Mixed. WHAT TO DO: Welcome-back conversation: what brought them back, what they are sourcing now, how often they plan to buy. WHAT NOT TO DO: Do not treat them as a brand-new customer. SUCCESS: New: 2+ orders across 2+ months within 90 days. Returned: orders in at least 2 of the next 3 months. | AC63: Recently Active | AD63: Returned Customer | AE63: =FALSE() -> FALSE | AF63: Not Eligible | AG63: Lumpy | AH63: N/A | AI63: Once H1/H2 history exists the account leaves this playbook automatically via re-segmentation. | AJ63: BASELINE | AK63: BASELINE | AL63: d857ee7a7173
A64: ACC-048 | B64: P2 | C64: Core | D64: 3113 | E64: 7. Onboard / Re-engage / Learn | F64: Establish / Re-establish | G64: RETURNED_CUSTOMER | H64: Ready — Human | I64: Draft Ready | J64: Account Manager | K64: =FALSE() -> FALSE | L64: =FALSE() -> FALSE | M64: PB04_ESTABLISH | N64: Personal email from AM, then call | O64: Send welcome-back outreach; book a call. | P64: 10 | Q64: New: 2+ orders across 2+ months within 90 days. Returned: orders in at least 2 of the next 3 months. | R64: Second order placed (new) or cadence agreed (returned). | S64: Returned Key account with no response after 2 attempts -> Portfolio Lead. | T64: MATERIAL_BROKER_INCONSISTENCY; H2_SINGLE_MONTH_SPIKE | U64: Draft ready (not sent) | V64: EST_RETURNED | W64: Hi {first_name}, Great to see you ordering with Fleek again. I'd love to catch up on what you're sourcing at the moment and how often you're planning to buy, so we can make sure the right handpicked stock is in front of you. Would a quick call in the next week or two work? Best, {sender_name} | X64: WHY NOW: Long-tenured customer returned in Dec-Feb after no Sep-Nov spend. WHAT WE KNOW: - Core, AM-Owned / Self-Serving, Account Managed; £3,113 6m GMV; Reseller, United Kingdom; tenure 14 months. - Momentum: H2 Active / No H1 GMV; Recently Active (last GMV month: February); 4 orders over 2 month(s). - Dependency: Low (broker reliance 15%; 1 AM-placed / 3 self-serve orders). - Engagement: 488 product views, 30 app days, 1 offer(s), 24 Fleek chats, 0 video requests; basket Handpick-only. - Warnings: MATERIAL_BROKER_INCONSISTENCY; H2_SINGLE_MONTH_SPIKE. WHAT TO DO: Welcome-back conversation: what brought them back, what they are sourcing now, how often they plan to buy. WHAT NOT TO DO: Do not treat them as a brand-new customer. SUCCESS: New: 2+ orders across 2+ months within 90 days. Returned: orders in at least 2 of the next 3 months. | AC64: Recently Active | AD64: Returned Customer | AE64: =FALSE() -> FALSE | AF64: Not Eligible | AG64: Lumpy | AH64: N/A | AI64: Once H1/H2 history exists the account leaves this playbook automatically via re-segmentation. | AJ64: BASELINE | AK64: BASELINE | AL64: 85c8f6987236
A65: ACC-217 | B65: P2 | C65: Core | D65: 2402 | E65: 7. Onboard / Re-engage / Learn | F65: Establish / Re-establish | G65: NEW_CUSTOMER | H65: Ready — Automated | I65: Draft Ready | J65: Automation | K65: =FALSE() -> FALSE | L65: =FALSE() -> FALSE | M65: PB04_ESTABLISH | N65: Email / in-app message | O65: Send onboarding message. | P65: 14 | Q65: New: 2+ orders across 2+ months within 90 days. Returned: orders in at least 2 of the next 3 months. | R65: Second order placed (new) or cadence agreed (returned). | S65: Returned Key account with no response after 2 attempts -> Portfolio Lead. | U65: Draft ready (not sent) | V65: EST_NEW | W65: Hi {first_name}, Welcome to Fleek, and thanks for your recent orders. A couple of tips as you build your buying routine: you can browse available stock in the app whenever suits you, and if a price doesn't quite work, you can use Make an Offer on items you're interested in. We're here if you need anything. Best, {sender_name} | AC65: Recently Active | AD65: New Customer | AE65: =FALSE() -> FALSE | AF65: Not Eligible | AG65: Regular | AH65: N/A | AI65: Once H1/H2 history exists the account leaves this playbook automatically via re-segmentation. | AJ65: BASELINE | AK65: BASELINE | AL65: 5a52a8fcef4c
A66: ACC-056 | B66: P2 | C66: Core | D66: 2380 | E66: 1. Migration Candidate | F66: Guided Self-Serve Migration | G66: MIGRATION_PHASE1_REVIEW | H66: Human Review Required | I66: Awaiting Human Review | J66: Account Manager | K66: =FALSE() -> FALSE | L66: =FALSE() -> FALSE | M66: PB03_GUIDED_MIGRATION | N66: AM call + in-app walkthrough; automated milestone tracking | O66: AM resolves the Phase 1 guardrail(s) before any customer contact. | P66: 15 | Q66: Day 90: Self-Serve Capability Demonstrated (>=25 PDP views, >=6 app days, self-serve share above baseline) with GMV guardrail held. | R66: GMV guardrail breached (At Risk) -> restore high-touch support; no behaviour change at day 90 -> reassess suitability. | S66: At Risk at day 45; any Key account change; customer pushback on the change. | T66: PHASE1_MANUAL_REVIEW; BORDERLINE_MOMENTUM; MATERIAL_BROKER_INCONSISTENCY; NO_FEB_GMV (Feb unconfirmed) | U66: Withheld until human review is complete | X66: WHY NOW: Meets Phase 1 entry criteria but a guardrail (borderline/February-sensitive momentum, lumpy cadence or broker % inconsistency) must be resolved. WHAT WE KNOW: - Core, Broker-Reliant, Account Managed; £2,380 6m GMV; Reseller, United Kingdom; tenure 7 months. - Momentum: Stable (Sep-Nov £1,089 -> Dec-Feb £1,291); Recently Active (last GMV month: January); 5 orders over 3 month(s). - Dependency: Medium (broker reliance 54%; 3 AM-placed / 2 self-serve orders). - Engagement: 9 product views, 7 app days, 1 offer(s), 9 Fleek chats, 0 video requests; basket Mixed. - Warnings: PHASE1_MANUAL_REVIEW; BORDERLINE_MOMENTUM; MATERIAL_BROKER_INCONSISTENCY; NO_FEB_GMV (Feb unconfirmed). WHAT TO DO: Resolve the listed guardrail(s) (verify order history / momentum), then decide Ready or not suitable. Record the decision. WHAT NOT TO DO: Do not contact the customer about self-serve changes until review is complete. SUCCESS: Day 90: Self-Serve Capability Demonstrated (>=25 PDP views, >=6 app days, self-serve share above baseline) with GMV guardrail held. | AC66: Recently Active | AD66: Existing Customer | AE66: =FALSE() -> FALSE | AF66: Manual Review | AG66: Regular | AH66: Baseline | AI66: Enter 90-day monitoring inputs; migration_progress_status updates (Baseline/Progressing/Capability/At Risk). Day-90 outcomes: Capability Demonstrated, Progressing - Extend, At Risk - Restore support, No Change - Reassess. | AJ66: BASELINE | AK66: BASELINE | AL66: 3ef68990c056
A67: ACC-058 | B67: P2 | C67: Core | D67: 2277 | E67: 1. Migration Candidate | F67: Guided Self-Serve Migration | G67: MIGRATION_PHASE1_REVIEW | H67: Human Review Required | I67: Awaiting Human Review | J67: Account Manager | K67: =FALSE() -> FALSE | L67: =FALSE() -> FALSE | M67: PB03_GUIDED_MIGRATION | N67: AM call + in-app walkthrough; automated milestone tracking | O67: AM resolves the Phase 1 guardrail(s) before any customer contact. | P67: 15 | Q67: Day 90: Self-Serve Capability Demonstrated (>=25 PDP views, >=6 app days, self-serve share above baseline) with GMV guardrail held. | R67: GMV guardrail breached (At Risk) -> restore high-touch support; no behaviour change at day 90 -> reassess suitability. | S67: At Risk at day 45; any Key account change; customer pushback on the change. | T67: PHASE1_MANUAL_REVIEW; LUMPY_CADENCE; FEB_SENSITIVE; H2_SINGLE_MONTH_SPIKE | U67: Withheld until human review is complete | X67: WHY NOW: Meets Phase 1 entry criteria but a guardrail (borderline/February-sensitive momentum, lumpy cadence or broker % inconsistency) must be resolved. WHAT WE KNOW: - Core, Broker-Reliant, Account Managed; £2,277 6m GMV; Reseller, Germany; tenure 14 months. - Momentum: Growing (Sep-Nov £982 -> Dec-Feb £1,295); Recently Active (last GMV month: February); 8 orders over 2 month(s). - Dependency: Medium (broker reliance 48%; 4 AM-placed / 4 self-serve orders). - Engagement: 3 product views, 5 app days, 0 offer(s), 21 Fleek chats, 2 video requests; basket Mixed. - Warnings: PHASE1_MANUAL_REVIEW; LUMPY_CADENCE; FEB_SENSITIVE; H2_SINGLE_MONTH_SPIKE. WHAT TO DO: Resolve the listed guardrail(s) (verify order history / momentum), then decide Ready or not suitable. Record the decision. WHAT NOT TO DO: Do not contact the customer about self-serve changes until review is complete. SUCCESS: Day 90: Self-Serve Capability Demonstrated (>=25 PDP views, >=6 app days, self-serve share above baseline) with GMV guardrail held. | AC67: Recently Active | AD67: Existing Customer | AE67: =FALSE() -> FALSE | AF67: Manual Review | AG67: Lumpy | AH67: Baseline | AI67: Enter 90-day monitoring inputs; migration_progress_status updates (Baseline/Progressing/Capability/At Risk). Day-90 outcomes: Capability Demonstrated, Progressing - Extend, At Risk - Restore support, No Change - Reassess. | AJ67: BASELINE | AK67: BASELINE | AL67: 3814d6df488f
A68: ACC-029 | B68: P3 | C68: Core | D68: 4513 | E68: 1. Migration Candidate | F68: Guided Self-Serve Migration | G68: MIGRATION_PRE_ENTRY | H68: Ready — Human | I68: Draft Ready | J68: Account Manager | K68: =FALSE() -> FALSE | L68: =FALSE() -> FALSE | M68: PB03_GUIDED_MIGRATION | N68: AM call + in-app walkthrough; automated milestone tracking | O68: AM encourages a second self-serve checkout. | P68: 15 | Q68: Day 90: Self-Serve Capability Demonstrated (>=25 PDP views, >=6 app days, self-serve share above baseline) with GMV guardrail held. | R68: GMV guardrail breached (At Risk) -> restore high-touch support; no behaviour change at day 90 -> reassess suitability. | S68: At Risk at day 45; any Key account change; customer pushback on the change. | T68: MATERIAL_BROKER_INCONSISTENCY | U68: Draft ready (not sent) | V68: MIG_PREENTRY | W68: Hi {first_name}, A quick tip: whenever you spot something you like while browsing the Fleek app, you can place the order directly there, at a time that suits you. I'll keep sourcing for you as usual, so nothing changes on my side. Let me know if a short walkthrough of the app would be helpful. Best, {sender_name} | X68: WHY NOW: Broker-reliant Core account with healthy spend but only one self-serve order. WHAT WE KNOW: - Core, Broker-Reliant, Account Managed; £4,513 6m GMV; Reseller, United Kingdom; tenure 6 months. - Momentum: Growing (Sep-Nov £496 -> Dec-Feb £4,018); Recently Active (last GMV month: February); 5 orders over 4 month(s). - Dependency: High (broker reliance 78%; 4 AM-placed / 1 self-serve orders). - Engagement: 10 product views, 6 app days, 0 offer(s), 3 Fleek chats, 0 video requests; basket Mixed. - Warnings: MATERIAL_BROKER_INCONSISTENCY. WHAT TO DO: Encourage a second self-serve checkout on stock the customer already wants; keep sourcing as usual; re-assess for Phase 1 next run. WHAT NOT TO DO: Do not reduce sourcing support. SUCCESS: Day 90: Self-Serve Capability Demonstrated (>=25 PDP views, >=6 app days, self-serve share above baseline) with GMV guardrail held. | AC68: Recently Active | AD68: Existing Customer | AE68: =FALSE() -> FALSE | AF68: Not Eligible | AG68: Regular | AH68: Baseline | AI68: Enter 90-day monitoring inputs; migration_progress_status updates (Baseline/Progressing/Capability/At Risk). Day-90 outcomes: Capability Demonstrated, Progressing - Extend, At Risk - Restore support, No Change - Reassess. | AJ68: BASELINE | AK68: BASELINE | AL68: 65f4916d6b6c
A69: ACC-034 | B69: P3 | C69: Core | D69: 3913 | E69: 1. Migration Candidate | F69: Guided Self-Serve Migration | G69: MIGRATION_PRE_ENTRY | H69: Ready — Human | I69: Draft Ready | J69: Account Manager | K69: =FALSE() -> FALSE | L69: =FALSE() -> FALSE | M69: PB03_GUIDED_MIGRATION | N69: AM call + in-app walkthrough; automated milestone tracking | O69: AM encourages a second self-serve checkout. | P69: 15 | Q69: Day 90: Self-Serve Capability Demonstrated (>=25 PDP views, >=6 app days, self-serve share above baseline) with GMV guardrail held. | R69: GMV guardrail breached (At Risk) -> restore high-touch support; no behaviour change at day 90 -> reassess suitability. | S69: At Risk at day 45; any Key account change; customer pushback on the change. | T69: LUMPY_CADENCE; MATERIAL_BROKER_INCONSISTENCY; H2_SINGLE_MONTH_SPIKE; NO_FEB_GMV (Feb unconfirmed) | U69: Draft ready (not sent) | V69: MIG_PREENTRY | W69: Hi {first_name}, A quick tip: whenever you spot something you like while browsing the Fleek app, you can place the order directly there, at a time that suits you. I'll keep sourcing for you as usual, so nothing changes on my side. Let me know if a short walkthrough of the app would be helpful. Best, {sender_name} | X69: WHY NOW: Broker-reliant Core account with healthy spend but only one self-serve order. WHAT WE KNOW: - Core, Broker-Reliant, Account Managed; £3,913 6m GMV; Reseller, Germany; tenure 7 months. - Momentum: Stable (Sep-Nov £1,941 -> Dec-Feb £1,971); Recently Active (last GMV month: January); 4 orders over 4 month(s). - Dependency: High (broker reliance 82%; 3 AM-placed / 1 self-serve orders). - Engagement: 9 product views, 5 app days, 1 offer(s), 76 Fleek chats, 0 video requests; basket Handpick-only. - Warnings: LUMPY_CADENCE; MATERIAL_BROKER_INCONSISTENCY; H2_SINGLE_MONTH_SPIKE; NO_FEB_GMV (Feb unconfirmed). WHAT TO DO: Encourage a second self-serve checkout on stock the customer already wants; keep sourcing as usual; re-assess for Phase 1 next run. WHAT NOT TO DO: Do not reduce sourcing support. SUCCESS: Day 90: Self-Serve Capability Demonstrated (>=25 PDP views, >=6 app days, self-serve share above baseline) with GMV guardrail held. | AC69: Recently Active | AD69: Existing Customer | AE69: =FALSE() -> FALSE | AF69: Not Eligible | AG69: Lumpy | AH69: Baseline | AI69: Enter 90-day monitoring inputs; migration_progress_status updates (Baseline/Progressing/Capability/At Risk). Day-90 outcomes: Capability Demonstrated, Progressing - Extend, At Risk - Restore support, No Change - Reassess. | AJ69: BASELINE | AK69: BASELINE | AL69: 879ab96f7320
A70: ACC-039 | B70: P3 | C70: Core | D70: 3626 | E70: 1. Migration Candidate | F70: Guided Self-Serve Migration | G70: MIGRATION_PRE_ENTRY | H70: Ready — Human | I70: Draft Ready | J70: Account Manager | K70: =FALSE() -> FALSE | L70: =FALSE() -> FALSE | M70: PB03_GUIDED_MIGRATION | N70: AM call + in-app walkthrough; automated milestone tracking | O70: AM encourages a second self-serve checkout. | P70: 15 | Q70: Day 90: Self-Serve Capability Demonstrated (>=25 PDP views, >=6 app days, self-serve share above baseline) with GMV guardrail held. | R70: GMV guardrail breached (At Risk) -> restore high-touch support; no behaviour change at day 90 -> reassess suitability. | S70: At Risk at day 45; any Key account change; customer pushback on the change. | T70: LUMPY_CADENCE; FEB_SENSITIVE; H2_SINGLE_MONTH_SPIKE | U70: Draft ready (not sent) | V70: MIG_PREENTRY | W70: Hi {first_name}, A quick tip: whenever you spot something you like while browsing the Fleek app, you can place the order directly there, at a time that suits you. I'll keep sourcing for you as usual, so nothing changes on my side. Let me know if a short walkthrough of the app would be helpful. Best, {sender_name} | X70: WHY NOW: Broker-reliant Core account with healthy spend but only one self-serve order. WHAT WE KNOW: - Core, Broker-Reliant, Account Managed; £3,626 6m GMV; Reseller, France; tenure 22 months. - Momentum: Growing (Sep-Nov £1,453 -> Dec-Feb £2,173); Recently Active (last GMV month: February); 4 orders over 3 month(s). - Dependency: High (broker reliance 70%; 3 AM-placed / 1 self-serve orders). - Engagement: 11 product views, 5 app days, 1 offer(s), 159 Fleek chats, 1 video requests; basket Mixed. - Warnings: LUMPY_CADENCE; FEB_SENSITIVE; H2_SINGLE_MONTH_SPIKE. WHAT TO DO: Encourage a second self-serve checkout on stock the customer already wants; keep sourcing as usual; re-assess for Phase 1 next run. WHAT NOT TO DO: Do not reduce sourcing support. SUCCESS: Day 90: Self-Serve Capability Demonstrated (>=25 PDP views, >=6 app days, self-serve share above baseline) with GMV guardrail held. | AC70: Recently Active | AD70: Existing Customer | AE70: =FALSE() -> FALSE | AF70: Not Eligible | AG70: Lumpy | AH70: Baseline | AI70: Enter 90-day monitoring inputs; migration_progress_status updates (Baseline/Progressing/Capability/At Risk). Day-90 outcomes: Capability Demonstrated, Progressing - Extend, At Risk - Restore support, No Change - Reassess. | AJ70: BASELINE | AK70: BASELINE | AL70: 0fcf3873bc5c
A71: ACC-049 | B71: P3 | C71: Core | D71: 3111 | E71: 1. Migration Candidate | F71: Guided Self-Serve Migration | G71: MIGRATION_PRE_ENTRY | H71: Ready — Human | I71: Draft Ready | J71: Account Manager | K71: =FALSE() -> FALSE | L71: =FALSE() -> FALSE | M71: PB03_GUIDED_MIGRATION | N71: AM call + in-app walkthrough; automated milestone tracking | O71: AM encourages a second self-serve checkout. | P71: 15 | Q71: Day 90: Self-Serve Capability Demonstrated (>=25 PDP views, >=6 app days, self-serve share above baseline) with GMV guardrail held. | R71: GMV guardrail breached (At Risk) -> restore high-touch support; no behaviour change at day 90 -> reassess suitability. | S71: At Risk at day 45; any Key account change; customer pushback on the change. | U71: Draft ready (not sent) | V71: MIG_PREENTRY | W71: Hi {first_name}, A quick tip: whenever you spot something you like while browsing the Fleek app, you can place the order directly there, at a time that suits you. I'll keep sourcing for you as usual, so nothing changes on my side. Let me know if a short walkthrough of the app would be helpful. Best, {sender_name} | X71: WHY NOW: Broker-reliant Core account with healthy spend but only one self-serve order. WHAT WE KNOW: - Core, Broker-Reliant, Account Managed; £3,111 6m GMV; Reseller, United Kingdom; tenure 10 months. - Momentum: Growing (Sep-Nov £765 -> Dec-Feb £2,347); Recently Active (last GMV month: February); 7 orders over 5 month(s). - Dependency: High (broker reliance 81%; 6 AM-placed / 1 self-serve orders). - Engagement: 13 product views, 8 app days, 1 offer(s), 20 Fleek chats, 0 video requests; basket Bundle-only. WHAT TO DO: Encourage a second self-serve checkout on stock the customer already wants; keep sourcing as usual; re-assess for Phase 1 next run. WHAT NOT TO DO: Do not reduce sourcing support. SUCCESS: Day 90: Self-Serve Capability Demonstrated (>=25 PDP views, >=6 app days, self-serve share above baseline) with GMV guardrail held. | AC71: Recently Active | AD71: Existing Customer | AE71: =FALSE() -> FALSE | AF71: Not Eligible | AG71: Regular | AH71: Baseline | AI71: Enter 90-day monitoring inputs; migration_progress_status updates (Baseline/Progressing/Capability/At Risk). Day-90 outcomes: Capability Demonstrated, Progressing - Extend, At Risk - Restore support, No Change - Reassess. | AJ71: BASELINE | AK71: BASELINE | AL71: e8d7cc4929a3
A72: ACC-057 | B72: P3 | C72: Core | D72: 2366 | E72: 1. Migration Candidate | F72: Guided Self-Serve Migration | G72: MIGRATION_PRE_ENTRY | H72: Ready — Human | I72: Draft Ready | J72: Account Manager | K72: =FALSE() -> FALSE | L72: =FALSE() -> FALSE | M72: PB03_GUIDED_MIGRATION | N72: AM call + in-app walkthrough; automated milestone tracking | O72: AM encourages a second self-serve checkout. | P72: 15 | Q72: Day 90: Self-Serve Capability Demonstrated (>=25 PDP views, >=6 app days, self-serve share above baseline) with GMV guardrail held. | R72: GMV guardrail breached (At Risk) -> restore high-touch support; no behaviour change at day 90 -> reassess suitability. | S72: At Risk at day 45; any Key account change; customer pushback on the change. | T72: LUMPY_CADENCE; H2_SINGLE_MONTH_SPIKE | U72: Draft ready (not sent) | V72: MIG_PREENTRY | W72: Hi {first_name}, A quick tip: whenever you spot something you like while browsing the Fleek app, you can place the order directly there, at a time that suits you. I'll keep sourcing for you as usual, so nothing changes on my side. Let me know if a short walkthrough of the app would be helpful. Best, {sender_name} | X72: WHY NOW: Broker-reliant Core account with healthy spend but only one self-serve order. WHAT WE KNOW: - Core, Broker-Reliant, Account Managed; £2,366 6m GMV; Reseller, France; tenure 16 months. - Momentum: Stable (Sep-Nov £1,167 -> Dec-Feb £1,199); Recent Inactivity (last GMV month: December); 3 orders over 3 month(s). - Dependency: High (broker reliance 61%; 2 AM-placed / 1 self-serve orders). - Engagement: 4 product views, 4 app days, 1 offer(s), 2 Fleek chats, 0 video requests; basket Bundle-only. - Warnings: LUMPY_CADENCE; H2_SINGLE_MONTH_SPIKE. WHAT TO DO: Encourage a second self-serve checkout on stock the customer already wants; keep sourcing as usual; re-assess for Phase 1 next run. WHAT NOT TO DO: Do not reduce sourcing support. SUCCESS: Day 90: Self-Serve Capability Demonstrated (>=25 PDP views, >=6 app days, self-serve share above baseline) with GMV guardrail held. | AC72: Recent Inactivity | AD72: Existing Customer | AE72: =FALSE() -> FALSE | AF72: Not Eligible | AG72: Lumpy | AH72: Baseline | AI72: Enter 90-day monitoring inputs; migration_progress_status updates (Baseline/Progressing/Capability/At Risk). Day-90 outcomes: Capability Demonstrated, Progressing - Extend, At Risk - Restore support, No Change - Reassess. | AJ72: BASELINE | AK72: BASELINE | AL72: debc77818ad3
A73: ACC-064 | B73: P3 | C73: Tail | D73: 1911 | E73: 5. Cost-to-Serve / Low-Touch | F73: Service Model Review | G73: COST_TO_SERVE_ACTIVE | H73: Ready — Human | I73: Not Started | J73: Portfolio Lead | K73: =FALSE() -> FALSE | L73: =FALSE() -> FALSE | M73: PB07_SERVICE_MODEL_REVIEW | N73: Internal review (no customer contact) | O73: Portfolio Lead reviews account card and records a service decision. | P73: 14 | Q73: Decision logged; broker effort reduced where agreed without GMV loss. | R73: Decision recorded. | S73: None. | T73: BORDERLINE_MOMENTUM; FEB_SENSITIVE | U73: None: internal-only review | X73: WHY NOW: Low-value broker-reliant account that is still buying. WHAT WE KNOW: - Tail, Broker-Reliant, Account Managed; £1,911 6m GMV; Retailer, United Kingdom; tenure 9 months. - Momentum: Stable (Sep-Nov £1,042 -> Dec-Feb £869); Recently Active (last GMV month: February); 15 orders over 5 month(s). - Dependency: High (broker reliance 68%; 10 AM-placed / 5 self-serve orders). - Engagement: 14 product views, 4 app days, 2 offer(s), 5 Fleek chats, 0 video requests; basket Bundle-only. - Warnings: BORDERLINE_MOMENTUM; FEB_SENSITIVE. WHAT TO DO: Review the card and decide: maintain support / move to lower-touch / automated nurture / revisit later. WHAT NOT TO DO: No customer message. No ROI claim (no AM cost data). SUCCESS: Decision logged; broker effort reduced where agreed without GMV loss. | AC73: Recently Active | AD73: Existing Customer | AE73: =FALSE() -> FALSE | AF73: Not Eligible | AG73: Regular | AH73: N/A | AI73: Decision stored; account not re-queued unless its NBA changes. | AJ73: BASELINE | AK73: BASELINE | AL73: ea60047c0021
A74: ACC-065 | B74: P3 | C74: Tail | D74: 1812 | E74: 9. Long-Tail Automated Nurture | F74: Automated Nurture | G74: RISING_TAIL_EARLY | H74: Ready — Automated | I74: Draft Ready | J74: Automation | K74: =FALSE() -> FALSE | L74: =TRUE() -> TRUE | M74: PB08_NURTURE | N74: Email / in-app message | O74: Queue automated message (Automated Nurture). | P74: 30 | Q74: Any (repeat) order within 90 days. | R74: Order placed, unsubscribe, or 2 unanswered dormant messages (pause 6 months). | S74: Rising Tail accounts that cross the Core line re-route automatically. | T74: NO_FEB_GMV (Feb unconfirmed) | U74: Draft ready (not sent) | V74: NUR_RISING | W74: Hi {first_name}, Thanks for your recent orders with Fleek. Whenever you're planning your next buy, the app is the quickest way to browse bundles and make an offer where a price doesn't quite work. If you're looking for something specific, reply here and we'll help. Best, {sender_name} | AB74: Rising tail – early pattern | AC74: Recently Active | AD74: Returned Customer | AE74: =TRUE() -> TRUE | AF74: Not Eligible | AG74: Lumpy | AH74: N/A | AI74: No repeat send while the logged action is inside its cadence window. | AJ74: BASELINE | AK74: BASELINE | AL74: c3a72372035f
A75: ACC-067 | B75: P3 | C75: Tail | D75: 1759 | E75: 5. Cost-to-Serve / Low-Touch | F75: Service Model Review | G75: COST_TO_SERVE_ACTIVE | H75: Ready — Human | I75: Not Started | J75: Portfolio Lead | K75: =FALSE() -> FALSE | L75: =FALSE() -> FALSE | M75: PB07_SERVICE_MODEL_REVIEW | N75: Internal review (no customer contact) | O75: Portfolio Lead reviews account card and records a service decision. | P75: 14 | Q75: Decision logged; broker effort reduced where agreed without GMV loss. | R75: Decision recorded. | S75: None. | U75: None: internal-only review | X75: WHY NOW: Low-value broker-reliant account that is still buying. WHAT WE KNOW: - Tail, Broker-Reliant, Account Managed; £1,759 6m GMV; Reseller, United Kingdom; tenure 14 months. - Momentum: Growing (Sep-Nov £655 -> Dec-Feb £1,104); Recently Active (last GMV month: February); 9 orders over 5 month(s). - Dependency: High (broker reliance 66%; 6 AM-placed / 3 self-serve orders). - Engagement: 7 product views, 2 app days, 2 offer(s), 7 Fleek chats, 3 video requests; basket Mixed. WHAT TO DO: Review the card and decide: maintain support / move to lower-touch / automated nurture / revisit later. WHAT NOT TO DO: No customer message. No ROI claim (no AM cost data). SUCCESS: Decision logged; broker effort reduced where agreed without GMV loss. | AC75: Recently Active | AD75: Existing Customer | AE75: =FALSE() -> FALSE | AF75: Not Eligible | AG75: Regular | AH75: N/A | AI75: Decision stored; account not re-queued unless its NBA changes. | AJ75: BASELINE | AK75: BASELINE | AL75: 59d976603aa8
A76: ACC-068 | B76: P3 | C76: Tail | D76: 1706 | E76: 9. Long-Tail Automated Nurture | F76: Reinforce Successful Behaviour | G76: RISING_TAIL | H76: Ready — Automated | I76: Draft Ready | J76: Automation | K76: =FALSE() -> FALSE | L76: =TRUE() -> TRUE | M76: PB06_REINFORCE | N76: Email / in-app message | O76: Queue automated message (Reinforce Successful Behaviour). | P76: 30 | Q76: GMV run-rate maintained or higher, with GMV in each month of the next quarter. | R76: Account shows Recent Inactivity (playbook must not run) or momentum turns Declining. | S76: Recent Inactivity -> Verify check (human). | U76: Draft ready (not sent) | V76: REINFORCE | W76: Hi {first_name}, Thanks for being an active Fleek buyer. Just a quick note to keep an eye on the app for bundles and handpicked stock that fits your range, and to let you know we're here if there's anything specific you're trying to source. Reply any time and we'll help. Best, {sender_name} | AC76: Recently Active | AD76: Existing Customer | AE76: =TRUE() -> TRUE | AF76: Not Eligible | AG76: Regular | AH76: N/A | AI76: Suppressed if Recent Inactivity; otherwise no repeat inside 30 days. | AJ76: BASELINE | AK76: BASELINE | AL76: d388a5f593ab
A77: ACC-071 | B77: P3 | C77: Tail | D77: 1614 | E77: 5. Cost-to-Serve / Low-Touch | F77: Service Model Review | G77: COST_TO_SERVE_ACTIVE | H77: Ready — Human | I77: Not Started | J77: Portfolio Lead | K77: =FALSE() -> FALSE | L77: =FALSE() -> FALSE | M77: PB07_SERVICE_MODEL_REVIEW | N77: Internal review (no customer contact) | O77: Portfolio Lead reviews account card and records a service decision. | P77: 14 | Q77: Decision logged; broker effort reduced where agreed without GMV loss. | R77: Decision recorded. | S77: None. | T77: H2_SINGLE_MONTH_SPIKE | U77: None: internal-only review | X77: WHY NOW: Low-value broker-reliant account that is still buying. WHAT WE KNOW: - Tail, Broker-Reliant, Account Managed; £1,614 6m GMV; Reseller, Ireland; tenure 12 months. - Momentum: Growing (Sep-Nov £68 -> Dec-Feb £1,547); Recently Active (last GMV month: February); 6 orders over 3 month(s). - Dependency: High (broker reliance 73%; 4 AM-placed / 2 self-serve orders). - Engagement: 3 product views, 6 app days, 1 offer(s), 3 Fleek chats, 0 video requests; basket Bundle-only. - Warnings: H2_SINGLE_MONTH_SPIKE. WHAT TO DO: Review the card and decide: maintain support / move to lower-touch / automated nurture / revisit later. WHAT NOT TO DO: No customer message. No ROI claim (no AM cost data). SUCCESS: Decision logged; broker effort reduced where agreed without GMV loss. | AC77: Recently Active | AD77: Existing Customer | AE77: =FALSE() -> FALSE | AF77: Not Eligible | AG77: Regular | AH77: N/A | AI77: Decision stored; account not re-queued unless its NBA changes. | AJ77: BASELINE | AK77: BASELINE | AL77: 6cd01173727a
A78: ACC-074 | B78: P3 | C78: Tail | D78: 1448 | E78: 5. Cost-to-Serve / Low-Touch | F78: Service Model Review | G78: COST_TO_SERVE_ACTIVE | H78: Ready — Human | I78: Not Started | J78: Portfolio Lead | K78: =FALSE() -> FALSE | L78: =FALSE() -> FALSE | M78: PB07_SERVICE_MODEL_REVIEW | N78: Internal review (no customer contact) | O78: Portfolio Lead reviews account card and records a service decision. | P78: 14 | Q78: Decision logged; broker effort reduced where agreed without GMV loss. | R78: Decision recorded. | S78: None. | T78: MATERIAL_BROKER_INCONSISTENCY; NO_FEB_GMV (Feb unconfirmed); LOW_CONFIDENCE | U78: None: internal-only review | X78: WHY NOW: Low-value broker-reliant account that is still buying. WHAT WE KNOW: - Tail, Broker-Reliant, Account Managed; £1,448 6m GMV; Reseller, France; tenure 10 months. - Momentum: H2 Active / No H1 GMV; Recently Active (last GMV month: January); 2 orders over 1 month(s). - Dependency: High (broker reliance 70%; 1 AM-placed / 1 self-serve orders). - Engagement: 5 product views, 8 app days, 0 offer(s), 52 Fleek chats, 0 video requests; basket Handpick-only. - Warnings: MATERIAL_BROKER_INCONSISTENCY; NO_FEB_GMV (Feb unconfirmed); LOW_CONFIDENCE. WHAT TO DO: Review the card and decide: maintain support / move to lower-touch / automated nurture / revisit later. WHAT NOT TO DO: No customer message. No ROI claim (no AM cost data). SUCCESS: Decision logged; broker effort reduced where agreed without GMV loss. | AC78: Recently Active | AD78: Returned Customer | AE78: =FALSE() -> FALSE | AF78: Not Eligible | AG78: Lumpy | AH78: N/A | AI78: Decision stored; account not re-queued unless its NBA changes. | AJ78: BASELINE | AK78: BASELINE | AL78: 0fab81c98c28
A79: ACC-075 | B79: P3 | C79: Tail | D79: 1422 | E79: 5. Cost-to-Serve / Low-Touch | F79: Service Model Review | G79: COST_TO_SERVE_ACTIVE | H79: Ready — Human | I79: Not Started | J79: Portfolio Lead | K79: =FALSE() -> FALSE | L79: =FALSE() -> FALSE | M79: PB07_SERVICE_MODEL_REVIEW | N79: Internal review (no customer contact) | O79: Portfolio Lead reviews account card and records a service decision. | P79: 14 | Q79: Decision logged; broker effort reduced where agreed without GMV loss. | R79: Decision recorded. | S79: None. | T79: H2_SINGLE_MONTH_SPIKE; NO_FEB_GMV (Feb unconfirmed) | U79: None: internal-only review | X79: WHY NOW: Low-value broker-reliant account that is still buying. WHAT WE KNOW: - Tail, Broker-Reliant, Account Managed; £1,422 6m GMV; Reseller, United Kingdom; tenure 14 months. - Momentum: Stable (Sep-Nov £690 -> Dec-Feb £731); Recently Active (last GMV month: January); 3 orders over 3 month(s). - Dependency: High (broker reliance 79%; 2 AM-placed / 1 self-serve orders). - Engagement: 13 product views, 1 app days, 2 offer(s), 8 Fleek chats, 0 video requests; basket Bundle-only. - Warnings: H2_SINGLE_MONTH_SPIKE; NO_FEB_GMV (Feb unconfirmed). WHAT TO DO: Review the card and decide: maintain support / move to lower-touch / automated nurture / revisit later. WHAT NOT TO DO: No customer message. No ROI claim (no AM cost data). SUCCESS: Decision logged; broker effort reduced where agreed without GMV loss. | AC79: Recently Active | AD79: Existing Customer | AE79: =FALSE() -> FALSE | AF79: Not Eligible | AG79: Lumpy | AH79: N/A | AI79: Decision stored; account not re-queued unless its NBA changes. | AJ79: BASELINE | AK79: BASELINE | AL79: 5e51c9a1ed5c
A80: ACC-077 | B80: P3 | C80: Tail | D80: 1401 | E80: 5. Cost-to-Serve / Low-Touch | F80: Service Model Review | G80: COST_TO_SERVE_ACTIVE | H80: Ready — Human | I80: Not Started | J80: Portfolio Lead | K80: =FALSE() -> FALSE | L80: =FALSE() -> FALSE | M80: PB07_SERVICE_MODEL_REVIEW | N80: Internal review (no customer contact) | O80: Portfolio Lead reviews account card and records a service decision. | P80: 14 | Q80: Decision logged; broker effort reduced where agreed without GMV loss. | R80: Decision recorded. | S80: None. | T80: FEB_SENSITIVE; H2_SINGLE_MONTH_SPIKE | U80: None: internal-only review | X80: WHY NOW: Low-value broker-reliant account that is still buying. WHAT WE KNOW: - Tail, Broker-Reliant, Account Managed; £1,401 6m GMV; Reseller, United Kingdom; tenure 14 months. - Momentum: Declining (Sep-Nov £1,130 -> Dec-Feb £272); Recently Active (last GMV month: February); 5 orders over 3 month(s). - Dependency: High (broker reliance 81%; 4 AM-placed / 1 self-serve orders). - Engagement: 10 product views, 4 app days, 1 offer(s), 6 Fleek chats, 0 video requests; basket Mixed. - Warnings: FEB_SENSITIVE; H2_SINGLE_MONTH_SPIKE. WHAT TO DO: Review the card and decide: maintain support / move to lower-touch / automated nurture / revisit later. WHAT NOT TO DO: No customer message. No ROI claim (no AM cost data). SUCCESS: Decision logged; broker effort reduced where agreed without GMV loss. | AC80: Recently Active | AD80: Existing Customer | AE80: =FALSE() -> FALSE | AF80: Not Eligible | AG80: Regular | AH80: N/A | AI80: Decision stored; account not re-queued unless its NBA changes. | AJ80: BASELINE | AK80: BASELINE | AL80: 4c8d2cf7f6c3
A81: ACC-078 | B81: P3 | C81: Tail | D81: 1366 | E81: 9. Long-Tail Automated Nurture | F81: Automated Nurture | G81: LONG_TAIL_STANDARD | H81: Human Review Required | I81: Awaiting Human Review | J81: Portfolio Lead | K81: =FALSE() -> FALSE | L81: =FALSE() -> FALSE | M81: PB08_NURTURE | N81: Email / in-app message | O81: Verify order-channel data; then release or re-route the automated message. | P81: 30 | Q81: Any (repeat) order within 90 days. | R81: Order placed, unsubscribe, or 2 unanswered dormant messages (pause 6 months). | S81: Rising Tail accounts that cross the Core line re-route automatically. | T81: MATERIAL_BROKER_INCONSISTENCY (segment would change); H2_SINGLE_MONTH_SPIKE | U81: Withheld until human review is complete | X81: WHY NOW: Low-value, low-dependency account. WHAT WE KNOW: - Tail, AM-Owned / Self-Serving, Account Managed; £1,366 6m GMV; Reseller, France; tenure 16 months. - Momentum: Stable (Sep-Nov £662 -> Dec-Feb £704); Recent Inactivity (last GMV month: December); 4 orders over 2 month(s). - Dependency: Low (broker reliance 16%; 1 AM-placed / 3 self-serve orders). - Engagement: 24 product views, 10 app days, 0 offer(s), 7 Fleek chats, 0 video requests; basket Handpick-only. - Warnings: MATERIAL_BROKER_INCONSISTENCY (segment would change); H2_SINGLE_MONTH_SPIKE. WHAT TO DO: Order counts imply a different broker reliance than the provided figure, which would move this account to 5. Cost-to-Serve / Low-Touch. Verify order-channel data, then release or re-route the automated action. WHAT NOT TO DO: Do not release the automated message until verified. SUCCESS: Any (repeat) order within 90 days. | AB81: Light-touch repeat buyer | AC81: Recent Inactivity | AD81: Existing Customer | AE81: =FALSE() -> FALSE | AF81: Not Eligible | AG81: Lumpy | AH81: N/A | AI81: No repeat send while the logged action is inside its cadence window. | AJ81: BASELINE | AK81: BASELINE | AL81: 6f3017b032a8
A82: ACC-080 | B82: P3 | C82: Tail | D82: 1342 | E82: 5. Cost-to-Serve / Low-Touch | F82: Service Model Review | G82: COST_TO_SERVE_ACTIVE | H82: Ready — Human | I82: Not Started | J82: Portfolio Lead | K82: =FALSE() -> FALSE | L82: =FALSE() -> FALSE | M82: PB07_SERVICE_MODEL_REVIEW | N82: Internal review (no customer contact) | O82: Portfolio Lead reviews account card and records a service decision. | P82: 14 | Q82: Decision logged; broker effort reduced where agreed without GMV loss. | R82: Decision recorded. | S82: None. | U82: None: internal-only review | X82: WHY NOW: Low-value broker-reliant account that is still buying. WHAT WE KNOW: - Tail, Broker-Reliant, Account Managed; £1,342 6m GMV; Reseller, United Kingdom; tenure 10 months. - Momentum: H2 Active / No H1 GMV; Recently Active (last GMV month: February); 7 orders over 2 month(s). - Dependency: High (broker reliance 58%; 4 AM-placed / 3 self-serve orders). - Engagement: 13 product views, 3 app days, 1 offer(s), 11 Fleek chats, 1 video requests; basket Mixed. WHAT TO DO: Review the card and decide: maintain support / move to lower-touch / automated nurture / revisit later. WHAT NOT TO DO: No customer message. No ROI claim (no AM cost data). SUCCESS: Decision logged; broker effort reduced where agreed without GMV loss. | AC82: Recently Active | AD82: Returned Customer | AE82: =FALSE() -> FALSE | AF82: Not Eligible | AG82: Lumpy | AH82: N/A | AI82: Decision stored; account not re-queued unless its NBA changes. | AJ82: BASELINE | AK82: BASELINE | AL82: 71d07324867c
A83: ACC-083 | B83: P3 | C83: Tail | D83: 1217 | E83: 9. Long-Tail Automated Nurture | F83: Reinforce Successful Behaviour | G83: RISING_TAIL | H83: Ready — Automated | I83: Draft Ready | J83: Automation | K83: =FALSE() -> FALSE | L83: =TRUE() -> TRUE | M83: PB06_REINFORCE | N83: Email / in-app message | O83: Queue automated message (Reinforce Successful Behaviour). | P83: 30 | Q83: GMV run-rate maintained or higher, with GMV in each month of the next quarter. | R83: Account shows Recent Inactivity (playbook must not run) or momentum turns Declining. | S83: Recent Inactivity -> Verify check (human). | U83: Draft ready (not sent) | V83: REINFORCE | W83: Hi {first_name}, Thanks for being an active Fleek buyer. Just a quick note to keep an eye on the app for bundles that fits your range, and to let you know we're here if there's anything specific you're trying to source. Reply any time and we'll help. Best, {sender_name} | Y83: Range Expansion Test — trial handpick | Z83: Treatment | AA83: Hi {first_name}, Would you like to explore another way of sourcing stock? Alongside the bundles you usually buy, Fleek also offers handpicked stock, which you can browse in the app. It's there if you ever want to try it; if you have any questions, just reply to this message. Best, {sender_name} | AC83: Recently Active | AD83: Existing Customer | AE83: =TRUE() -> TRUE | AF83: Not Eligible | AG83: Regular | AH83: N/A | AI83: Suppressed if Recent Inactivity; otherwise no repeat inside 30 days. | AJ83: BASELINE | AK83: BASELINE | AL83: aa8993285b83
A84: ACC-085 | B84: P3 | C84: Tail | D84: 1166 | E84: 9. Long-Tail Automated Nurture | F84: Reinforce Successful Behaviour | G84: RISING_TAIL | H84: Ready — Automated | I84: Draft Ready | J84: Automation | K84: =FALSE() -> FALSE | L84: =TRUE() -> TRUE | M84: PB06_REINFORCE | N84: Email / in-app message | O84: Queue automated message (Reinforce Successful Behaviour). | P84: 30 | Q84: GMV run-rate maintained or higher, with GMV in each month of the next quarter. | R84: Account shows Recent Inactivity (playbook must not run) or momentum turns Declining. | S84: Recent Inactivity -> Verify check (human). | U84: Draft ready (not sent) | V84: REINFORCE | W84: Hi {first_name}, Thanks for being an active Fleek buyer. Just a quick note to keep an eye on the app for bundles that fits your range, and to let you know we're here if there's anything specific you're trying to source. Reply any time and we'll help. Best, {sender_name} | Y84: Range Expansion Test — trial handpick | Z84: Treatment | AA84: Hi {first_name}, Would you like to explore another way of sourcing stock? Alongside the bundles you usually buy, Fleek also offers handpicked stock, which you can browse in the app. It's there if you ever want to try it; if you have any questions, just reply to this message. Best, {sender_name} | AC84: Recently Active | AD84: Existing Customer | AE84: =TRUE() -> TRUE | AF84: Not Eligible | AG84: Lumpy | AH84: N/A | AI84: Suppressed if Recent Inactivity; otherwise no repeat inside 30 days. | AJ84: BASELINE | AK84: BASELINE | AL84: f2b94879059a
A85: ACC-219 | B85: P3 | C85: Tail | D85: 1166 | E85: 9. Long-Tail Automated Nurture | F85: Discovery-to-Offer Enablement | G85: BROWSING_LOW_OFFERS | H85: Ready — Automated | I85: Draft Ready | J85: Automation | K85: =FALSE() -> FALSE | L85: =FALSE() -> FALSE | M85: PB05_DISCOVERY_TO_OFFER | N85: Email / in-app message | O85: Queue automated message (Discovery-to-Offer Enablement). | P85: 14 | Q85: 3+ offers within 90 days and ideally an order afterwards (association only - no offer-acceptance data). | R85: Offers reach 3, or two messages sent, or account becomes inactive/declining. | S85: None (automated). Re-routes automatically if momentum turns Declining/Lapsed. | U85: Draft ready (not sent) | V85: DTO | W85: Hi {first_name}, If you spot an item you like on Fleek but the price doesn't quite work for you, you can use Make an Offer directly from the product page to propose your own price. It's a simple way to negotiate on stock you're already looking at, and you stay in control of what you pay. Best, {sender_name} | AC85: Recently Active | AD85: New Customer | AE85: =TRUE() -> TRUE | AF85: Not Eligible | AG85: Regular | AH85: N/A | AI85: No re-send while the action is already logged for this NBA; eligible again only after the NBA changes. | AJ85: BASELINE | AK85: BASELINE | AL85: 9001107dfa80
A86: ACC-086 | B86: P3 | C86: Tail | D86: 1153 | E86: 9. Long-Tail Automated Nurture | F86: Automated Nurture | G86: RISING_TAIL_EARLY | H86: Ready — Automated | I86: Draft Ready | J86: Automation | K86: =FALSE() -> FALSE | L86: =TRUE() -> TRUE | M86: PB08_NURTURE | N86: Email / in-app message | O86: Queue automated message (Automated Nurture). | P86: 30 | Q86: Any (repeat) order within 90 days. | R86: Order placed, unsubscribe, or 2 unanswered dormant messages (pause 6 months). | S86: Rising Tail accounts that cross the Core line re-route automatically. | T86: FEB_SENSITIVE; H2_SINGLE_MONTH_SPIKE | U86: Draft ready (not sent) | V86: NUR_RISING | W86: Hi {first_name}, Thanks for your recent orders with Fleek. Whenever you're planning your next buy, the app is the quickest way to browse bundles and handpicked stock and make an offer where a price doesn't quite work. If you're looking for something specific, reply here and we'll help. Best, {sender_name} | AB86: Rising tail – early pattern | AC86: Recently Active | AD86: Existing Customer | AE86: =TRUE() -> TRUE | AF86: Not Eligible | AG86: Lumpy | AH86: N/A | AI86: No repeat send while the logged action is inside its cadence window. | AJ86: BASELINE | AK86: BASELINE | AL86: 51560fabe901
A87: ACC-104 | B87: P3 | C87: Tail | D87: 718 | E87: 5. Cost-to-Serve / Low-Touch | F87: Service Model Review | G87: COST_TO_SERVE_ACTIVE | H87: Ready — Human | I87: Not Started | J87: Portfolio Lead | K87: =FALSE() -> FALSE | L87: =FALSE() -> FALSE | M87: PB07_SERVICE_MODEL_REVIEW | N87: Internal review (no customer contact) | O87: Portfolio Lead reviews account card and records a service decision. | P87: 14 | Q87: Decision logged; broker effort reduced where agreed without GMV loss. | R87: Decision recorded. | S87: None. | T87: NO_FEB_GMV (Feb unconfirmed); LOW_CONFIDENCE | U87: None: internal-only review | X87: WHY NOW: Low-value broker-reliant account that is still buying. WHAT WE KNOW: - Tail, Broker-Reliant, Account Managed; £718 6m GMV; Reseller, France; tenure 18 months. - Momentum: Stable (Sep-Nov £383 -> Dec-Feb £335); Recently Active (last GMV month: January); 2 orders over 2 month(s). - Dependency: Medium (broker reliance 53%; 1 AM-placed / 1 self-serve orders). - Engagement: 12 product views, 3 app days, 2 offer(s), 25 Fleek chats, 0 video requests; basket Bundle-only. - Warnings: NO_FEB_GMV (Feb unconfirmed); LOW_CONFIDENCE. WHAT TO DO: Review the card and decide: maintain support / move to lower-touch / automated nurture / revisit later. WHAT NOT TO DO: No customer message. No ROI claim (no AM cost data). SUCCESS: Decision logged; broker effort reduced where agreed without GMV loss. | AC87: Recently Active | AD87: Existing Customer | AE87: =FALSE() -> FALSE | AF87: Not Eligible | AG87: Lumpy | AH87: N/A | AI87: Decision stored; account not re-queued unless its NBA changes. | AJ87: BASELINE | AK87: BASELINE | AL87: 8b1c267f7bdf
A88: ACC-111 | B88: P3 | C88: Tail | D88: 592 | E88: 9. Long-Tail Automated Nurture | F88: Discovery-to-Offer Enablement | G88: BROWSING_LOW_OFFERS | H88: Human Review Required | I88: Awaiting Human Review | J88: Portfolio Lead | K88: =FALSE() -> FALSE | L88: =FALSE() -> FALSE | M88: PB05_DISCOVERY_TO_OFFER | N88: Email / in-app message | O88: Verify order-channel data; then release or re-route the automated message. | P88: 14 | Q88: 3+ offers within 90 days and ideally an order afterwards (association only - no offer-acceptance data). | R88: Offers reach 3, or two messages sent, or account becomes inactive/declining. | S88: None (automated). Re-routes automatically if momentum turns Declining/Lapsed. | T88: MATERIAL_BROKER_INCONSISTENCY (segment would change); NO_FEB_GMV (Feb unconfirmed) | U88: Withheld until human review is complete | X88: WHY NOW: Independent browser making few offers. WHAT WE KNOW: - Tail, AM-Owned / Self-Serving, Account Managed; £592 6m GMV; Reseller, Germany; tenure 14 months. - Momentum: Stable (Sep-Nov £288 -> Dec-Feb £304); Recently Active (last GMV month: January); 4 orders over 4 month(s). - Dependency: Low (broker reliance 19%; 1 AM-placed / 3 self-serve orders). - Engagement: 153 product views, 29 app days, 0 offer(s), 34 Fleek chats, 0 video requests; basket Handpick-only. - Warnings: MATERIAL_BROKER_INCONSISTENCY (segment would change); NO_FEB_GMV (Feb unconfirmed). WHAT TO DO: Order counts imply a different broker reliance than the provided figure, which would move this account to 5. Cost-to-Serve / Low-Touch. Verify order-channel data, then release or re-route the automated action. WHAT NOT TO DO: Do not release the automated message until verified. SUCCESS: 3+ offers within 90 days and ideally an order afterwards (association only - no offer-acceptance data). | AC88: Recently Active | AD88: Existing Customer | AE88: =FALSE() -> FALSE | AF88: Not Eligible | AG88: Lumpy | AH88: N/A | AI88: No re-send while the action is already logged for this NBA; eligible again only after the NBA changes. | AJ88: BASELINE | AK88: BASELINE | AL88: 99ad3fc1cdb9
A89: ACC-256 | B89: P3 | C89: Tail | D89: 263 | E89: 9. Long-Tail Automated Nurture | F89: Discovery-to-Offer Enablement | G89: BROWSING_LOW_OFFERS | H89: Ready — Automated | I89: Draft Ready | J89: Automation | K89: =FALSE() -> FALSE | L89: =FALSE() -> FALSE | M89: PB05_DISCOVERY_TO_OFFER | N89: Email / in-app message | O89: Queue automated message (Discovery-to-Offer Enablement). | P89: 14 | Q89: 3+ offers within 90 days and ideally an order afterwards (association only - no offer-acceptance data). | R89: Offers reach 3, or two messages sent, or account becomes inactive/declining. | S89: None (automated). Re-routes automatically if momentum turns Declining/Lapsed. | T89: LOW_CONFIDENCE | U89: Draft ready (not sent) | V89: DTO | W89: Hi {first_name}, If you spot an item you like on Fleek but the price doesn't quite work for you, you can use Make an Offer directly from the product page to propose your own price. It's a simple way to negotiate on stock you're already looking at, and you stay in control of what you pay. Best, {sender_name} | AC89: Recently Active | AD89: New Customer | AE89: =FALSE() -> FALSE | AF89: Not Eligible | AG89: Lumpy | AH89: N/A | AI89: No re-send while the action is already logged for this NBA; eligible again only after the NBA changes. | AJ89: BASELINE | AK89: BASELINE | AL89: a18f3158b1a0
A90: ACC-160 | B90: P3 | C90: Tail | D90: 249 | E90: 9. Long-Tail Automated Nurture | F90: Discovery-to-Offer Enablement | G90: BROWSING_LOW_OFFERS | H90: Ready — Automated | I90: Draft Ready | J90: Automation | K90: =FALSE() -> FALSE | L90: =TRUE() -> TRUE | M90: PB05_DISCOVERY_TO_OFFER | N90: Email / in-app message | O90: Queue automated message (Discovery-to-Offer Enablement). | P90: 14 | Q90: 3+ offers within 90 days and ideally an order afterwards (association only - no offer-acceptance data). | R90: Offers reach 3, or two messages sent, or account becomes inactive/declining. | S90: None (automated). Re-routes automatically if momentum turns Declining/Lapsed. | T90: NO_FEB_GMV (Feb unconfirmed); LOW_CONFIDENCE | U90: Draft ready (not sent) | V90: DTO | W90: Hi {first_name}, If you spot an item you like on Fleek but the price doesn't quite work for you, you can use Make an Offer directly from the product page to propose your own price. It's a simple way to negotiate on stock you're already looking at, and you stay in control of what you pay. Best, {sender_name} | AC90: Recently Active | AD90: Existing Customer | AE90: =FALSE() -> FALSE | AF90: Not Eligible | AG90: Lumpy | AH90: N/A | AI90: No re-send while the action is already logged for this NBA; eligible again only after the NBA changes. | AJ90: BASELINE | AK90: BASELINE | AL90: 597ead36ba57
A91: ACC-063 | B91: P4 | C91: Tail | D91: 1963 | E91: 9. Long-Tail Automated Nurture | F91: Automated Nurture | G91: LONG_TAIL_STANDARD | H91: Ready — Automated | I91: Draft Ready | J91: Automation | K91: =FALSE() -> FALSE | L91: =TRUE() -> TRUE | M91: PB08_NURTURE | N91: Email / in-app message | O91: Queue automated message (Automated Nurture). | P91: 60 | Q91: Any (repeat) order within 90 days. | R91: Order placed, unsubscribe, or 2 unanswered dormant messages (pause 6 months). | S91: Rising Tail accounts that cross the Core line re-route automatically. | T91: LOW_CONFIDENCE | U91: Draft ready (not sent) | V91: NUR_DORMANT | W91: Hi {first_name}, Whenever you're planning your next stock buy, you can browse bundles on the Fleek app at any time. If you're looking for something specific, reply to this message and we'll do our best to help you find it. No pressure, just a friendly reminder that we're here. Best, {sender_name} | AB91: Dormant | AC91: No Meaningful History | AD91: Existing Customer | AE91: =FALSE() -> FALSE | AF91: Not Eligible | AG91: Lumpy | AH91: N/A | AI91: No repeat send while the logged action is inside its cadence window. | AJ91: BASELINE | AK91: BASELINE | AL91: ac28d5041fff
A92: ACC-066 | B92: P4 | C92: Tail | D92: 1791 | E92: 9. Long-Tail Automated Nurture | F92: Automated Nurture | G92: LONG_TAIL_STANDARD | H92: Ready — Automated | I92: Draft Ready | J92: Automation | K92: =FALSE() -> FALSE | L92: =TRUE() -> TRUE | M92: PB08_NURTURE | N92: Email / in-app message | O92: Queue automated message (Automated Nurture). | P92: 60 | Q92: Any (repeat) order within 90 days. | R92: Order placed, unsubscribe, or 2 unanswered dormant messages (pause 6 months). | S92: Rising Tail accounts that cross the Core line re-route automatically. | U92: Draft ready (not sent) | V92: NUR_DORMANT | W92: Hi {first_name}, Whenever you're planning your next stock buy, you can browse bundles and handpicked stock on the Fleek app at any time. If you're looking for something specific, reply to this message and we'll do our best to help you find it. No pressure, just a friendly reminder that we're here. Best, {sender_name} | AB92: Dormant | AC92: Recent Inactivity | AD92: Existing Customer | AE92: =FALSE() -> FALSE | AF92: Not Eligible | AG92: Lumpy | AH92: N/A | AI92: No repeat send while the logged action is inside its cadence window. | AJ92: BASELINE | AK92: BASELINE | AL92: f751494a0af2
A93: ACC-069 | B93: P4 | C93: Tail | D93: 1682 | E93: 9. Long-Tail Automated Nurture | F93: Automated Nurture | G93: LONG_TAIL_STANDARD | H93: Ready — Automated | I93: Draft Ready | J93: Automation | K93: =FALSE() -> FALSE | L93: =TRUE() -> TRUE | M93: PB08_NURTURE | N93: Email / in-app message | O93: Queue automated message (Automated Nurture). | P93: 30 | Q93: Any (repeat) order within 90 days. | R93: Order placed, unsubscribe, or 2 unanswered dormant messages (pause 6 months). | S93: Rising Tail accounts that cross the Core line re-route automatically. | U93: Draft ready (not sent) | V93: NUR_STANDARD | W93: Hi {first_name}, A quick reminder that you can browse bundles and handpicked stock on the Fleek app whenever you're planning your next buy, at a time that suits you. If there's something specific you're looking for, reply to this message and we'll do our best to help. Best, {sender_name} | AB93: Standard long tail | AC93: Recently Active | AD93: Existing Customer | AE93: =FALSE() -> FALSE | AF93: Not Eligible | AG93: Regular | AH93: N/A | AI93: No repeat send while the logged action is inside its cadence window. | AJ93: BASELINE | AK93: BASELINE | AL93: d5e8a6c32695
A94: ACC-070 | B94: P4 | C94: Tail | D94: 1671 | E94: 9. Long-Tail Automated Nurture | F94: Automated Nurture | G94: LONG_TAIL_STANDARD | H94: Ready — Automated | I94: Draft Ready | J94: Automation | K94: =FALSE() -> FALSE | L94: =TRUE() -> TRUE | M94: PB08_NURTURE | N94: Email / in-app message | O94: Queue automated message (Automated Nurture). | P94: 60 | Q94: Any (repeat) order within 90 days. | R94: Order placed, unsubscribe, or 2 unanswered dormant messages (pause 6 months). | S94: Rising Tail accounts that cross the Core line re-route automatically. | T94: LOW_CONFIDENCE | U94: Draft ready (not sent) | V94: NUR_DORMANT | W94: Hi {first_name}, Whenever you're planning your next stock buy, you can browse bundles on the Fleek app at any time. If you're looking for something specific, reply to this message and we'll do our best to help you find it. No pressure, just a friendly reminder that we're here. Best, {sender_name} | AB94: Dormant | AC94: No Meaningful History | AD94: Existing Customer | AE94: =FALSE() -> FALSE | AF94: Not Eligible | AG94: Lumpy | AH94: N/A | AI94: No repeat send while the logged action is inside its cadence window. | AJ94: BASELINE | AK94: BASELINE | AL94: 953b6127c446
A95: ACC-072 | B95: P4 | C95: Tail | D95: 1542 | E95: 9. Long-Tail Automated Nurture | F95: Automated Nurture | G95: LONG_TAIL_STANDARD | H95: Ready — Automated | I95: Draft Ready | J95: Automation | K95: =FALSE() -> FALSE | L95: =TRUE() -> TRUE | M95: PB08_NURTURE | N95: Email / in-app message | O95: Queue automated message (Automated Nurture). | P95: 30 | Q95: Any (repeat) order within 90 days. | R95: Order placed, unsubscribe, or 2 unanswered dormant messages (pause 6 months). | S95: Rising Tail accounts that cross the Core line re-route automatically. | T95: H2_SINGLE_MONTH_SPIKE; NO_FEB_GMV (Feb unconfirmed) | U95: Draft ready (not sent) | V95: NUR_STANDARD | W95: Hi {first_name}, A quick reminder that you can browse bundles and handpicked stock on the Fleek app whenever you're planning your next buy, at a time that suits you. If there's something specific you're looking for, reply to this message and we'll do our best to help. Best, {sender_name} | AB95: Standard long tail | AC95: Recently Active | AD95: Existing Customer | AE95: =FALSE() -> FALSE | AF95: Not Eligible | AG95: Regular | AH95: N/A | AI95: No repeat send while the logged action is inside its cadence window. | AJ95: BASELINE | AK95: BASELINE | AL95: 5ae2b2cde0f1
A96: ACC-073 | B96: P4 | C96: Tail | D96: 1501 | E96: 9. Long-Tail Automated Nurture | F96: Automated Nurture | G96: LONG_TAIL_STANDARD | H96: Ready — Automated | I96: Draft Ready | J96: Automation | K96: =FALSE() -> FALSE | L96: =TRUE() -> TRUE | M96: PB08_NURTURE | N96: Email / in-app message | O96: Queue automated message (Automated Nurture). | P96: 30 | Q96: Any (repeat) order within 90 days. | R96: Order placed, unsubscribe, or 2 unanswered dormant messages (pause 6 months). | S96: Rising Tail accounts that cross the Core line re-route automatically. | T96: LOW_CONFIDENCE | U96: Draft ready (not sent) | V96: NUR_RETURNED | W96: Hi {first_name}, Welcome back to Fleek, and thanks for your recent order. You can browse handpicked stock in the app whenever it suits you. If there's anything specific you're sourcing at the moment, reply to this message and we'll help point you in the right direction. Best, {sender_name} | AB96: Returned customer | AC96: No Meaningful History | AD96: Returned Customer | AE96: =FALSE() -> FALSE | AF96: Not Eligible | AG96: Lumpy | AH96: N/A | AI96: No repeat send while the logged action is inside its cadence window. | AJ96: BASELINE | AK96: BASELINE | AL96: f47f5f56f997
